[{"verse":1,"words":[{"t":"Περὶ","l":"περί","k":"ペリ","p":"prep","g":"〜について"},{"t":"μὲν","l":"μέν","k":"メン","p":"conj","g":"一方では"},{"t":"γὰρ","l":"γάρ","k":"ガル","p":"conj","g":"なぜなら"},{"t":"τῆς","l":"ὁ","k":"テース","p":"art","m":{"case":"属格","number":"単数","gender":"女性"},"g":"その"},{"t":"διακονίας","l":"διακονία","k":"ディアコニアス","p":"noun","m":{"case":"属格","number":"単数","gender":"女性"}},{"t":"τῆς","l":"ὁ","k":"テース","p":"art","m":{"case":"属格","number":"単数","gender":"女性"},"g":"その"},{"t":"εἰς","l":"εἰς","k":"エイス","p":"prep","g":"〜の中へ"},{"t":"τοὺς","l":"ὁ","k":"トウス","p":"art","m":{"case":"対格","number":"複数","gender":"男性"},"g":"その"},{"t":"ἁγίους","l":"ἅγιος","k":"ハギウース","p":"adj","m":{"case":"対格","number":"複数","gender":"男性"},"g":"聖なる"},{"t":"περισσόν","l":"περισσός","k":"ペリスソン","p":"adj","m":{"case":"主格","number":"単数","gender":"中性"}},{"t":"μοί","l":"ἐγώ","k":"モイ","p":"pers","m":{"case":"与格","number":"単数"},"g":"私"},{"t":"ἐστιν","l":"εἰμί","k":"エスティン","p":"verb","m":{"person":"3人称","tense":"現在","voice":"能動態","mood":"直説法"},"g":"〜である"},{"t":"τὸ","l":"ὁ","k":"ト","p":"art","m":{"case":"主格","number":"単数","gender":"中性"},"g":"その"},{"t":"γράφειν","l":"γράφω","k":"グラフェイン","p":"verb","m":{"tense":"現在","voice":"能動態","mood":"不定詞"},"g":"書く"},{"t":"ὑμῖν","l":"σύ","k":"フミン","p":"pers","m":{"case":"与格","number":"複数"},"g":"あなた"}]},{"verse":2,"words":[{"t":"οἶδα","l":"οἶδα","k":"オイダ","p":"verb","m":{"person":"1人称","voice":"能動態","mood":"直説法"},"g":"知る"},{"t":"γὰρ","l":"γάρ","k":"ガル","p":"conj","g":"なぜなら"},{"t":"τὴν","l":"ὁ","k":"テーン","p":"art","m":{"case":"対格","number":"単数","gender":"女性"},"g":"その"},{"t":"προθυμίαν","l":"προθυμία","k":"プロシュミアン","p":"noun","m":{"case":"対格","number":"単数","gender":"女性"}},{"t":"ὑμῶν","l":"σύ","k":"フモーン","p":"pers","m":{"case":"属格","number":"複数"},"g":"あなた"},{"t":"ἣν","l":"ὅς","k":"ヘーン","p":"rel","m":{"case":"対格","number":"単数","gender":"女性"},"g":"〜ところの"},{"t":"ὑπὲρ","l":"ὑπέρ","k":"フペル","p":"prep","g":"〜のために"},{"t":"ὑμῶν","l":"σύ","k":"フモーン","p":"pers","m":{"case":"属格","number":"複数"},"g":"あなた"},{"t":"καυχῶμαι","l":"καυχάομαι","k":"カウコーマイ","p":"verb","m":{"person":"1人称","tense":"現在","voice":"中動態","mood":"直説法"}},{"t":"Μακεδόσιν","l":"Μακεδών","k":"マケドシン","p":"noun","m":{"case":"与格","number":"複数","gender":"男性"}},{"t":"ὅτι","l":"ὅτι","k":"ホティ","p":"adv","g":"〜ということ"},{"t":"Ἀχαΐα","l":"Ἀχαΐα","k":"アカイア","p":"noun","m":{"case":"主格","number":"単数","gender":"女性"}},{"t":"παρεσκεύασται","l":"παρασκευάζω","k":"パレスケウアスタイ","p":"verb","m":{"person":"3人称","voice":"中動態","mood":"直説法"}},{"t":"ἀπὸ","l":"ἀπό","k":"アポ","p":"prep","g":"〜から"},{"t":"πέρυσι","l":"πέρυσι(ν)","k":"ペリュシン","p":"adv"},{"t":"καὶ","l":"καί","k":"カイ","p":"conj","g":"そして"},{"t":"⸀τὸ","l":"ὁ","k":"ト","p":"art","m":{"case":"主格","number":"単数","gender":"中性"},"g":"その"},{"t":"ὑμῶν","l":"σύ","k":"フモーン","p":"pers","m":{"case":"属格","number":"複数"},"g":"あなた"},{"t":"ζῆλος","l":"ζῆλος","k":"ゼーロス","p":"noun","m":{"case":"主格","number":"単数","gender":"中性"}},{"t":"ἠρέθισε","l":"ἐρεθίζω","k":"エーレシセン","p":"verb","m":{"person":"3人称","tense":"アオリスト","voice":"能動態","mood":"直説法"}},{"t":"τοὺς","l":"ὁ","k":"トウス","p":"art","m":{"case":"対格","number":"複数","gender":"男性"},"g":"その"},{"t":"πλείονας","l":"πολύς","k":"プレイオナス","p":"adj","m":{"case":"対格","number":"複数","gender":"男性","degree":"比較級"},"g":"多くの"}]},{"verse":3,"words":[{"t":"ἔπεμψα","l":"πέμπω","k":"エペムプサ","p":"verb","m":{"person":"1人称","tense":"アオリスト","voice":"能動態","mood":"直説法"},"g":"送る"},{"t":"δὲ","l":"δέ","k":"デ","p":"conj","g":"しかし"},{"t":"τοὺς","l":"ὁ","k":"トウス","p":"art","m":{"case":"対格","number":"複数","gender":"男性"},"g":"その"},{"t":"ἀδελφούς","l":"ἀδελφός","k":"アデルフォウス","p":"noun","m":{"case":"対格","number":"複数","gender":"男性"},"g":"兄弟"},{"t":"ἵνα","l":"ἵνα","k":"ヒナ","p":"conj","g":"〜するために"},{"t":"μὴ","l":"μή","k":"メー","p":"adv","g":"〜ない"},{"t":"τὸ","l":"ὁ","k":"ト","p":"art","m":{"case":"主格","number":"単数","gender":"中性"},"g":"その"},{"t":"καύχημα","l":"καύχημα","k":"カウケーマ","p":"noun","m":{"case":"主格","number":"単数","gender":"中性"}},{"t":"ἡμῶν","l":"ἐγώ","k":"ヘーモーン","p":"pers","m":{"case":"属格","number":"複数"},"g":"私"},{"t":"τὸ","l":"ὁ","k":"ト","p":"art","m":{"case":"主格","number":"単数","gender":"中性"},"g":"その"},{"t":"ὑπὲρ","l":"ὑπέρ","k":"フペル","p":"prep","g":"〜のために"},{"t":"ὑμῶν","l":"σύ","k":"フモーン","p":"pers","m":{"case":"属格","number":"複数"},"g":"あなた"},{"t":"κενωθῇ","l":"κενόω","k":"ケノーセー","p":"verb","m":{"person":"3人称","tense":"アオリスト","voice":"受動態","mood":"接続法"}},{"t":"ἐν","l":"ἐν","k":"エン","p":"prep","g":"〜の中に"},{"t":"τῷ","l":"ὁ","k":"トー","p":"art","m":{"case":"与格","number":"単数","gender":"中性"},"g":"その"},{"t":"μέρει","l":"μέρος","k":"メレイ","p":"noun","m":{"case":"与格","number":"単数","gender":"中性"}},{"t":"τούτῳ","l":"οὗτος","k":"トウトー","p":"dem","m":{"case":"与格","number":"単数","gender":"中性"},"g":"この"},{"t":"ἵνα","l":"ἵνα","k":"ヒナ","p":"conj","g":"〜するために"},{"t":"καθὼς","l":"καθώς","k":"カソース","p":"conj","g":"〜のように"},{"t":"ἔλεγον","l":"λέγω","k":"エレゴン","p":"verb","m":{"person":"1人称","tense":"未完了","voice":"能動態","mood":"直説法"},"g":"言う"},{"t":"παρεσκευασμένοι","l":"παρασκευάζω","k":"パレスケウアスメノイ","p":"verb","m":{"voice":"中動態","mood":"分詞","case":"主格","number":"複数","gender":"男性"}},{"t":"ἦτε","l":"εἰμί","k":"エーテ","p":"verb","m":{"person":"2人称","tense":"現在","voice":"能動態","mood":"接続法"},"g":"〜である"}]},{"verse":4,"words":[{"t":"μή","l":"μή","k":"メー","p":"conj","g":"〜ない"},{"t":"πως","l":"πώς","k":"ポース","p":"adv"},{"t":"ἐὰν","l":"ἐάν","k":"エアン","p":"conj","g":"もし〜なら"},{"t":"ἔλθωσιν","l":"ἔρχομαι","k":"エルソーシン","p":"verb","m":{"person":"3人称","tense":"アオリスト","voice":"能動態","mood":"接続法"},"g":"来る"},{"t":"σὺν","l":"σύν","k":"シュン","p":"prep","g":"〜と共に"},{"t":"ἐμοὶ","l":"ἐγώ","k":"エモイ","p":"pers","m":{"case":"与格","number":"単数"},"g":"私"},{"t":"Μακεδόνες","l":"Μακεδών","k":"マケドネス","p":"noun","m":{"case":"主格","number":"複数","gender":"男性"}},{"t":"καὶ","l":"καί","k":"カイ","p":"conj","g":"そして"},{"t":"εὕρωσιν","l":"εὑρίσκω","k":"エウローシン","p":"verb","m":{"person":"3人称","tense":"アオリスト","voice":"能動態","mood":"接続法"},"g":"見つける"},{"t":"ὑμᾶς","l":"σύ","k":"フマス","p":"pers","m":{"case":"対格","number":"複数"},"g":"あなた"},{"t":"ἀπαρασκευάστους","l":"ἀπαρασκεύαστος","k":"アパラスケウアストウス","p":"adj","m":{"case":"対格","number":"複数","gender":"男性"}},{"t":"καταισχυνθῶμεν","l":"καταισχύνω","k":"カタイスキュンソーメン","p":"verb","m":{"person":"1人称","tense":"アオリスト","voice":"受動態","mood":"接続法"}},{"t":"ἡμεῖς","l":"ἐγώ","k":"ヘーメイス","p":"pers","m":{"case":"主格","number":"複数"},"g":"私"},{"t":"ἵνα","l":"ἵνα","k":"ヒナ","p":"conj","g":"〜するために"},{"t":"μὴ","l":"μή","k":"メー","p":"adv","g":"〜ない"},{"t":"⸀λέγωμεν","l":"λέγω","k":"レゴーメン","p":"verb","m":{"person":"1人称","tense":"現在","voice":"能動態","mood":"接続法"},"g":"言う"},{"t":"ὑμεῖς","l":"σύ","k":"フメイス","p":"pers","m":{"case":"主格","number":"複数"},"g":"あなた"},{"t":"ἐν","l":"ἐν","k":"エン","p":"prep","g":"〜の中に"},{"t":"τῇ","l":"ὁ","k":"テー","p":"art","m":{"case":"与格","number":"単数","gender":"女性"},"g":"その"},{"t":"ὑποστάσει","l":"ὑπόστασις","k":"フポスタセイ","p":"noun","m":{"case":"与格","number":"単数","gender":"女性"}},{"t":"⸀ταύτῃ","l":"οὗτος","k":"タウテー","p":"dem","m":{"case":"与格","number":"単数","gender":"女性"},"g":"この"}]},{"verse":5,"words":[{"t":"ἀναγκαῖον","l":"ἀναγκαῖος","k":"アナンカイオン","p":"adj","m":{"case":"主格","number":"単数","gender":"中性"}},{"t":"οὖν","l":"οὖν","k":"ウーン","p":"conj","g":"それゆえ"},{"t":"ἡγησάμην","l":"ἡγέομαι","k":"ヘーゲーサメーン","p":"verb","m":{"person":"1人称","tense":"アオリスト","voice":"中動態","mood":"直説法"}},{"t":"παρακαλέσαι","l":"παρακαλέω","k":"パラカレサイ","p":"verb","m":{"tense":"アオリスト","voice":"能動態","mood":"不定詞"},"g":"励ます"},{"t":"τοὺς","l":"ὁ","k":"トウス","p":"art","m":{"case":"対格","number":"複数","gender":"男性"},"g":"その"},{"t":"ἀδελφοὺς","l":"ἀδελφός","k":"アデルフォウス","p":"noun","m":{"case":"対格","number":"複数","gender":"男性"},"g":"兄弟"},{"t":"ἵνα","l":"ἵνα","k":"ヒナ","p":"conj","g":"〜するために"},{"t":"προέλθωσιν","l":"προέρχομαι","k":"プロエルソーシン","p":"verb","m":{"person":"3人称","tense":"アオリスト","voice":"能動態","mood":"接続法"}},{"t":"⸀εἰς","l":"εἰς","k":"エイス","p":"prep","g":"〜の中へ"},{"t":"ὑμᾶς","l":"σύ","k":"フマス","p":"pers","m":{"case":"対格","number":"複数"},"g":"あなた"},{"t":"καὶ","l":"καί","k":"カイ","p":"conj","g":"そして"},{"t":"προκαταρτίσωσι","l":"προκαταρτίζω","k":"プロカタルティソーシン","p":"verb","m":{"person":"3人称","tense":"アオリスト","voice":"能動態","mood":"接続法"}},{"t":"τὴν","l":"ὁ","k":"テーン","p":"art","m":{"case":"対格","number":"単数","gender":"女性"},"g":"その"},{"t":"⸀προεπηγγελμένην","l":"προεπαγγέλλομαι","k":"プロエペーンゲルメネーン","p":"verb","m":{"voice":"中動態","mood":"分詞","case":"対格","number":"単数","gender":"女性"}},{"t":"εὐλογίαν","l":"εὐλογία","k":"エウロギアン","p":"noun","m":{"case":"対格","number":"単数","gender":"女性"}},{"t":"ὑμῶν","l":"σύ","k":"フモーン","p":"pers","m":{"case":"属格","number":"複数"},"g":"あなた"},{"t":"ταύτην","l":"οὗτος","k":"タウテーン","p":"dem","m":{"case":"対格","number":"単数","gender":"女性"},"g":"この"},{"t":"ἑτοίμην","l":"ἕτοιμος","k":"ヘトイメーン","p":"adj","m":{"case":"対格","number":"単数","gender":"女性"},"g":"準備ができた"},{"t":"εἶναι","l":"εἰμί","k":"エイナイ","p":"verb","m":{"tense":"現在","voice":"能動態","mood":"不定詞"},"g":"〜である"},{"t":"οὕτως","l":"οὕτω(ς)","k":"ウートース","p":"adv"},{"t":"ὡς","l":"ὡς","k":"ホース","p":"conj","g":"〜のように"},{"t":"εὐλογίαν","l":"εὐλογία","k":"エウロギアン","p":"noun","m":{"case":"対格","number":"単数","gender":"女性"}},{"t":"καὶ","l":"καί","k":"カイ","p":"conj","g":"そして"},{"t":"μὴ","l":"μή","k":"メー","p":"adv","g":"〜ない"},{"t":"ὡς","l":"ὡς","k":"ホース","p":"conj","g":"〜のように"},{"t":"πλεονεξίαν","l":"πλεονεξία","k":"プレオネクシアン","p":"noun","m":{"case":"対格","number":"単数","gender":"女性"}}]},{"verse":6,"words":[{"t":"Τοῦτο","l":"οὗτος","k":"トウト","p":"dem","m":{"case":"対格","number":"単数","gender":"中性"},"g":"この"},{"t":"δέ","l":"δέ","k":"デ","p":"conj","g":"しかし"},{"t":"ὁ","l":"ὁ","k":"ホ","p":"art","m":{"case":"主格","number":"単数","gender":"男性"},"g":"その"},{"t":"σπείρων","l":"σπείρω","k":"スペイローン","p":"verb","m":{"tense":"現在","voice":"能動態","mood":"分詞","case":"主格","number":"単数","gender":"男性"}},{"t":"φειδομένως","l":"φειδομένως","k":"フェイドメノース","p":"adv"},{"t":"φειδομένως","l":"φειδομένως","k":"フェイドメノース","p":"adv"},{"t":"καὶ","l":"καί","k":"カイ","p":"adv","g":"そして"},{"t":"θερίσει","l":"θερίζω","k":"セリセイ","p":"verb","m":{"person":"3人称","tense":"未来","voice":"能動態","mood":"直説法"}},{"t":"καὶ","l":"καί","k":"カイ","p":"conj","g":"そして"},{"t":"ὁ","l":"ὁ","k":"ホ","p":"art","m":{"case":"主格","number":"単数","gender":"男性"},"g":"その"},{"t":"σπείρων","l":"σπείρω","k":"スペイローン","p":"verb","m":{"tense":"現在","voice":"能動態","mood":"分詞","case":"主格","number":"単数","gender":"男性"}},{"t":"ἐπ’","l":"ἐπί","k":"エピ","p":"prep","g":"〜の上に"},{"t":"εὐλογίαις","l":"εὐλογία","k":"エウロギアイス","p":"noun","m":{"case":"与格","number":"複数","gender":"女性"}},{"t":"ἐπ’","l":"ἐπί","k":"エピ","p":"prep","g":"〜の上に"},{"t":"εὐλογίαις","l":"εὐλογία","k":"エウロギアイス","p":"noun","m":{"case":"与格","number":"複数","gender":"女性"}},{"t":"καὶ","l":"καί","k":"カイ","p":"adv","g":"そして"},{"t":"θερίσει","l":"θερίζω","k":"セリセイ","p":"verb","m":{"person":"3人称","tense":"未来","voice":"能動態","mood":"直説法"}}]},{"verse":7,"words":[{"t":"ἕκαστος","l":"ἕκαστος","k":"ヘカストス","p":"adj","m":{"case":"主格","number":"単数","gender":"男性"},"g":"それぞれの"},{"t":"καθὼς","l":"καθώς","k":"カソース","p":"conj","g":"〜のように"},{"t":"⸀προῄρηται","l":"προαιρέομαι","k":"プロエーレータイ","p":"verb","m":{"person":"3人称","voice":"中動態","mood":"直説法"}},{"t":"τῇ","l":"ὁ","k":"テー","p":"art","m":{"case":"与格","number":"単数","gender":"女性"},"g":"その"},{"t":"καρδίᾳ","l":"καρδία","k":"カルディア","p":"noun","m":{"case":"与格","number":"単数","gender":"女性"},"g":"心"},{"t":"μὴ","l":"μή","k":"メー","p":"adv","g":"〜ない"},{"t":"ἐκ","l":"ἐκ","k":"エク","p":"prep","g":"〜から"},{"t":"λύπης","l":"λύπη","k":"リュペース","p":"noun","m":{"case":"属格","number":"単数","gender":"女性"}},{"t":"ἢ","l":"ἤ","k":"エー","p":"conj","g":"または"},{"t":"ἐξ","l":"ἐκ","k":"エク","p":"prep","g":"〜から"},{"t":"ἀνάγκης","l":"ἀνάγκη","k":"アナンケース","p":"noun","m":{"case":"属格","number":"単数","gender":"女性"}},{"t":"ἱλαρὸν","l":"ἱλαρός","k":"ヒラロン","p":"adj","m":{"case":"対格","number":"単数","gender":"男性"}},{"t":"γὰρ","l":"γάρ","k":"ガル","p":"conj","g":"なぜなら"},{"t":"δότην","l":"δότης","k":"ドテーン","p":"noun","m":{"case":"対格","number":"単数","gender":"男性"}},{"t":"ἀγαπᾷ","l":"ἀγαπάω","k":"アガパ","p":"verb","m":{"person":"3人称","tense":"現在","voice":"能動態","mood":"直説法"},"g":"愛する"},{"t":"ὁ","l":"ὁ","k":"ホ","p":"art","m":{"case":"主格","number":"単数","gender":"男性"},"g":"その"},{"t":"θεός","l":"θεός","k":"セオス","p":"noun","m":{"case":"主格","number":"単数","gender":"男性"},"g":"神"}]},{"verse":8,"words":[{"t":"⸀δυνατεῖ","l":"δυνατέω","k":"デュナテイ","p":"verb","m":{"person":"3人称","tense":"現在","voice":"能動態","mood":"直説法"}},{"t":"δὲ","l":"δέ","k":"デ","p":"conj","g":"しかし"},{"t":"ὁ","l":"ὁ","k":"ホ","p":"art","m":{"case":"主格","number":"単数","gender":"男性"},"g":"その"},{"t":"θεὸς","l":"θεός","k":"セオス","p":"noun","m":{"case":"主格","number":"単数","gender":"男性"},"g":"神"},{"t":"πᾶσαν","l":"πᾶς","k":"パサン","p":"adj","m":{"case":"対格","number":"単数","gender":"女性"},"g":"すべての"},{"t":"χάριν","l":"χάρις","k":"カリン","p":"noun","m":{"case":"対格","number":"単数","gender":"女性"},"g":"恵み"},{"t":"περισσεῦσαι","l":"περισσεύω","k":"ペリスセウサイ","p":"verb","m":{"tense":"アオリスト","voice":"能動態","mood":"不定詞"}},{"t":"εἰς","l":"εἰς","k":"エイス","p":"prep","g":"〜の中へ"},{"t":"ὑμᾶς","l":"σύ","k":"フマス","p":"pers","m":{"case":"対格","number":"複数"},"g":"あなた"},{"t":"ἵνα","l":"ἵνα","k":"ヒナ","p":"conj","g":"〜するために"},{"t":"ἐν","l":"ἐν","k":"エン","p":"prep","g":"〜の中に"},{"t":"παντὶ","l":"πᾶς","k":"パンティ","p":"adj","m":{"case":"与格","number":"単数","gender":"中性"},"g":"すべての"},{"t":"πάντοτε","l":"πάντοτε","k":"パントテ","p":"adv","g":"いつも"},{"t":"πᾶσαν","l":"πᾶς","k":"パサン","p":"adj","m":{"case":"対格","number":"単数","gender":"女性"},"g":"すべての"},{"t":"αὐτάρκειαν","l":"αὐτάρκεια","k":"アウタルケイアン","p":"noun","m":{"case":"対格","number":"単数","gender":"女性"}},{"t":"ἔχοντες","l":"ἔχω","k":"エコンテス","p":"verb","m":{"tense":"現在","voice":"能動態","mood":"分詞","case":"主格","number":"複数","gender":"男性"},"g":"持つ"},{"t":"περισσεύητε","l":"περισσεύω","k":"ペリスセウエーテ","p":"verb","m":{"person":"2人称","tense":"現在","voice":"能動態","mood":"接続法"}},{"t":"εἰς","l":"εἰς","k":"エイス","p":"prep","g":"〜の中へ"},{"t":"πᾶν","l":"πᾶς","k":"パン","p":"adj","m":{"case":"対格","number":"単数","gender":"中性"},"g":"すべての"},{"t":"ἔργον","l":"ἔργον","k":"エルゴン","p":"noun","m":{"case":"対格","number":"単数","gender":"中性"},"g":"業"},{"t":"ἀγαθόν","l":"ἀγαθός","k":"アガソン","p":"adj","m":{"case":"対格","number":"単数","gender":"中性"},"g":"善い"}]},{"verse":9,"words":[{"t":"(καθὼς","l":"καθώς","k":"カソース","p":"conj","g":"〜のように"},{"t":"γέγραπται","l":"γράφω","k":"ゲグラプタイ","p":"verb","m":{"person":"3人称","voice":"受動態","mood":"直説法"},"g":"書く"},{"t":"Ἐσκόρπισεν","l":"σκορπίζω","k":"エスコルピセン","p":"verb","m":{"person":"3人称","tense":"アオリスト","voice":"能動態","mood":"直説法"}},{"t":"ἔδωκεν","l":"δίδωμι","k":"エドーケン","p":"verb","m":{"person":"3人称","tense":"アオリスト","voice":"能動態","mood":"直説法"},"g":"与える"},{"t":"τοῖς","l":"ὁ","k":"トイス","p":"art","m":{"case":"与格","number":"複数","gender":"男性"},"g":"その"},{"t":"πένησιν","l":"πένης","k":"ペネーシン","p":"adj","m":{"case":"与格","number":"複数","gender":"男性"}},{"t":"ἡ","l":"ὁ","k":"ヘー","p":"art","m":{"case":"主格","number":"単数","gender":"女性"},"g":"その"},{"t":"δικαιοσύνη","l":"δικαιοσύνη","k":"ディカイオシュネー","p":"noun","m":{"case":"主格","number":"単数","gender":"女性"},"g":"義"},{"t":"αὐτοῦ","l":"αὐτός","k":"アウトウ","p":"pers","m":{"case":"属格","number":"単数","gender":"男性"},"g":"彼"},{"t":"μένει","l":"μένω","k":"メネイ","p":"verb","m":{"person":"3人称","tense":"現在","voice":"能動態","mood":"直説法"},"g":"留まる"},{"t":"εἰς","l":"εἰς","k":"エイス","p":"prep","g":"〜の中へ"},{"t":"τὸν","l":"ὁ","k":"トン","p":"art","m":{"case":"対格","number":"単数","gender":"男性"},"g":"その"},{"t":"αἰῶνα","l":"αἰών","k":"アイオーナ","p":"noun","m":{"case":"対格","number":"単数","gender":"男性"},"g":"時代"}]},{"verse":10,"words":[{"t":"ὁ","l":"ὁ","k":"ホ","p":"art","m":{"case":"主格","number":"単数","gender":"男性"},"g":"その"},{"t":"δὲ","l":"δέ","k":"デ","p":"conj","g":"しかし"},{"t":"ἐπιχορηγῶν","l":"ἐπιχορηγέω","k":"エピコレーゴーン","p":"verb","m":{"tense":"現在","voice":"能動態","mood":"分詞","case":"主格","number":"単数","gender":"男性"}},{"t":"⸀σπόρον","l":"σπόρος","k":"スポロン","p":"noun","m":{"case":"対格","number":"単数","gender":"男性"}},{"t":"τῷ","l":"ὁ","k":"トー","p":"art","m":{"case":"与格","number":"単数","gender":"男性"},"g":"その"},{"t":"σπείροντι","l":"σπείρω","k":"スペイロンティ","p":"verb","m":{"tense":"現在","voice":"能動態","mood":"分詞","case":"与格","number":"単数","gender":"男性"}},{"t":"καὶ","l":"καί","k":"カイ","p":"conj","g":"そして"},{"t":"ἄρτον","l":"ἄρτος","k":"アルトン","p":"noun","m":{"case":"対格","number":"単数","gender":"男性"}},{"t":"εἰς","l":"εἰς","k":"エイス","p":"prep","g":"〜の中へ"},{"t":"βρῶσιν","l":"βρῶσις","k":"ブローシン","p":"noun","m":{"case":"対格","number":"単数","gender":"女性"}},{"t":"⸀χορηγήσει","l":"χορηγέω","k":"コレーゲーセイ","p":"verb","m":{"person":"3人称","tense":"未来","voice":"能動態","mood":"直説法"}},{"t":"καὶ","l":"καί","k":"カイ","p":"conj","g":"そして"},{"t":"⸀πληθυνεῖ","l":"πληθύνω","k":"プレーシュネイ","p":"verb","m":{"person":"3人称","tense":"未来","voice":"能動態","mood":"直説法"}},{"t":"τὸν","l":"ὁ","k":"トン","p":"art","m":{"case":"対格","number":"単数","gender":"男性"},"g":"その"},{"t":"σπόρον","l":"σπόρος","k":"スポロン","p":"noun","m":{"case":"対格","number":"単数","gender":"男性"}},{"t":"ὑμῶν","l":"σύ","k":"フモーン","p":"pers","m":{"case":"属格","number":"複数"},"g":"あなた"},{"t":"καὶ","l":"καί","k":"カイ","p":"conj","g":"そして"},{"t":"⸀αὐξήσει","l":"αὐξάνω","k":"アウクセーセイ","p":"verb","m":{"person":"3人称","tense":"未来","voice":"能動態","mood":"直説法"}},{"t":"τὰ","l":"ὁ","k":"タ","p":"art","m":{"case":"対格","number":"複数","gender":"中性"},"g":"その"},{"t":"γενήματα","l":"γένημα","k":"ゲネーマタ","p":"noun","m":{"case":"対格","number":"複数","gender":"中性"}},{"t":"τῆς","l":"ὁ","k":"テース","p":"art","m":{"case":"属格","number":"単数","gender":"女性"},"g":"その"},{"t":"δικαιοσύνης","l":"δικαιοσύνη","k":"ディカイオシュネース","p":"noun","m":{"case":"属格","number":"単数","gender":"女性"},"g":"義"},{"t":"ὑμῶν)","l":"σύ","k":"フモーン","p":"pers","m":{"case":"属格","number":"複数"},"g":"あなた"}]},{"verse":11,"words":[{"t":"ἐν","l":"ἐν","k":"エン","p":"prep","g":"〜の中に"},{"t":"παντὶ","l":"πᾶς","k":"パンティ","p":"adj","m":{"case":"与格","number":"単数","gender":"中性"},"g":"すべての"},{"t":"πλουτιζόμενοι","l":"πλουτίζω","k":"プロウティゾメノイ","p":"verb","m":{"tense":"現在","voice":"受動態","mood":"分詞","case":"主格","number":"複数","gender":"男性"}},{"t":"εἰς","l":"εἰς","k":"エイス","p":"prep","g":"〜の中へ"},{"t":"πᾶσαν","l":"πᾶς","k":"パサン","p":"adj","m":{"case":"対格","number":"単数","gender":"女性"},"g":"すべての"},{"t":"ἁπλότητα","l":"ἁπλότης","k":"ハプロテータ","p":"noun","m":{"case":"対格","number":"単数","gender":"女性"}},{"t":"ἥτις","l":"ὅστις","k":"ヘーティス","p":"rel","m":{"case":"主格","number":"単数","gender":"女性"},"g":"〜ところの者"},{"t":"κατεργάζεται","l":"κατεργάζομαι","k":"カテルガゼタイ","p":"verb","m":{"person":"3人称","tense":"現在","voice":"中動態","mood":"直説法"}},{"t":"δι’","l":"διά","k":"ディア","p":"prep","g":"〜を通して"},{"t":"ἡμῶν","l":"ἐγώ","k":"ヘーモーン","p":"pers","m":{"case":"属格","number":"複数"},"g":"私"},{"t":"εὐχαριστίαν","l":"εὐχαριστία","k":"エウカリスティアン","p":"noun","m":{"case":"対格","number":"単数","gender":"女性"}},{"t":"τῷ","l":"ὁ","k":"トー","p":"art","m":{"case":"与格","number":"単数","gender":"男性"},"g":"その"},{"t":"θεῷ—","l":"θεός","k":"セオー","p":"noun","m":{"case":"与格","number":"単数","gender":"男性"},"g":"神"}]},{"verse":12,"words":[{"t":"ὅτι","l":"ὅτι","k":"ホティ","p":"conj","g":"〜ということ"},{"t":"ἡ","l":"ὁ","k":"ヘー","p":"art","m":{"case":"主格","number":"単数","gender":"女性"},"g":"その"},{"t":"διακονία","l":"διακονία","k":"ディアコニア","p":"noun","m":{"case":"主格","number":"単数","gender":"女性"}},{"t":"τῆς","l":"ὁ","k":"テース","p":"art","m":{"case":"属格","number":"単数","gender":"女性"},"g":"その"},{"t":"λειτουργίας","l":"λειτουργία","k":"レイトウルギアス","p":"noun","m":{"case":"属格","number":"単数","gender":"女性"}},{"t":"ταύτης","l":"οὗτος","k":"タウテース","p":"dem","m":{"case":"属格","number":"単数","gender":"女性"},"g":"この"},{"t":"οὐ","l":"οὐ","k":"ウー","p":"adv","g":"〜ない"},{"t":"μόνον","l":"μόνος","k":"モノン","p":"adj","m":{"case":"対格","number":"単数","gender":"中性"},"g":"ただ〜だけ"},{"t":"ἐστὶν","l":"εἰμί","k":"エスティン","p":"verb","m":{"person":"3人称","tense":"現在","voice":"能動態","mood":"直説法"},"g":"〜である"},{"t":"προσαναπληροῦσα","l":"προσαναπληρόω","k":"プロサナプレーロウサ","p":"verb","m":{"tense":"現在","voice":"能動態","mood":"分詞","case":"主格","number":"単数","gender":"女性"}},{"t":"τὰ","l":"ὁ","k":"タ","p":"art","m":{"case":"対格","number":"複数","gender":"中性"},"g":"その"},{"t":"ὑστερήματα","l":"ὑστέρημα","k":"フステレーマタ","p":"noun","m":{"case":"対格","number":"複数","gender":"中性"}},{"t":"τῶν","l":"ὁ","k":"トーン","p":"art","m":{"case":"属格","number":"複数","gender":"男性"},"g":"その"},{"t":"ἁγίων","l":"ἅγιος","k":"ハギオーン","p":"adj","m":{"case":"属格","number":"複数","gender":"男性"},"g":"聖なる"},{"t":"ἀλλὰ","l":"ἀλλά","k":"アルラ","p":"conj","g":"しかし"},{"t":"καὶ","l":"καί","k":"カイ","p":"adv","g":"そして"},{"t":"περισσεύουσα","l":"περισσεύω","k":"ペリスセウウーサ","p":"verb","m":{"tense":"現在","voice":"能動態","mood":"分詞","case":"主格","number":"単数","gender":"女性"}},{"t":"διὰ","l":"διά","k":"ディア","p":"prep","g":"〜を通して"},{"t":"πολλῶν","l":"πολύς","k":"ポルローン","p":"adj","m":{"case":"属格","number":"複数","gender":"女性"},"g":"多くの"},{"t":"εὐχαριστιῶν","l":"εὐχαριστία","k":"エウカリスティオーン","p":"noun","m":{"case":"属格","number":"複数","gender":"女性"}},{"t":"τῷ","l":"ὁ","k":"トー","p":"art","m":{"case":"与格","number":"単数","gender":"男性"},"g":"その"},{"t":"θεῷ—","l":"θεός","k":"セオー","p":"noun","m":{"case":"与格","number":"単数","gender":"男性"},"g":"神"}]},{"verse":13,"words":[{"t":"διὰ","l":"διά","k":"ディア","p":"prep","g":"〜を通して"},{"t":"τῆς","l":"ὁ","k":"テース","p":"art","m":{"case":"属格","number":"単数","gender":"女性"},"g":"その"},{"t":"δοκιμῆς","l":"δοκιμή","k":"ドキメース","p":"noun","m":{"case":"属格","number":"単数","gender":"女性"}},{"t":"τῆς","l":"ὁ","k":"テース","p":"art","m":{"case":"属格","number":"単数","gender":"女性"},"g":"その"},{"t":"διακονίας","l":"διακονία","k":"ディアコニアス","p":"noun","m":{"case":"属格","number":"単数","gender":"女性"}},{"t":"ταύτης","l":"οὗτος","k":"タウテース","p":"dem","m":{"case":"属格","number":"単数","gender":"女性"},"g":"この"},{"t":"δοξάζοντες","l":"δοξάζω","k":"ドクサゾンテス","p":"verb","m":{"tense":"現在","voice":"能動態","mood":"分詞","case":"主格","number":"複数","gender":"男性"},"g":"栄光を帰す"},{"t":"τὸν","l":"ὁ","k":"トン","p":"art","m":{"case":"対格","number":"単数","gender":"男性"},"g":"その"},{"t":"θεὸν","l":"θεός","k":"セオン","p":"noun","m":{"case":"対格","number":"単数","gender":"男性"},"g":"神"},{"t":"ἐπὶ","l":"ἐπί","k":"エピ","p":"prep","g":"〜の上に"},{"t":"τῇ","l":"ὁ","k":"テー","p":"art","m":{"case":"与格","number":"単数","gender":"女性"},"g":"その"},{"t":"ὑποταγῇ","l":"ὑποταγή","k":"フポタゲー","p":"noun","m":{"case":"与格","number":"単数","gender":"女性"}},{"t":"τῆς","l":"ὁ","k":"テース","p":"art","m":{"case":"属格","number":"単数","gender":"女性"},"g":"その"},{"t":"ὁμολογίας","l":"ὁμολογία","k":"ホモロギアス","p":"noun","m":{"case":"属格","number":"単数","gender":"女性"}},{"t":"ὑμῶν","l":"σύ","k":"フモーン","p":"pers","m":{"case":"属格","number":"複数"},"g":"あなた"},{"t":"εἰς","l":"εἰς","k":"エイス","p":"prep","g":"〜の中へ"},{"t":"τὸ","l":"ὁ","k":"ト","p":"art","m":{"case":"対格","number":"単数","gender":"中性"},"g":"その"},{"t":"εὐαγγέλιον","l":"εὐαγγέλιον","k":"エウアンゲリオン","p":"noun","m":{"case":"対格","number":"単数","gender":"中性"},"g":"福音"},{"t":"τοῦ","l":"ὁ","k":"トウ","p":"art","m":{"case":"属格","number":"単数","gender":"男性"},"g":"その"},{"t":"Χριστοῦ","l":"Χριστός","k":"クリストウ","p":"noun","m":{"case":"属格","number":"単数","gender":"男性"},"g":"キリスト"},{"t":"καὶ","l":"καί","k":"カイ","p":"conj","g":"そして"},{"t":"ἁπλότητι","l":"ἁπλότης","k":"ハプロテーティ","p":"noun","m":{"case":"与格","number":"単数","gender":"女性"}},{"t":"τῆς","l":"ὁ","k":"テース","p":"art","m":{"case":"属格","number":"単数","gender":"女性"},"g":"その"},{"t":"κοινωνίας","l":"κοινωνία","k":"コイノーニアス","p":"noun","m":{"case":"属格","number":"単数","gender":"女性"}},{"t":"εἰς","l":"εἰς","k":"エイス","p":"prep","g":"〜の中へ"},{"t":"αὐτοὺς","l":"αὐτός","k":"アウトウス","p":"pers","m":{"case":"対格","number":"複数","gender":"男性"},"g":"彼"},{"t":"καὶ","l":"καί","k":"カイ","p":"conj","g":"そして"},{"t":"εἰς","l":"εἰς","k":"エイス","p":"prep","g":"〜の中へ"},{"t":"πάντας","l":"πᾶς","k":"パンタス","p":"adj","m":{"case":"対格","number":"複数","gender":"男性"},"g":"すべての"}]},{"verse":14,"words":[{"t":"καὶ","l":"καί","k":"カイ","p":"conj","g":"そして"},{"t":"αὐτῶν","l":"αὐτός","k":"アウトーン","p":"pers","m":{"case":"属格","number":"複数","gender":"男性"},"g":"彼"},{"t":"δεήσει","l":"δέησις","k":"デエーセイ","p":"noun","m":{"case":"与格","number":"単数","gender":"女性"}},{"t":"ὑπὲρ","l":"ὑπέρ","k":"フペル","p":"prep","g":"〜のために"},{"t":"ὑμῶν","l":"σύ","k":"フモーン","p":"pers","m":{"case":"属格","number":"複数"},"g":"あなた"},{"t":"ἐπιποθούντων","l":"ἐπιποθέω","k":"エピポソウントーン","p":"verb","m":{"tense":"現在","voice":"能動態","mood":"分詞","case":"属格","number":"複数","gender":"男性"}},{"t":"ὑμᾶς","l":"σύ","k":"フマス","p":"pers","m":{"case":"対格","number":"複数"},"g":"あなた"},{"t":"διὰ","l":"διά","k":"ディア","p":"prep","g":"〜を通して"},{"t":"τὴν","l":"ὁ","k":"テーン","p":"art","m":{"case":"対格","number":"単数","gender":"女性"},"g":"その"},{"t":"ὑπερβάλλουσαν","l":"ὑπερβάλλω","k":"フペルバルロウサン","p":"verb","m":{"tense":"現在","voice":"能動態","mood":"分詞","case":"対格","number":"単数","gender":"女性"}},{"t":"χάριν","l":"χάρις","k":"カリン","p":"noun","m":{"case":"対格","number":"単数","gender":"女性"},"g":"恵み"},{"t":"τοῦ","l":"ὁ","k":"トウ","p":"art","m":{"case":"属格","number":"単数","gender":"男性"},"g":"その"},{"t":"θεοῦ","l":"θεός","k":"セウー","p":"noun","m":{"case":"属格","number":"単数","gender":"男性"},"g":"神"},{"t":"ἐφ’","l":"ἐπί","k":"エピ","p":"prep","g":"〜の上に"},{"t":"ὑμῖν","l":"σύ","k":"フミン","p":"pers","m":{"case":"与格","number":"複数"},"g":"あなた"}]},{"verse":15,"words":[{"t":"⸀χάρις","l":"χάρις","k":"カリス","p":"noun","m":{"case":"主格","number":"単数","gender":"女性"},"g":"恵み"},{"t":"τῷ","l":"ὁ","k":"トー","p":"art","m":{"case":"与格","number":"単数","gender":"男性"},"g":"その"},{"t":"θεῷ","l":"θεός","k":"セオー","p":"noun","m":{"case":"与格","number":"単数","gender":"男性"},"g":"神"},{"t":"ἐπὶ","l":"ἐπί","k":"エピ","p":"prep","g":"〜の上に"},{"t":"τῇ","l":"ὁ","k":"テー","p":"art","m":{"case":"与格","number":"単数","gender":"女性"},"g":"その"},{"t":"ἀνεκδιηγήτῳ","l":"ἀνεκδιήγητος","k":"アネクディエーゲートー","p":"adj","m":{"case":"与格","number":"単数","gender":"女性"}},{"t":"αὐτοῦ","l":"αὐτός","k":"アウトウ","p":"pers","m":{"case":"属格","number":"単数","gender":"男性"},"g":"彼"},{"t":"δωρεᾷ","l":"δωρεά","k":"ドーレア","p":"noun","m":{"case":"与格","number":"単数","gender":"女性"}}]}]