[{"verse":1,"words":[{"t":"Εἶπεν","l":"λέγω","k":"エイペン","p":"verb","m":{"person":"3人称","tense":"アオリスト","voice":"能動態","mood":"直説法"},"g":"言う"},{"t":"δὲ","l":"δέ","k":"デ","p":"conj","g":"しかし"},{"t":"πρὸς","l":"πρός","k":"プロス","p":"prep","g":"〜に向かって"},{"t":"τοὺς","l":"ὁ","k":"トウス","p":"art","m":{"case":"対格","number":"複数","gender":"男性"},"g":"その"},{"t":"μαθητὰς","l":"μαθητής","k":"マセータス","p":"noun","m":{"case":"対格","number":"複数","gender":"男性"},"g":"弟子"},{"t":"⸀αὐτοῦ","l":"αὐτός","k":"アウトウ","p":"pers","m":{"case":"属格","number":"単数","gender":"男性"},"g":"彼"},{"t":"Ἀνένδεκτόν","l":"ἀνένδεκτος","k":"アネンデクトン","p":"adj","m":{"case":"主格","number":"単数","gender":"中性"}},{"t":"ἐστιν","l":"εἰμί","k":"エスティン","p":"verb","m":{"person":"3人称","tense":"現在","voice":"能動態","mood":"直説法"},"g":"〜である"},{"t":"τοῦ","l":"ὁ","k":"トウ","p":"art","m":{"case":"属格","number":"単数","gender":"中性"},"g":"その"},{"t":"⸂τὰ","l":"ὁ","k":"タ","p":"art","m":{"case":"対格","number":"複数","gender":"中性"},"g":"その"},{"t":"σκάνδαλα","l":"σκάνδαλον","k":"スカンダラ","p":"noun","m":{"case":"対格","number":"複数","gender":"中性"}},{"t":"μὴ","l":"μή","k":"メー","p":"adv","g":"〜ない"},{"t":"ἐλθεῖν⸃","l":"ἔρχομαι","k":"エルセイン","p":"verb","m":{"tense":"アオリスト","voice":"能動態","mood":"不定詞"},"g":"来る"},{"t":"⸂πλὴν","l":"πλήν","k":"プレーン","p":"conj"},{"t":"οὐαὶ⸃","l":"οὐαί","k":"ウーアイ","p":"part"},{"t":"δι’","l":"διά","k":"ディア","p":"prep","g":"〜を通して"},{"t":"οὗ","l":"ὅς","k":"ウー","p":"rel","m":{"case":"属格","number":"単数","gender":"男性"},"g":"〜ところの"},{"t":"ἔρχεται","l":"ἔρχομαι","k":"エルケタイ","p":"verb","m":{"person":"3人称","tense":"現在","voice":"中動態","mood":"直説法"},"g":"来る"}]},{"verse":2,"words":[{"t":"λυσιτελεῖ","l":"λυσιτελεῖ","k":"リュシテレイ","p":"verb","m":{"person":"3人称","tense":"現在","voice":"能動態","mood":"直説法"}},{"t":"αὐτῷ","l":"αὐτός","k":"アウトー","p":"pers","m":{"case":"与格","number":"単数","gender":"男性"},"g":"彼"},{"t":"εἰ","l":"εἰ","k":"エイ","p":"conj","g":"もし"},{"t":"⸂λίθος","l":"λίθος","k":"リソス","p":"noun","m":{"case":"主格","number":"単数","gender":"男性"}},{"t":"μυλικὸς⸃","l":"μυλικός","k":"ミュリコス","p":"adj","m":{"case":"主格","number":"単数","gender":"男性"}},{"t":"περίκειται","l":"περίκειμαι","k":"ペリケイタイ","p":"verb","m":{"person":"3人称","tense":"現在","voice":"中動態","mood":"直説法"}},{"t":"περὶ","l":"περί","k":"ペリ","p":"prep","g":"〜について"},{"t":"τὸν","l":"ὁ","k":"トン","p":"art","m":{"case":"対格","number":"単数","gender":"男性"},"g":"その"},{"t":"τράχηλον","l":"τράχηλος","k":"トラケーロン","p":"noun","m":{"case":"対格","number":"単数","gender":"男性"}},{"t":"αὐτοῦ","l":"αὐτός","k":"アウトウ","p":"pers","m":{"case":"属格","number":"単数","gender":"男性"},"g":"彼"},{"t":"καὶ","l":"καί","k":"カイ","p":"conj","g":"そして"},{"t":"ἔρριπται","l":"ῥίπτω","k":"エルリプタイ","p":"verb","m":{"person":"3人称","voice":"受動態","mood":"直説法"}},{"t":"εἰς","l":"εἰς","k":"エイス","p":"prep","g":"〜の中へ"},{"t":"τὴν","l":"ὁ","k":"テーン","p":"art","m":{"case":"対格","number":"単数","gender":"女性"},"g":"その"},{"t":"θάλασσαν","l":"θάλασσα","k":"サラスサン","p":"noun","m":{"case":"対格","number":"単数","gender":"女性"},"g":"海"},{"t":"ἢ","l":"ἤ","k":"エー","p":"conj","g":"または"},{"t":"ἵνα","l":"ἵνα","k":"ヒナ","p":"conj","g":"〜するために"},{"t":"σκανδαλίσῃ","l":"σκανδαλίζω","k":"スカンダリセー","p":"verb","m":{"person":"3人称","tense":"アオリスト","voice":"能動態","mood":"接続法"},"g":"つまずかせる"},{"t":"⸂τῶν","l":"ὁ","k":"トーン","p":"art","m":{"case":"属格","number":"複数","gender":"男性"},"g":"その"},{"t":"μικρῶν","l":"μικρός","k":"ミクローン","p":"adj","m":{"case":"属格","number":"複数","gender":"男性"},"g":"小さい"},{"t":"τούτων","l":"οὗτος","k":"トウトーン","p":"dem","m":{"case":"属格","number":"複数","gender":"男性"},"g":"この"},{"t":"ἕνα⸃","l":"εἷς","k":"ヘナ","p":"adj","m":{"case":"対格","number":"単数","gender":"男性"},"g":"一つ"}]},{"verse":3,"words":[{"t":"προσέχετε","l":"προσέχω","k":"プロセケテ","p":"verb","m":{"person":"2人称","tense":"現在","voice":"能動態"}},{"t":"ἑαυτοῖς","l":"ἑαυτοῦ","k":"ヘアウトイス","p":"pers","m":{"case":"与格","number":"複数","gender":"男性"},"g":"自分自身"},{"t":"ἐὰν","l":"ἐάν","k":"エアン","p":"conj","g":"もし〜なら"},{"t":"⸀ἁμάρτῃ","l":"ἁμαρτάνω","k":"ハマルテー","p":"verb","m":{"person":"3人称","tense":"アオリスト","voice":"能動態","mood":"接続法"},"g":"罪を犯す"},{"t":"ὁ","l":"ὁ","k":"ホ","p":"art","m":{"case":"主格","number":"単数","gender":"男性"},"g":"その"},{"t":"ἀδελφός","l":"ἀδελφός","k":"アデルフォス","p":"noun","m":{"case":"主格","number":"単数","gender":"男性"},"g":"兄弟"},{"t":"σου","l":"σύ","k":"ソウ","p":"pers","m":{"case":"属格","number":"単数"},"g":"あなた"},{"t":"ἐπιτίμησον","l":"ἐπιτιμάω","k":"エピティメーソン","p":"verb","m":{"person":"2人称","tense":"アオリスト","voice":"能動態"},"g":"叱る"},{"t":"αὐτῷ","l":"αὐτός","k":"アウトー","p":"pers","m":{"case":"与格","number":"単数","gender":"男性"},"g":"彼"},{"t":"καὶ","l":"καί","k":"カイ","p":"conj","g":"そして"},{"t":"ἐὰν","l":"ἐάν","k":"エアン","p":"conj","g":"もし〜なら"},{"t":"μετανοήσῃ","l":"μετανοέω","k":"メタノエーセー","p":"verb","m":{"person":"3人称","tense":"アオリスト","voice":"能動態","mood":"接続法"},"g":"悔い改める"},{"t":"ἄφες","l":"ἀφίημι","k":"アフェス","p":"verb","m":{"person":"2人称","tense":"アオリスト","voice":"能動態"},"g":"赦す"},{"t":"αὐτῷ","l":"αὐτός","k":"アウトー","p":"pers","m":{"case":"与格","number":"単数","gender":"男性"},"g":"彼"}]},{"verse":4,"words":[{"t":"καὶ","l":"καί","k":"カイ","p":"conj","g":"そして"},{"t":"ἐὰν","l":"ἐάν","k":"エアン","p":"conj","g":"もし〜なら"},{"t":"ἑπτάκις","l":"ἑπτάκις","k":"ヘプタキス","p":"adv"},{"t":"τῆς","l":"ὁ","k":"テース","p":"art","m":{"case":"属格","number":"単数","gender":"女性"},"g":"その"},{"t":"ἡμέρας","l":"ἡμέρα","k":"ヘーメラス","p":"noun","m":{"case":"属格","number":"単数","gender":"女性"},"g":"日"},{"t":"⸀ἁμαρτήσῃ","l":"ἁμαρτάνω","k":"ハマルテーセー","p":"verb","m":{"person":"3人称","tense":"アオリスト","voice":"能動態","mood":"接続法"},"g":"罪を犯す"},{"t":"εἰς","l":"εἰς","k":"エイス","p":"prep","g":"〜の中へ"},{"t":"σὲ","l":"σύ","k":"セ","p":"pers","m":{"case":"対格","number":"単数"},"g":"あなた"},{"t":"καὶ","l":"καί","k":"カイ","p":"conj","g":"そして"},{"t":"⸀ἑπτάκις","l":"ἑπτάκις","k":"ヘプタキス","p":"adv"},{"t":"ἐπιστρέψῃ","l":"ἐπιστρέφω","k":"エピストレプセー","p":"verb","m":{"person":"3人称","tense":"アオリスト","voice":"能動態","mood":"接続法"}},{"t":"⸂πρὸς","l":"πρός","k":"プロス","p":"prep","g":"〜に向かって"},{"t":"σὲ⸃","l":"σύ","k":"セ","p":"pers","m":{"case":"対格","number":"単数"},"g":"あなた"},{"t":"λέγων","l":"λέγω","k":"レゴーン","p":"verb","m":{"tense":"現在","voice":"能動態","mood":"分詞","case":"主格","number":"単数","gender":"男性"},"g":"言う"},{"t":"Μετανοῶ","l":"μετανοέω","k":"メタノオー","p":"verb","m":{"person":"1人称","tense":"現在","voice":"能動態","mood":"直説法"},"g":"悔い改める"},{"t":"ἀφήσεις","l":"ἀφίημι","k":"アフェーセイス","p":"verb","m":{"person":"2人称","tense":"未来","voice":"能動態","mood":"直説法"},"g":"赦す"},{"t":"αὐτῷ","l":"αὐτός","k":"アウトー","p":"pers","m":{"case":"与格","number":"単数","gender":"男性"},"g":"彼"}]},{"verse":5,"words":[{"t":"Καὶ","l":"καί","k":"カイ","p":"conj","g":"そして"},{"t":"εἶπαν","l":"λέγω","k":"エイパン","p":"verb","m":{"person":"3人称","tense":"アオリスト","voice":"能動態","mood":"直説法"},"g":"言う"},{"t":"οἱ","l":"ὁ","k":"オイ","p":"art","m":{"case":"主格","number":"複数","gender":"男性"},"g":"その"},{"t":"ἀπόστολοι","l":"ἀπόστολος","k":"アポストロイ","p":"noun","m":{"case":"主格","number":"複数","gender":"男性"},"g":"使徒"},{"t":"τῷ","l":"ὁ","k":"トー","p":"art","m":{"case":"与格","number":"単数","gender":"男性"},"g":"その"},{"t":"κυρίῳ","l":"κύριος","k":"キュリオー","p":"noun","m":{"case":"与格","number":"単数","gender":"男性"},"g":"主人"},{"t":"Πρόσθες","l":"προστίθημι","k":"プロスセス","p":"verb","m":{"person":"2人称","tense":"アオリスト","voice":"能動態"}},{"t":"ἡμῖν","l":"ἐγώ","k":"ヘーミン","p":"pers","m":{"case":"与格","number":"複数"},"g":"私"},{"t":"πίστιν","l":"πίστις","k":"ピスティン","p":"noun","m":{"case":"対格","number":"単数","gender":"女性"},"g":"信仰"}]},{"verse":6,"words":[{"t":"εἶπεν","l":"λέγω","k":"エイペン","p":"verb","m":{"person":"3人称","tense":"アオリスト","voice":"能動態","mood":"直説法"},"g":"言う"},{"t":"δὲ","l":"δέ","k":"デ","p":"conj","g":"しかし"},{"t":"ὁ","l":"ὁ","k":"ホ","p":"art","m":{"case":"主格","number":"単数","gender":"男性"},"g":"その"},{"t":"κύριος","l":"κύριος","k":"キュリオス","p":"noun","m":{"case":"主格","number":"単数","gender":"男性"},"g":"主人"},{"t":"Εἰ","l":"εἰ","k":"エイ","p":"conj","g":"もし"},{"t":"ἔχετε","l":"ἔχω","k":"エケテ","p":"verb","m":{"person":"2人称","tense":"現在","voice":"能動態","mood":"直説法"},"g":"持つ"},{"t":"πίστιν","l":"πίστις","k":"ピスティン","p":"noun","m":{"case":"対格","number":"単数","gender":"女性"},"g":"信仰"},{"t":"ὡς","l":"ὡς","k":"ホース","p":"conj","g":"〜のように"},{"t":"κόκκον","l":"κόκκος","k":"コクコン","p":"noun","m":{"case":"対格","number":"単数","gender":"男性"}},{"t":"σινάπεως","l":"σίναπι","k":"シナペオース","p":"noun","m":{"case":"属格","number":"単数","gender":"中性"}},{"t":"ἐλέγετε","l":"λέγω","k":"エレゲテ","p":"verb","m":{"person":"2人称","tense":"未完了","voice":"能動態","mood":"直説法"},"g":"言う"},{"t":"ἂν","l":"ἄν","k":"アン","p":"part"},{"t":"τῇ","l":"ὁ","k":"テー","p":"art","m":{"case":"与格","number":"単数","gender":"女性"},"g":"その"},{"t":"συκαμίνῳ","l":"συκάμινος","k":"シュカミノー","p":"noun","m":{"case":"与格","number":"単数","gender":"女性"}},{"t":"ταύτῃ","l":"οὗτος","k":"タウテー","p":"dem","m":{"case":"与格","number":"単数","gender":"女性"},"g":"この"},{"t":"Ἐκριζώθητι","l":"ἐκριζόω","k":"エクリゾーセーティ","p":"verb","m":{"person":"2人称","tense":"アオリスト","voice":"受動態"}},{"t":"καὶ","l":"καί","k":"カイ","p":"conj","g":"そして"},{"t":"φυτεύθητι","l":"φυτεύω","k":"フュテウセーティ","p":"verb","m":{"person":"2人称","tense":"アオリスト","voice":"受動態"}},{"t":"ἐν","l":"ἐν","k":"エン","p":"prep","g":"〜の中に"},{"t":"τῇ","l":"ὁ","k":"テー","p":"art","m":{"case":"与格","number":"単数","gender":"女性"},"g":"その"},{"t":"θαλάσσῃ","l":"θάλασσα","k":"サラスセー","p":"noun","m":{"case":"与格","number":"単数","gender":"女性"},"g":"海"},{"t":"καὶ","l":"καί","k":"カイ","p":"conj","g":"そして"},{"t":"ὑπήκουσεν","l":"ὑπακούω","k":"フペーコウセン","p":"verb","m":{"person":"3人称","tense":"アオリスト","voice":"能動態","mood":"直説法"}},{"t":"ἂν","l":"ἄν","k":"アン","p":"part"},{"t":"ὑμῖν","l":"σύ","k":"フミン","p":"pers","m":{"case":"与格","number":"複数"},"g":"あなた"}]},{"verse":7,"words":[{"t":"Τίς","l":"τίς","k":"ティス","p":"inter","m":{"case":"主格","number":"単数","gender":"男性"},"g":"誰"},{"t":"δὲ","l":"δέ","k":"デ","p":"conj","g":"しかし"},{"t":"ἐξ","l":"ἐκ","k":"エク","p":"prep","g":"〜から"},{"t":"ὑμῶν","l":"σύ","k":"フモーン","p":"pers","m":{"case":"属格","number":"複数"},"g":"あなた"},{"t":"δοῦλον","l":"δοῦλος","k":"ドウロン","p":"noun","m":{"case":"対格","number":"単数","gender":"男性"},"g":"奴隷"},{"t":"ἔχων","l":"ἔχω","k":"エコーン","p":"verb","m":{"tense":"現在","voice":"能動態","mood":"分詞","case":"主格","number":"単数","gender":"男性"},"g":"持つ"},{"t":"ἀροτριῶντα","l":"ἀροτριάω","k":"アロトリオーンタ","p":"verb","m":{"tense":"現在","voice":"能動態","mood":"分詞","case":"対格","number":"単数","gender":"男性"}},{"t":"ἢ","l":"ἤ","k":"エー","p":"conj","g":"または"},{"t":"ποιμαίνοντα","l":"ποιμαίνω","k":"ポイマイノンタ","p":"verb","m":{"tense":"現在","voice":"能動態","mood":"分詞","case":"対格","number":"単数","gender":"男性"}},{"t":"ὃς","l":"ὅς","k":"ホス","p":"rel","m":{"case":"主格","number":"単数","gender":"男性"},"g":"〜ところの"},{"t":"εἰσελθόντι","l":"εἰσέρχομαι","k":"エイセルソンティ","p":"verb","m":{"tense":"アオリスト","voice":"能動態","mood":"分詞","case":"与格","number":"単数","gender":"男性"},"g":"入る"},{"t":"ἐκ","l":"ἐκ","k":"エク","p":"prep","g":"〜から"},{"t":"τοῦ","l":"ὁ","k":"トウ","p":"art","m":{"case":"属格","number":"単数","gender":"男性"},"g":"その"},{"t":"ἀγροῦ","l":"ἀγρός","k":"アグロウ","p":"noun","m":{"case":"属格","number":"単数","gender":"男性"},"g":"畑"},{"t":"ἐρεῖ","l":"λέγω","k":"エレイ","p":"verb","m":{"person":"3人称","tense":"未来","voice":"能動態","mood":"直説法"},"g":"言う"},{"t":"⸀αὐτῷ","l":"αὐτός","k":"アウトー","p":"pers","m":{"case":"与格","number":"単数","gender":"男性"},"g":"彼"},{"t":"Εὐθέως","l":"εὐθέως","k":"エウセオース","p":"adv","g":"すぐに"},{"t":"παρελθὼν","l":"παρέρχομαι","k":"パレルソーン","p":"verb","m":{"tense":"アオリスト","voice":"能動態","mood":"分詞","case":"主格","number":"単数","gender":"男性"}},{"t":"ἀνάπεσε","l":"ἀναπίπτω","k":"アナペセ","p":"verb","m":{"person":"2人称","tense":"アオリスト","voice":"能動態"}}]},{"verse":8,"words":[{"t":"ἀλλ’","l":"ἀλλά","k":"アルラ","p":"conj","g":"しかし"},{"t":"οὐχὶ","l":"οὐχί","k":"ウーキ","p":"part","g":"いいえ"},{"t":"ἐρεῖ","l":"λέγω","k":"エレイ","p":"verb","m":{"person":"3人称","tense":"未来","voice":"能動態","mood":"直説法"},"g":"言う"},{"t":"αὐτῷ","l":"αὐτός","k":"アウトー","p":"pers","m":{"case":"与格","number":"単数","gender":"男性"},"g":"彼"},{"t":"Ἑτοίμασον","l":"ἑτοιμάζω","k":"ヘトイマソン","p":"verb","m":{"person":"2人称","tense":"アオリスト","voice":"能動態"}},{"t":"τί","l":"τίς","k":"ティ","p":"inter","m":{"case":"対格","number":"単数","gender":"中性"},"g":"誰"},{"t":"δειπνήσω","l":"δειπνέω","k":"デイプネーソー","p":"verb","m":{"person":"1人称","tense":"アオリスト","voice":"能動態","mood":"接続法"}},{"t":"καὶ","l":"καί","k":"カイ","p":"conj","g":"そして"},{"t":"περιζωσάμενος","l":"περιζώννυμι","k":"ペリゾーサメノス","p":"verb","m":{"tense":"アオリスト","voice":"中動態","mood":"分詞","case":"主格","number":"単数","gender":"男性"}},{"t":"διακόνει","l":"διακονέω","k":"ディアコネイ","p":"verb","m":{"person":"2人称","tense":"現在","voice":"能動態"}},{"t":"μοι","l":"ἐγώ","k":"モイ","p":"pers","m":{"case":"与格","number":"単数"},"g":"私"},{"t":"ἕως","l":"ἕως","k":"ヘオース","p":"conj","g":"〜まで"},{"t":"φάγω","l":"ἐσθίω","k":"ファゴー","p":"verb","m":{"person":"1人称","tense":"アオリスト","voice":"能動態","mood":"接続法"},"g":"食べる"},{"t":"καὶ","l":"καί","k":"カイ","p":"conj","g":"そして"},{"t":"πίω","l":"πίνω","k":"ピオー","p":"verb","m":{"person":"1人称","tense":"アオリスト","voice":"能動態","mood":"接続法"},"g":"飲む"},{"t":"καὶ","l":"καί","k":"カイ","p":"conj","g":"そして"},{"t":"μετὰ","l":"μετά","k":"メタ","p":"prep","g":"〜と共に"},{"t":"ταῦτα","l":"οὗτος","k":"タウタ","p":"dem","m":{"case":"対格","number":"複数","gender":"中性"},"g":"この"},{"t":"φάγεσαι","l":"ἐσθίω","k":"ファゲサイ","p":"verb","m":{"person":"2人称","tense":"未来","voice":"中動態","mood":"直説法"},"g":"食べる"},{"t":"καὶ","l":"καί","k":"カイ","p":"conj","g":"そして"},{"t":"πίεσαι","l":"πίνω","k":"ピエサイ","p":"verb","m":{"person":"2人称","tense":"未来","voice":"中動態","mood":"直説法"},"g":"飲む"},{"t":"σύ","l":"σύ","k":"シュ","p":"pers","m":{"case":"主格","number":"単数"},"g":"あなた"}]},{"verse":9,"words":[{"t":"μὴ","l":"μή","k":"メー","p":"part","g":"〜ない"},{"t":"⸂ἔχει","l":"ἔχω","k":"エケイ","p":"verb","m":{"person":"3人称","tense":"現在","voice":"能動態","mood":"直説法"},"g":"持つ"},{"t":"χάριν⸃","l":"χάρις","k":"カリン","p":"noun","m":{"case":"対格","number":"単数","gender":"女性"},"g":"恵み"},{"t":"τῷ","l":"ὁ","k":"トー","p":"art","m":{"case":"与格","number":"単数","gender":"男性"},"g":"その"},{"t":"⸀δούλῳ","l":"δοῦλος","k":"ドウロー","p":"noun","m":{"case":"与格","number":"単数","gender":"男性"},"g":"奴隷"},{"t":"ὅτι","l":"ὅτι","k":"ホティ","p":"conj","g":"〜ということ"},{"t":"ἐποίησεν","l":"ποιέω","k":"エポイエーセン","p":"verb","m":{"person":"3人称","tense":"アオリスト","voice":"能動態","mood":"直説法"},"g":"する"},{"t":"τὰ","l":"ὁ","k":"タ","p":"art","m":{"case":"対格","number":"複数","gender":"中性"},"g":"その"},{"t":"⸀διαταχθέντα","l":"διατάσσω","k":"ディアタクセンタ","p":"verb","m":{"tense":"アオリスト","voice":"受動態","mood":"分詞","case":"対格","number":"複数","gender":"中性"}}]},{"verse":10,"words":[{"t":"οὕτως","l":"οὕτω(ς)","k":"ウートース","p":"adv"},{"t":"καὶ","l":"καί","k":"カイ","p":"adv","g":"そして"},{"t":"ὑμεῖς","l":"σύ","k":"フメイス","p":"pers","m":{"case":"主格","number":"複数"},"g":"あなた"},{"t":"ὅταν","l":"ὅταν","k":"ホタン","p":"conj","g":"〜する時はいつでも"},{"t":"ποιήσητε","l":"ποιέω","k":"ポイエーセーテ","p":"verb","m":{"person":"2人称","tense":"アオリスト","voice":"能動態","mood":"接続法"},"g":"する"},{"t":"πάντα","l":"πᾶς","k":"パンタ","p":"adj","m":{"case":"対格","number":"複数","gender":"中性"},"g":"すべての"},{"t":"τὰ","l":"ὁ","k":"タ","p":"art","m":{"case":"対格","number":"複数","gender":"中性"},"g":"その"},{"t":"διαταχθέντα","l":"διατάσσω","k":"ディアタクセンタ","p":"verb","m":{"tense":"アオリスト","voice":"受動態","mood":"分詞","case":"対格","number":"複数","gender":"中性"}},{"t":"ὑμῖν","l":"σύ","k":"フミン","p":"pers","m":{"case":"与格","number":"複数"},"g":"あなた"},{"t":"λέγετε","l":"λέγω","k":"レゲテ","p":"verb","m":{"person":"2人称","tense":"現在","voice":"能動態"},"g":"言う"},{"t":"ὅτι","l":"ὅτι","k":"ホティ","p":"conj","g":"〜ということ"},{"t":"Δοῦλοι","l":"δοῦλος","k":"ドウロイ","p":"noun","m":{"case":"主格","number":"複数","gender":"男性"},"g":"奴隷"},{"t":"ἀχρεῖοί","l":"ἀχρεῖος","k":"アクレイオイ","p":"adj","m":{"case":"主格","number":"複数","gender":"男性"}},{"t":"ἐσμεν","l":"εἰμί","k":"エスメン","p":"verb","m":{"person":"1人称","tense":"現在","voice":"能動態","mood":"直説法"},"g":"〜である"},{"t":"⸂ὃ","l":"ὅς","k":"ホ","p":"rel","m":{"case":"対格","number":"単数","gender":"中性"},"g":"〜ところの"},{"t":"ὠφείλομεν⸃","l":"ὀφείλω","k":"オーフェイロメン","p":"verb","m":{"person":"1人称","tense":"未完了","voice":"能動態","mood":"直説法"}},{"t":"ποιῆσαι","l":"ποιέω","k":"ポイエーサイ","p":"verb","m":{"tense":"アオリスト","voice":"能動態","mood":"不定詞"},"g":"する"},{"t":"πεποιήκαμεν","l":"ποιέω","k":"ペポイエーカメン","p":"verb","m":{"person":"1人称","voice":"能動態","mood":"直説法"},"g":"する"}]},{"verse":11,"words":[{"t":"Καὶ","l":"καί","k":"カイ","p":"conj","g":"そして"},{"t":"ἐγένετο","l":"γίνομαι","k":"エゲネト","p":"verb","m":{"person":"3人称","tense":"アオリスト","voice":"中動態","mood":"直説法"},"g":"〜になる"},{"t":"ἐν","l":"ἐν","k":"エン","p":"prep","g":"〜の中に"},{"t":"τῷ","l":"ὁ","k":"トー","p":"art","m":{"case":"与格","number":"単数","gender":"中性"},"g":"その"},{"t":"⸀πορεύεσθαι","l":"πορεύομαι","k":"ポレウエスサイ","p":"verb","m":{"tense":"現在","voice":"中動態","mood":"不定詞"},"g":"行く"},{"t":"εἰς","l":"εἰς","k":"エイス","p":"prep","g":"〜の中へ"},{"t":"Ἰερουσαλὴμ","l":"Ἰερουσαλήμ","k":"イエロウサレーム","p":"noun","m":{"case":"対格","number":"単数","gender":"女性"},"g":"エルサレム"},{"t":"καὶ","l":"καί","k":"カイ","p":"conj","g":"そして"},{"t":"αὐτὸς","l":"αὐτός","k":"アウトス","p":"pers","m":{"case":"主格","number":"単数","gender":"男性"},"g":"彼"},{"t":"διήρχετο","l":"διέρχομαι","k":"ディエールケト","p":"verb","m":{"person":"3人称","tense":"未完了","voice":"中動態","mood":"直説法"}},{"t":"διὰ","l":"διά","k":"ディア","p":"prep","g":"〜を通して"},{"t":"⸀μέσον","l":"μέσος","k":"メソン","p":"adj","m":{"case":"対格","number":"単数","gender":"中性"}},{"t":"Σαμαρείας","l":"Σαμάρεια","k":"サマレイアス","p":"noun","m":{"case":"属格","number":"単数","gender":"女性"}},{"t":"καὶ","l":"καί","k":"カイ","p":"conj","g":"そして"},{"t":"Γαλιλαίας","l":"Γαλιλαία","k":"ガリライアス","p":"noun","m":{"case":"属格","number":"単数","gender":"女性"},"g":"ガリラヤ"}]},{"verse":12,"words":[{"t":"καὶ","l":"καί","k":"カイ","p":"conj","g":"そして"},{"t":"εἰσερχομένου","l":"εἰσέρχομαι","k":"エイセルコメノウ","p":"verb","m":{"tense":"現在","voice":"中動態","mood":"分詞","case":"属格","number":"単数","gender":"男性"},"g":"入る"},{"t":"αὐτοῦ","l":"αὐτός","k":"アウトウ","p":"pers","m":{"case":"属格","number":"単数","gender":"男性"},"g":"彼"},{"t":"εἴς","l":"εἰς","k":"エイス","p":"prep","g":"〜の中へ"},{"t":"τινα","l":"τις","k":"ティナ","p":"inter","m":{"case":"対格","number":"単数","gender":"女性"}},{"t":"κώμην","l":"κώμη","k":"コーメーン","p":"noun","m":{"case":"対格","number":"単数","gender":"女性"}},{"t":"⸀ἀπήντησαν","l":"ἀπαντάω","k":"アペーンテーサン","p":"verb","m":{"person":"3人称","tense":"アオリスト","voice":"能動態","mood":"直説法"}},{"t":"δέκα","l":"δέκα","k":"デカ","p":"adj","m":{"case":"主格","number":"複数","gender":"男性"},"g":"十"},{"t":"λεπροὶ","l":"λεπρός","k":"レプロイ","p":"adj","m":{"case":"主格","number":"複数","gender":"男性"}},{"t":"ἄνδρες","l":"ἀνήρ","k":"アンドレス","p":"noun","m":{"case":"主格","number":"複数","gender":"男性"},"g":"男"},{"t":"οἳ","l":"ὅς","k":"オイ","p":"rel","m":{"case":"主格","number":"複数","gender":"男性"},"g":"〜ところの"},{"t":"⸀ἔστησαν","l":"ἵστημι","k":"エステーサン","p":"verb","m":{"person":"3人称","tense":"アオリスト","voice":"能動態","mood":"直説法"},"g":"立つ"},{"t":"πόρρωθεν","l":"πόρρωθεν","k":"ポルローセン","p":"adv"}]},{"verse":13,"words":[{"t":"καὶ","l":"καί","k":"カイ","p":"conj","g":"そして"},{"t":"αὐτοὶ","l":"αὐτός","k":"アウトイ","p":"pers","m":{"case":"主格","number":"複数","gender":"男性"},"g":"彼"},{"t":"ἦραν","l":"αἴρω","k":"エーラン","p":"verb","m":{"person":"3人称","tense":"アオリスト","voice":"能動態","mood":"直説法"},"g":"取り上げる"},{"t":"φωνὴν","l":"φωνή","k":"フォーネーン","p":"noun","m":{"case":"対格","number":"単数","gender":"女性"}},{"t":"λέγοντες","l":"λέγω","k":"レゴンテス","p":"verb","m":{"tense":"現在","voice":"能動態","mood":"分詞","case":"主格","number":"複数","gender":"男性"},"g":"言う"},{"t":"Ἰησοῦ","l":"Ἰησοῦς","k":"イエーソウ","p":"noun","m":{"case":"呼格","number":"単数","gender":"男性"},"g":"イエス"},{"t":"ἐπιστάτα","l":"ἐπιστάτης","k":"エピスタタ","p":"noun","m":{"case":"呼格","number":"単数","gender":"男性"}},{"t":"ἐλέησον","l":"ἐλεάω","k":"エレエーソン","p":"verb","m":{"person":"2人称","tense":"アオリスト","voice":"能動態"}},{"t":"ἡμᾶς","l":"ἐγώ","k":"ヘーマス","p":"pers","m":{"case":"対格","number":"複数"},"g":"私"}]},{"verse":14,"words":[{"t":"καὶ","l":"καί","k":"カイ","p":"conj","g":"そして"},{"t":"ἰδὼν","l":"ὁράω","k":"イドーン","p":"verb","m":{"tense":"アオリスト","voice":"能動態","mood":"分詞","case":"主格","number":"単数","gender":"男性"},"g":"見る"},{"t":"εἶπεν","l":"λέγω","k":"エイペン","p":"verb","m":{"person":"3人称","tense":"アオリスト","voice":"能動態","mood":"直説法"},"g":"言う"},{"t":"αὐτοῖς","l":"αὐτός","k":"アウトイス","p":"pers","m":{"case":"与格","number":"複数","gender":"男性"},"g":"彼"},{"t":"Πορευθέντες","l":"πορεύομαι","k":"ポレウセンテス","p":"verb","m":{"tense":"アオリスト","voice":"受動態","mood":"分詞","case":"主格","number":"複数","gender":"男性"},"g":"行く"},{"t":"ἐπιδείξατε","l":"ἐπιδείκνυμι","k":"エピデイクサテ","p":"verb","m":{"person":"2人称","tense":"アオリスト","voice":"能動態"}},{"t":"ἑαυτοὺς","l":"ἑαυτοῦ","k":"ヘアウトウス","p":"pers","m":{"case":"対格","number":"複数","gender":"男性"},"g":"自分自身"},{"t":"τοῖς","l":"ὁ","k":"トイス","p":"art","m":{"case":"与格","number":"複数","gender":"男性"},"g":"その"},{"t":"ἱερεῦσιν","l":"ἱερεύς","k":"ヒエレウシン","p":"noun","m":{"case":"与格","number":"複数","gender":"男性"},"g":"祭司"},{"t":"καὶ","l":"καί","k":"カイ","p":"conj","g":"そして"},{"t":"ἐγένετο","l":"γίνομαι","k":"エゲネト","p":"verb","m":{"person":"3人称","tense":"アオリスト","voice":"中動態","mood":"直説法"},"g":"〜になる"},{"t":"ἐν","l":"ἐν","k":"エン","p":"prep","g":"〜の中に"},{"t":"τῷ","l":"ὁ","k":"トー","p":"art","m":{"case":"与格","number":"単数","gender":"中性"},"g":"その"},{"t":"ὑπάγειν","l":"ὑπάγω","k":"フパゲイン","p":"verb","m":{"tense":"現在","voice":"能動態","mood":"不定詞"},"g":"行く"},{"t":"αὐτοὺς","l":"αὐτός","k":"アウトウス","p":"pers","m":{"case":"対格","number":"複数","gender":"男性"},"g":"彼"},{"t":"ἐκαθαρίσθησαν","l":"καθαρίζω","k":"エカサリスセーサン","p":"verb","m":{"person":"3人称","tense":"アオリスト","voice":"受動態","mood":"直説法"}}]},{"verse":15,"words":[{"t":"εἷς","l":"εἷς","k":"エイス","p":"adj","m":{"case":"主格","number":"単数","gender":"男性"},"g":"一つ"},{"t":"δὲ","l":"δέ","k":"デ","p":"conj","g":"しかし"},{"t":"ἐξ","l":"ἐκ","k":"エク","p":"prep","g":"〜から"},{"t":"αὐτῶν","l":"αὐτός","k":"アウトーン","p":"pers","m":{"case":"属格","number":"複数","gender":"男性"},"g":"彼"},{"t":"ἰδὼν","l":"ὁράω","k":"イドーン","p":"verb","m":{"tense":"アオリスト","voice":"能動態","mood":"分詞","case":"主格","number":"単数","gender":"男性"},"g":"見る"},{"t":"ὅτι","l":"ὅτι","k":"ホティ","p":"conj","g":"〜ということ"},{"t":"ἰάθη","l":"ἰάομαι","k":"イアセー","p":"verb","m":{"person":"3人称","tense":"アオリスト","voice":"受動態","mood":"直説法"}},{"t":"ὑπέστρεψεν","l":"ὑποστρέφω","k":"フペストレプセン","p":"verb","m":{"person":"3人称","tense":"アオリスト","voice":"能動態","mood":"直説法"}},{"t":"μετὰ","l":"μετά","k":"メタ","p":"prep","g":"〜と共に"},{"t":"φωνῆς","l":"φωνή","k":"フォーネース","p":"noun","m":{"case":"属格","number":"単数","gender":"女性"}},{"t":"μεγάλης","l":"μέγας","k":"メガレース","p":"adj","m":{"case":"属格","number":"単数","gender":"女性"},"g":"大きい"},{"t":"δοξάζων","l":"δοξάζω","k":"ドクサゾーン","p":"verb","m":{"tense":"現在","voice":"能動態","mood":"分詞","case":"主格","number":"単数","gender":"男性"},"g":"栄光を帰す"},{"t":"τὸν","l":"ὁ","k":"トン","p":"art","m":{"case":"対格","number":"単数","gender":"男性"},"g":"その"},{"t":"θεόν","l":"θεός","k":"セオン","p":"noun","m":{"case":"対格","number":"単数","gender":"男性"},"g":"神"}]},{"verse":16,"words":[{"t":"καὶ","l":"καί","k":"カイ","p":"conj","g":"そして"},{"t":"ἔπεσεν","l":"πίπτω","k":"エペセン","p":"verb","m":{"person":"3人称","tense":"アオリスト","voice":"能動態","mood":"直説法"},"g":"落ちる"},{"t":"ἐπὶ","l":"ἐπί","k":"エピ","p":"prep","g":"〜の上に"},{"t":"πρόσωπον","l":"πρόσωπον","k":"プロソーポン","p":"noun","m":{"case":"対格","number":"単数","gender":"中性"},"g":"顔"},{"t":"παρὰ","l":"παρά","k":"パラ","p":"prep","g":"〜のそばに"},{"t":"τοὺς","l":"ὁ","k":"トウス","p":"art","m":{"case":"対格","number":"複数","gender":"男性"},"g":"その"},{"t":"πόδας","l":"πούς","k":"ポダス","p":"noun","m":{"case":"対格","number":"複数","gender":"男性"},"g":"足"},{"t":"αὐτοῦ","l":"αὐτός","k":"アウトウ","p":"pers","m":{"case":"属格","number":"単数","gender":"男性"},"g":"彼"},{"t":"εὐχαριστῶν","l":"εὐχαριστέω","k":"エウカリストーン","p":"verb","m":{"tense":"現在","voice":"能動態","mood":"分詞","case":"主格","number":"単数","gender":"男性"},"g":"感謝する"},{"t":"αὐτῷ","l":"αὐτός","k":"アウトー","p":"pers","m":{"case":"与格","number":"単数","gender":"男性"},"g":"彼"},{"t":"καὶ","l":"καί","k":"カイ","p":"conj","g":"そして"},{"t":"αὐτὸς","l":"αὐτός","k":"アウトス","p":"pers","m":{"case":"主格","number":"単数","gender":"男性"},"g":"彼"},{"t":"ἦν","l":"εἰμί","k":"エーン","p":"verb","m":{"person":"3人称","tense":"未完了","voice":"能動態","mood":"直説法"},"g":"〜である"},{"t":"Σαμαρίτης","l":"Σαμαρίτης","k":"サマリテース","p":"noun","m":{"case":"主格","number":"単数","gender":"男性"}}]},{"verse":17,"words":[{"t":"ἀποκριθεὶς","l":"ἀποκρίνομαι","k":"アポクリセイス","p":"verb","m":{"tense":"アオリスト","voice":"受動態","mood":"分詞","case":"主格","number":"単数","gender":"男性"},"g":"答える"},{"t":"δὲ","l":"δέ","k":"デ","p":"conj","g":"しかし"},{"t":"ὁ","l":"ὁ","k":"ホ","p":"art","m":{"case":"主格","number":"単数","gender":"男性"},"g":"その"},{"t":"Ἰησοῦς","l":"Ἰησοῦς","k":"イエーソウス","p":"noun","m":{"case":"主格","number":"単数","gender":"男性"},"g":"イエス"},{"t":"εἶπεν","l":"λέγω","k":"エイペン","p":"verb","m":{"person":"3人称","tense":"アオリスト","voice":"能動態","mood":"直説法"},"g":"言う"},{"t":"⸀Οὐχὶ","l":"οὐχί","k":"ウーキ","p":"part","g":"いいえ"},{"t":"οἱ","l":"ὁ","k":"オイ","p":"art","m":{"case":"主格","number":"複数","gender":"男性"},"g":"その"},{"t":"δέκα","l":"δέκα","k":"デカ","p":"adj","m":{"case":"主格","number":"複数","gender":"男性"},"g":"十"},{"t":"ἐκαθαρίσθησαν","l":"καθαρίζω","k":"エカサリスセーサン","p":"verb","m":{"person":"3人称","tense":"アオリスト","voice":"受動態","mood":"直説法"}},{"t":"οἱ","l":"ὁ","k":"オイ","p":"art","m":{"case":"主格","number":"複数","gender":"男性"},"g":"その"},{"t":"δὲ","l":"δέ","k":"デ","p":"conj","g":"しかし"},{"t":"ἐννέα","l":"ἐννέα","k":"エンネア","p":"adj","m":{"case":"主格","number":"複数","gender":"男性"},"g":"九"},{"t":"ποῦ","l":"ποῦ","k":"ポウ","p":"adv","g":"どこに"}]},{"verse":18,"words":[{"t":"οὐχ","l":"οὐ","k":"ウー","p":"adv","g":"〜ない"},{"t":"εὑρέθησαν","l":"εὑρίσκω","k":"エウレセーサン","p":"verb","m":{"person":"3人称","tense":"アオリスト","voice":"受動態","mood":"直説法"},"g":"見つける"},{"t":"ὑποστρέψαντες","l":"ὑποστρέφω","k":"フポストレプサンテス","p":"verb","m":{"tense":"アオリスト","voice":"能動態","mood":"分詞","case":"主格","number":"複数","gender":"男性"}},{"t":"δοῦναι","l":"δίδωμι","k":"ドウナイ","p":"verb","m":{"tense":"アオリスト","voice":"能動態","mood":"不定詞"},"g":"与える"},{"t":"δόξαν","l":"δόξα","k":"ドクサン","p":"noun","m":{"case":"対格","number":"単数","gender":"女性"},"g":"栄光"},{"t":"τῷ","l":"ὁ","k":"トー","p":"art","m":{"case":"与格","number":"単数","gender":"男性"},"g":"その"},{"t":"θεῷ","l":"θεός","k":"セオー","p":"noun","m":{"case":"与格","number":"単数","gender":"男性"},"g":"神"},{"t":"εἰ","l":"εἰ","k":"エイ","p":"conj","g":"もし"},{"t":"μὴ","l":"μή","k":"メー","p":"adv","g":"〜ない"},{"t":"ὁ","l":"ὁ","k":"ホ","p":"art","m":{"case":"主格","number":"単数","gender":"男性"},"g":"その"},{"t":"ἀλλογενὴς","l":"ἀλλογενής","k":"アルロゲネース","p":"adj","m":{"case":"主格","number":"単数","gender":"男性"}},{"t":"οὗτος","l":"οὗτος","k":"ウートス","p":"dem","m":{"case":"主格","number":"単数","gender":"男性"},"g":"この"}]},{"verse":19,"words":[{"t":"καὶ","l":"καί","k":"カイ","p":"conj","g":"そして"},{"t":"εἶπεν","l":"λέγω","k":"エイペン","p":"verb","m":{"person":"3人称","tense":"アオリスト","voice":"能動態","mood":"直説法"},"g":"言う"},{"t":"αὐτῷ","l":"αὐτός","k":"アウトー","p":"pers","m":{"case":"与格","number":"単数","gender":"男性"},"g":"彼"},{"t":"Ἀναστὰς","l":"ἀνίστημι","k":"アナスタス","p":"verb","m":{"tense":"アオリスト","voice":"能動態","mood":"分詞","case":"主格","number":"単数","gender":"男性"},"g":"立ち上がる"},{"t":"πορεύου","l":"πορεύομαι","k":"ポレウウー","p":"verb","m":{"person":"2人称","tense":"現在","voice":"中動態"},"g":"行く"},{"t":"ἡ","l":"ὁ","k":"ヘー","p":"art","m":{"case":"主格","number":"単数","gender":"女性"},"g":"その"},{"t":"πίστις","l":"πίστις","k":"ピスティス","p":"noun","m":{"case":"主格","number":"単数","gender":"女性"},"g":"信仰"},{"t":"σου","l":"σύ","k":"ソウ","p":"pers","m":{"case":"属格","number":"単数"},"g":"あなた"},{"t":"σέσωκέν","l":"σῴζω","k":"セソーケン","p":"verb","m":{"person":"3人称","voice":"能動態","mood":"直説法"},"g":"救う"},{"t":"σε","l":"σύ","k":"セ","p":"pers","m":{"case":"対格","number":"単数"},"g":"あなた"}]},{"verse":20,"words":[{"t":"Ἐπερωτηθεὶς","l":"ἐπερωτάω","k":"エペローテーセイス","p":"verb","m":{"tense":"アオリスト","voice":"受動態","mood":"分詞","case":"主格","number":"単数","gender":"男性"}},{"t":"δὲ","l":"δέ","k":"デ","p":"conj","g":"しかし"},{"t":"ὑπὸ","l":"ὑπό","k":"フポ","p":"prep","g":"〜によって"},{"t":"τῶν","l":"ὁ","k":"トーン","p":"art","m":{"case":"属格","number":"複数","gender":"男性"},"g":"その"},{"t":"Φαρισαίων","l":"Φαρισαῖος","k":"ファリサイオーン","p":"noun","m":{"case":"属格","number":"複数","gender":"男性"},"g":"パリサイ人"},{"t":"πότε","l":"πότε","k":"ポテ","p":"adv"},{"t":"ἔρχεται","l":"ἔρχομαι","k":"エルケタイ","p":"verb","m":{"person":"3人称","tense":"現在","voice":"中動態","mood":"直説法"},"g":"来る"},{"t":"ἡ","l":"ὁ","k":"ヘー","p":"art","m":{"case":"主格","number":"単数","gender":"女性"},"g":"その"},{"t":"βασιλεία","l":"βασιλεία","k":"バシレイア","p":"noun","m":{"case":"主格","number":"単数","gender":"女性"},"g":"王国"},{"t":"τοῦ","l":"ὁ","k":"トウ","p":"art","m":{"case":"属格","number":"単数","gender":"男性"},"g":"その"},{"t":"θεοῦ","l":"θεός","k":"セウー","p":"noun","m":{"case":"属格","number":"単数","gender":"男性"},"g":"神"},{"t":"ἀπεκρίθη","l":"ἀποκρίνομαι","k":"アペクリセー","p":"verb","m":{"person":"3人称","tense":"アオリスト","voice":"受動態","mood":"直説法"},"g":"答える"},{"t":"αὐτοῖς","l":"αὐτός","k":"アウトイス","p":"pers","m":{"case":"与格","number":"複数","gender":"男性"},"g":"彼"},{"t":"καὶ","l":"καί","k":"カイ","p":"conj","g":"そして"},{"t":"εἶπεν","l":"λέγω","k":"エイペン","p":"verb","m":{"person":"3人称","tense":"アオリスト","voice":"能動態","mood":"直説法"},"g":"言う"},{"t":"Οὐκ","l":"οὐ","k":"ウー","p":"adv","g":"〜ない"},{"t":"ἔρχεται","l":"ἔρχομαι","k":"エルケタイ","p":"verb","m":{"person":"3人称","tense":"現在","voice":"中動態","mood":"直説法"},"g":"来る"},{"t":"ἡ","l":"ὁ","k":"ヘー","p":"art","m":{"case":"主格","number":"単数","gender":"女性"},"g":"その"},{"t":"βασιλεία","l":"βασιλεία","k":"バシレイア","p":"noun","m":{"case":"主格","number":"単数","gender":"女性"},"g":"王国"},{"t":"τοῦ","l":"ὁ","k":"トウ","p":"art","m":{"case":"属格","number":"単数","gender":"男性"},"g":"その"},{"t":"θεοῦ","l":"θεός","k":"セウー","p":"noun","m":{"case":"属格","number":"単数","gender":"男性"},"g":"神"},{"t":"μετὰ","l":"μετά","k":"メタ","p":"prep","g":"〜と共に"},{"t":"παρατηρήσεως","l":"παρατήρησις","k":"パラテーレーセオース","p":"noun","m":{"case":"属格","number":"単数","gender":"女性"}}]},{"verse":21,"words":[{"t":"οὐδὲ","l":"οὐδέ","k":"ウーデ","p":"conj","g":"〜もない"},{"t":"ἐροῦσιν","l":"λέγω","k":"エロウシン","p":"verb","m":{"person":"3人称","tense":"未来","voice":"能動態","mood":"直説法"},"g":"言う"},{"t":"Ἰδοὺ","l":"ἰδού","k":"イドウ","p":"part","g":"見よ"},{"t":"ὧδε","l":"ὧδε","k":"オーデ","p":"adv","g":"ここに"},{"t":"ἤ","l":"ἤ","k":"エー","p":"conj","g":"または"},{"t":"⸀Ἐκεῖ","l":"ἐκεῖ","k":"エケイ","p":"adv","g":"そこに"},{"t":"ἰδοὺ","l":"ἰδού","k":"イドウ","p":"part","g":"見よ"},{"t":"γὰρ","l":"γάρ","k":"ガル","p":"conj","g":"なぜなら"},{"t":"ἡ","l":"ὁ","k":"ヘー","p":"art","m":{"case":"主格","number":"単数","gender":"女性"},"g":"その"},{"t":"βασιλεία","l":"βασιλεία","k":"バシレイア","p":"noun","m":{"case":"主格","number":"単数","gender":"女性"},"g":"王国"},{"t":"τοῦ","l":"ὁ","k":"トウ","p":"art","m":{"case":"属格","number":"単数","gender":"男性"},"g":"その"},{"t":"θεοῦ","l":"θεός","k":"セウー","p":"noun","m":{"case":"属格","number":"単数","gender":"男性"},"g":"神"},{"t":"ἐντὸς","l":"ἐντός","k":"エントス","p":"prep","g":"〜の内に"},{"t":"ὑμῶν","l":"σύ","k":"フモーン","p":"pers","m":{"case":"属格","number":"複数"},"g":"あなた"},{"t":"ἐστιν","l":"εἰμί","k":"エスティン","p":"verb","m":{"person":"3人称","tense":"現在","voice":"能動態","mood":"直説法"},"g":"〜である"}]},{"verse":22,"words":[{"t":"Εἶπεν","l":"λέγω","k":"エイペン","p":"verb","m":{"person":"3人称","tense":"アオリスト","voice":"能動態","mood":"直説法"},"g":"言う"},{"t":"δὲ","l":"δέ","k":"デ","p":"conj","g":"しかし"},{"t":"πρὸς","l":"πρός","k":"プロス","p":"prep","g":"〜に向かって"},{"t":"τοὺς","l":"ὁ","k":"トウス","p":"art","m":{"case":"対格","number":"複数","gender":"男性"},"g":"その"},{"t":"μαθητάς","l":"μαθητής","k":"マセータス","p":"noun","m":{"case":"対格","number":"複数","gender":"男性"},"g":"弟子"},{"t":"Ἐλεύσονται","l":"ἔρχομαι","k":"エレウソンタイ","p":"verb","m":{"person":"3人称","tense":"未来","voice":"中動態","mood":"直説法"},"g":"来る"},{"t":"ἡμέραι","l":"ἡμέρα","k":"ヘーメライ","p":"noun","m":{"case":"主格","number":"複数","gender":"女性"},"g":"日"},{"t":"ὅτε","l":"ὅτε","k":"ホテ","p":"adv","g":"〜の時"},{"t":"ἐπιθυμήσετε","l":"ἐπιθυμέω","k":"エピシュメーセテ","p":"verb","m":{"person":"2人称","tense":"未来","voice":"能動態","mood":"直説法"}},{"t":"μίαν","l":"εἷς","k":"ミアン","p":"adj","m":{"case":"対格","number":"単数","gender":"女性"},"g":"一つ"},{"t":"τῶν","l":"ὁ","k":"トーン","p":"art","m":{"case":"属格","number":"複数","gender":"女性"},"g":"その"},{"t":"ἡμερῶν","l":"ἡμέρα","k":"ヘーメローン","p":"noun","m":{"case":"属格","number":"複数","gender":"女性"},"g":"日"},{"t":"τοῦ","l":"ὁ","k":"トウ","p":"art","m":{"case":"属格","number":"単数","gender":"男性"},"g":"その"},{"t":"υἱοῦ","l":"υἱός","k":"ウイウー","p":"noun","m":{"case":"属格","number":"単数","gender":"男性"},"g":"息子"},{"t":"τοῦ","l":"ὁ","k":"トウ","p":"art","m":{"case":"属格","number":"単数","gender":"男性"},"g":"その"},{"t":"ἀνθρώπου","l":"ἄνθρωπος","k":"アンスローポウ","p":"noun","m":{"case":"属格","number":"単数","gender":"男性"},"g":"人"},{"t":"ἰδεῖν","l":"ὁράω","k":"イデイン","p":"verb","m":{"tense":"アオリスト","voice":"能動態","mood":"不定詞"},"g":"見る"},{"t":"καὶ","l":"καί","k":"カイ","p":"conj","g":"そして"},{"t":"οὐκ","l":"οὐ","k":"ウー","p":"adv","g":"〜ない"},{"t":"ὄψεσθε","l":"ὁράω","k":"オプセスセ","p":"verb","m":{"person":"2人称","tense":"未来","voice":"中動態","mood":"直説法"},"g":"見る"}]},{"verse":23,"words":[{"t":"καὶ","l":"καί","k":"カイ","p":"conj","g":"そして"},{"t":"ἐροῦσιν","l":"λέγω","k":"エロウシン","p":"verb","m":{"person":"3人称","tense":"未来","voice":"能動態","mood":"直説法"},"g":"言う"},{"t":"ὑμῖν","l":"σύ","k":"フミン","p":"pers","m":{"case":"与格","number":"複数"},"g":"あなた"},{"t":"Ἰδοὺ","l":"ἰδού","k":"イドウ","p":"part","g":"見よ"},{"t":"⸂ἐκεῖ","l":"ἐκεῖ","k":"エケイ","p":"adv","g":"そこに"},{"t":"Ἰδοὺ","l":"ἰδού","k":"イドウ","p":"part","g":"見よ"},{"t":"ὧδε⸃","l":"ὧδε","k":"オーデ","p":"adv","g":"ここに"},{"t":"μὴ","l":"μή","k":"メー","p":"adv","g":"〜ない"},{"t":"ἀπέλθητε","l":"ἀπέρχομαι","k":"アペルセーテ","p":"verb","m":{"person":"2人称","tense":"アオリスト","voice":"能動態","mood":"接続法"},"g":"去る"},{"t":"μηδὲ","l":"μηδέ","k":"メーデ","p":"conj","g":"〜もない"},{"t":"διώξητε","l":"διώκω","k":"ディオークセーテ","p":"verb","m":{"person":"2人称","tense":"アオリスト","voice":"能動態","mood":"接続法"}}]},{"verse":24,"words":[{"t":"ὥσπερ","l":"ὥσπερ","k":"ホースペル","p":"conj"},{"t":"γὰρ","l":"γάρ","k":"ガル","p":"conj","g":"なぜなら"},{"t":"ἡ","l":"ὁ","k":"ヘー","p":"art","m":{"case":"主格","number":"単数","gender":"女性"},"g":"その"},{"t":"⸀ἀστραπὴ","l":"ἀστραπή","k":"アストラペー","p":"noun","m":{"case":"主格","number":"単数","gender":"女性"}},{"t":"ἀστράπτουσα","l":"ἀστράπτω","k":"アストラプトウサ","p":"verb","m":{"tense":"現在","voice":"能動態","mood":"分詞","case":"主格","number":"単数","gender":"女性"}},{"t":"ἐκ","l":"ἐκ","k":"エク","p":"prep","g":"〜から"},{"t":"τῆς","l":"ὁ","k":"テース","p":"art","m":{"case":"属格","number":"単数","gender":"女性"},"g":"その"},{"t":"⸂ὑπὸ","l":"ὑπό","k":"フポ","p":"prep","g":"〜によって"},{"t":"τὸν⸃","l":"ὁ","k":"トン","p":"art","m":{"case":"対格","number":"単数","gender":"男性"},"g":"その"},{"t":"οὐρανὸν","l":"οὐρανός","k":"ウーラノン","p":"noun","m":{"case":"対格","number":"単数","gender":"男性"},"g":"天"},{"t":"εἰς","l":"εἰς","k":"エイス","p":"prep","g":"〜の中へ"},{"t":"τὴν","l":"ὁ","k":"テーン","p":"art","m":{"case":"対格","number":"単数","gender":"女性"},"g":"その"},{"t":"ὑπ’","l":"ὑπό","k":"フポ","p":"prep","g":"〜によって"},{"t":"οὐρανὸν","l":"οὐρανός","k":"ウーラノン","p":"noun","m":{"case":"対格","number":"単数","gender":"男性"},"g":"天"},{"t":"λάμπει","l":"λάμπω","k":"ラムペイ","p":"verb","m":{"person":"3人称","tense":"現在","voice":"能動態","mood":"直説法"}},{"t":"οὕτως","l":"οὕτω(ς)","k":"ウートース","p":"adv"},{"t":"ἔσται","l":"εἰμί","k":"エスタイ","p":"verb","m":{"person":"3人称","tense":"未来","voice":"中動態","mood":"直説法"},"g":"〜である"},{"t":"ὁ","l":"ὁ","k":"ホ","p":"art","m":{"case":"主格","number":"単数","gender":"男性"},"g":"その"},{"t":"υἱὸς","l":"υἱός","k":"ウイオス","p":"noun","m":{"case":"主格","number":"単数","gender":"男性"},"g":"息子"},{"t":"τοῦ","l":"ὁ","k":"トウ","p":"art","m":{"case":"属格","number":"単数","gender":"男性"},"g":"その"},{"t":"ἀνθρώπου","l":"ἄνθρωπος","k":"アンスローポウ","p":"noun","m":{"case":"属格","number":"単数","gender":"男性"},"g":"人"},{"t":"⸂ἐν","l":"ἐν","k":"エン","p":"prep","g":"〜の中に"},{"t":"τῇ","l":"ὁ","k":"テー","p":"art","m":{"case":"与格","number":"単数","gender":"女性"},"g":"その"},{"t":"ἡμέρᾳ","l":"ἡμέρα","k":"ヘーメラ","p":"noun","m":{"case":"与格","number":"単数","gender":"女性"},"g":"日"},{"t":"αὐτοῦ⸃","l":"αὐτός","k":"アウトウ","p":"pers","m":{"case":"属格","number":"単数","gender":"男性"},"g":"彼"}]},{"verse":25,"words":[{"t":"πρῶτον","l":"πρῶτος","k":"プロートン","p":"adj","m":{"case":"対格","number":"単数","gender":"中性"},"g":"第一の"},{"t":"δὲ","l":"δέ","k":"デ","p":"conj","g":"しかし"},{"t":"δεῖ","l":"δέω","k":"デイ","p":"verb","m":{"person":"3人称","tense":"現在","voice":"能動態","mood":"直説法"}},{"t":"αὐτὸν","l":"αὐτός","k":"アウトン","p":"pers","m":{"case":"対格","number":"単数","gender":"男性"},"g":"彼"},{"t":"πολλὰ","l":"πολύς","k":"ポルラ","p":"adj","m":{"case":"対格","number":"複数","gender":"中性"},"g":"多くの"},{"t":"παθεῖν","l":"πάσχω","k":"パセイン","p":"verb","m":{"tense":"アオリスト","voice":"能動態","mood":"不定詞"}},{"t":"καὶ","l":"καί","k":"カイ","p":"conj","g":"そして"},{"t":"ἀποδοκιμασθῆναι","l":"ἀποδοκιμάζω","k":"アポドキマスセーナイ","p":"verb","m":{"tense":"アオリスト","voice":"受動態","mood":"不定詞"}},{"t":"ἀπὸ","l":"ἀπό","k":"アポ","p":"prep","g":"〜から"},{"t":"τῆς","l":"ὁ","k":"テース","p":"art","m":{"case":"属格","number":"単数","gender":"女性"},"g":"その"},{"t":"γενεᾶς","l":"γενεά","k":"ゲネアス","p":"noun","m":{"case":"属格","number":"単数","gender":"女性"}},{"t":"ταύτης","l":"οὗτος","k":"タウテース","p":"dem","m":{"case":"属格","number":"単数","gender":"女性"},"g":"この"}]},{"verse":26,"words":[{"t":"καὶ","l":"καί","k":"カイ","p":"conj","g":"そして"},{"t":"καθὼς","l":"καθώς","k":"カソース","p":"conj","g":"〜のように"},{"t":"ἐγένετο","l":"γίνομαι","k":"エゲネト","p":"verb","m":{"person":"3人称","tense":"アオリスト","voice":"中動態","mood":"直説法"},"g":"〜になる"},{"t":"ἐν","l":"ἐν","k":"エン","p":"prep","g":"〜の中に"},{"t":"ταῖς","l":"ὁ","k":"タイス","p":"art","m":{"case":"与格","number":"複数","gender":"女性"},"g":"その"},{"t":"ἡμέραις","l":"ἡμέρα","k":"ヘーメライス","p":"noun","m":{"case":"与格","number":"複数","gender":"女性"},"g":"日"},{"t":"Νῶε","l":"Νῶε","k":"ノーエ","p":"noun","m":{"case":"属格","number":"単数","gender":"男性"}},{"t":"οὕτως","l":"οὕτω(ς)","k":"ウートース","p":"adv"},{"t":"ἔσται","l":"εἰμί","k":"エスタイ","p":"verb","m":{"person":"3人称","tense":"未来","voice":"中動態","mood":"直説法"},"g":"〜である"},{"t":"καὶ","l":"καί","k":"カイ","p":"adv","g":"そして"},{"t":"ἐν","l":"ἐν","k":"エン","p":"prep","g":"〜の中に"},{"t":"ταῖς","l":"ὁ","k":"タイス","p":"art","m":{"case":"与格","number":"複数","gender":"女性"},"g":"その"},{"t":"ἡμέραις","l":"ἡμέρα","k":"ヘーメライス","p":"noun","m":{"case":"与格","number":"複数","gender":"女性"},"g":"日"},{"t":"τοῦ","l":"ὁ","k":"トウ","p":"art","m":{"case":"属格","number":"単数","gender":"男性"},"g":"その"},{"t":"υἱοῦ","l":"υἱός","k":"ウイウー","p":"noun","m":{"case":"属格","number":"単数","gender":"男性"},"g":"息子"},{"t":"τοῦ","l":"ὁ","k":"トウ","p":"art","m":{"case":"属格","number":"単数","gender":"男性"},"g":"その"},{"t":"ἀνθρώπου","l":"ἄνθρωπος","k":"アンスローポウ","p":"noun","m":{"case":"属格","number":"単数","gender":"男性"},"g":"人"}]},{"verse":27,"words":[{"t":"ἤσθιον","l":"ἐσθίω","k":"エースシオン","p":"verb","m":{"person":"3人称","tense":"未完了","voice":"能動態","mood":"直説法"},"g":"食べる"},{"t":"ἔπινον","l":"πίνω","k":"エピノン","p":"verb","m":{"person":"3人称","tense":"未完了","voice":"能動態","mood":"直説法"},"g":"飲む"},{"t":"ἐγάμουν","l":"γαμέω","k":"エガモウン","p":"verb","m":{"person":"3人称","tense":"未完了","voice":"能動態","mood":"直説法"}},{"t":"⸀ἐγαμίζοντο","l":"γαμίζω","k":"エガミゾント","p":"verb","m":{"person":"3人称","tense":"未完了","voice":"受動態","mood":"直説法"}},{"t":"ἄχρι","l":"ἄχρι","k":"アクリ","p":"prep","g":"〜まで"},{"t":"ἧς","l":"ὅς","k":"エース","p":"rel","m":{"case":"属格","number":"単数","gender":"女性"},"g":"〜ところの"},{"t":"ἡμέρας","l":"ἡμέρα","k":"ヘーメラス","p":"noun","m":{"case":"属格","number":"単数","gender":"女性"},"g":"日"},{"t":"εἰσῆλθεν","l":"εἰσέρχομαι","k":"エイセールセン","p":"verb","m":{"person":"3人称","tense":"アオリスト","voice":"能動態","mood":"直説法"},"g":"入る"},{"t":"Νῶε","l":"Νῶε","k":"ノーエ","p":"noun","m":{"case":"主格","number":"単数","gender":"男性"}},{"t":"εἰς","l":"εἰς","k":"エイス","p":"prep","g":"〜の中へ"},{"t":"τὴν","l":"ὁ","k":"テーン","p":"art","m":{"case":"対格","number":"単数","gender":"女性"},"g":"その"},{"t":"κιβωτόν","l":"κιβωτός","k":"キボートン","p":"noun","m":{"case":"対格","number":"単数","gender":"女性"}},{"t":"καὶ","l":"καί","k":"カイ","p":"conj","g":"そして"},{"t":"ἦλθεν","l":"ἔρχομαι","k":"エールセン","p":"verb","m":{"person":"3人称","tense":"アオリスト","voice":"能動態","mood":"直説法"},"g":"来る"},{"t":"ὁ","l":"ὁ","k":"ホ","p":"art","m":{"case":"主格","number":"単数","gender":"男性"},"g":"その"},{"t":"κατακλυσμὸς","l":"κατακλυσμός","k":"カタクリュスモス","p":"noun","m":{"case":"主格","number":"単数","gender":"男性"}},{"t":"καὶ","l":"καί","k":"カイ","p":"conj","g":"そして"},{"t":"ἀπώλεσεν","l":"ἀπόλλυμι","k":"アポーレセン","p":"verb","m":{"person":"3人称","tense":"アオリスト","voice":"能動態","mood":"直説法"},"g":"滅ぼす"},{"t":"⸀πάντας","l":"πᾶς","k":"パンタス","p":"adj","m":{"case":"対格","number":"複数","gender":"男性"},"g":"すべての"}]},{"verse":28,"words":[{"t":"ὁμοίως","l":"ὁμοίως","k":"ホモイオース","p":"adv"},{"t":"⸀καθὼς","l":"καθώς","k":"カソース","p":"conj","g":"〜のように"},{"t":"ἐγένετο","l":"γίνομαι","k":"エゲネト","p":"verb","m":{"person":"3人称","tense":"アオリスト","voice":"中動態","mood":"直説法"},"g":"〜になる"},{"t":"ἐν","l":"ἐν","k":"エン","p":"prep","g":"〜の中に"},{"t":"ταῖς","l":"ὁ","k":"タイス","p":"art","m":{"case":"与格","number":"複数","gender":"女性"},"g":"その"},{"t":"ἡμέραις","l":"ἡμέρα","k":"ヘーメライス","p":"noun","m":{"case":"与格","number":"複数","gender":"女性"},"g":"日"},{"t":"Λώτ","l":"Λώτ","k":"ロート","p":"noun","m":{"case":"属格","number":"単数","gender":"男性"}},{"t":"ἤσθιον","l":"ἐσθίω","k":"エースシオン","p":"verb","m":{"person":"3人称","tense":"未完了","voice":"能動態","mood":"直説法"},"g":"食べる"},{"t":"ἔπινον","l":"πίνω","k":"エピノン","p":"verb","m":{"person":"3人称","tense":"未完了","voice":"能動態","mood":"直説法"},"g":"飲む"},{"t":"ἠγόραζον","l":"ἀγοράζω","k":"エーゴラゾン","p":"verb","m":{"person":"3人称","tense":"未完了","voice":"能動態","mood":"直説法"}},{"t":"ἐπώλουν","l":"πωλέω","k":"エポーロウン","p":"verb","m":{"person":"3人称","tense":"未完了","voice":"能動態","mood":"直説法"}},{"t":"ἐφύτευον","l":"φυτεύω","k":"エフュテウオン","p":"verb","m":{"person":"3人称","tense":"未完了","voice":"能動態","mood":"直説法"}},{"t":"ᾠκοδόμουν","l":"οἰκοδομέω","k":"オーコドモウン","p":"verb","m":{"person":"3人称","tense":"未完了","voice":"能動態","mood":"直説法"}}]},{"verse":29,"words":[{"t":"ᾗ","l":"ὅς","k":"エー","p":"rel","m":{"case":"与格","number":"単数","gender":"女性"},"g":"〜ところの"},{"t":"δὲ","l":"δέ","k":"デ","p":"conj","g":"しかし"},{"t":"ἡμέρᾳ","l":"ἡμέρα","k":"ヘーメラ","p":"noun","m":{"case":"与格","number":"単数","gender":"女性"},"g":"日"},{"t":"ἐξῆλθεν","l":"ἐξέρχομαι","k":"エクセールセン","p":"verb","m":{"person":"3人称","tense":"アオリスト","voice":"能動態","mood":"直説法"},"g":"出る"},{"t":"Λὼτ","l":"Λώτ","k":"ロート","p":"noun","m":{"case":"主格","number":"単数","gender":"男性"}},{"t":"ἀπὸ","l":"ἀπό","k":"アポ","p":"prep","g":"〜から"},{"t":"Σοδόμων","l":"Σόδομα","k":"ソドモーン","p":"noun","m":{"case":"属格","number":"複数","gender":"中性"}},{"t":"ἔβρεξεν","l":"βρέχω","k":"エブレクセン","p":"verb","m":{"person":"3人称","tense":"アオリスト","voice":"能動態","mood":"直説法"}},{"t":"πῦρ","l":"πῦρ","k":"ピュル","p":"noun","m":{"case":"対格","number":"単数","gender":"中性"},"g":"火"},{"t":"καὶ","l":"καί","k":"カイ","p":"conj","g":"そして"},{"t":"θεῖον","l":"θεῖον","k":"セイオン","p":"noun","m":{"case":"対格","number":"単数","gender":"中性"}},{"t":"ἀπ’","l":"ἀπό","k":"アポ","p":"prep","g":"〜から"},{"t":"οὐρανοῦ","l":"οὐρανός","k":"ウーラノウ","p":"noun","m":{"case":"属格","number":"単数","gender":"男性"},"g":"天"},{"t":"καὶ","l":"καί","k":"カイ","p":"conj","g":"そして"},{"t":"ἀπώλεσεν","l":"ἀπόλλυμι","k":"アポーレセン","p":"verb","m":{"person":"3人称","tense":"アオリスト","voice":"能動態","mood":"直説法"},"g":"滅ぼす"},{"t":"⸀πάντας","l":"πᾶς","k":"パンタス","p":"adj","m":{"case":"対格","number":"複数","gender":"男性"},"g":"すべての"}]},{"verse":30,"words":[{"t":"κατὰ","l":"κατά","k":"カタ","p":"prep","g":"〜に従って"},{"t":"⸂τὰ","l":"ὁ","k":"タ","p":"art","m":{"case":"対格","number":"複数","gender":"中性"},"g":"その"},{"t":"αὐτὰ⸃","l":"αὐτός","k":"アウタ","p":"adj","m":{"case":"対格","number":"複数","gender":"中性"},"g":"彼"},{"t":"ἔσται","l":"εἰμί","k":"エスタイ","p":"verb","m":{"person":"3人称","tense":"未来","voice":"中動態","mood":"直説法"},"g":"〜である"},{"t":"ᾗ","l":"ὅς","k":"エー","p":"rel","m":{"case":"与格","number":"単数","gender":"女性"},"g":"〜ところの"},{"t":"ἡμέρᾳ","l":"ἡμέρα","k":"ヘーメラ","p":"noun","m":{"case":"与格","number":"単数","gender":"女性"},"g":"日"},{"t":"ὁ","l":"ὁ","k":"ホ","p":"art","m":{"case":"主格","number":"単数","gender":"男性"},"g":"その"},{"t":"υἱὸς","l":"υἱός","k":"ウイオス","p":"noun","m":{"case":"主格","number":"単数","gender":"男性"},"g":"息子"},{"t":"τοῦ","l":"ὁ","k":"トウ","p":"art","m":{"case":"属格","number":"単数","gender":"男性"},"g":"その"},{"t":"ἀνθρώπου","l":"ἄνθρωπος","k":"アンスローポウ","p":"noun","m":{"case":"属格","number":"単数","gender":"男性"},"g":"人"},{"t":"ἀποκαλύπτεται","l":"ἀποκαλύπτω","k":"アポカリュプテタイ","p":"verb","m":{"person":"3人称","tense":"現在","voice":"受動態","mood":"直説法"}}]},{"verse":31,"words":[{"t":"ἐν","l":"ἐν","k":"エン","p":"prep","g":"〜の中に"},{"t":"ἐκείνῃ","l":"ἐκεῖνος","k":"エケイネー","p":"dem","m":{"case":"与格","number":"単数","gender":"女性"},"g":"あの"},{"t":"τῇ","l":"ὁ","k":"テー","p":"art","m":{"case":"与格","number":"単数","gender":"女性"},"g":"その"},{"t":"ἡμέρᾳ","l":"ἡμέρα","k":"ヘーメラ","p":"noun","m":{"case":"与格","number":"単数","gender":"女性"},"g":"日"},{"t":"ὃς","l":"ὅς","k":"ホス","p":"rel","m":{"case":"主格","number":"単数","gender":"男性"},"g":"〜ところの"},{"t":"ἔσται","l":"εἰμί","k":"エスタイ","p":"verb","m":{"person":"3人称","tense":"未来","voice":"中動態","mood":"直説法"},"g":"〜である"},{"t":"ἐπὶ","l":"ἐπί","k":"エピ","p":"prep","g":"〜の上に"},{"t":"τοῦ","l":"ὁ","k":"トウ","p":"art","m":{"case":"属格","number":"単数","gender":"中性"},"g":"その"},{"t":"δώματος","l":"δῶμα","k":"ドーマトス","p":"noun","m":{"case":"属格","number":"単数","gender":"中性"}},{"t":"καὶ","l":"καί","k":"カイ","p":"conj","g":"そして"},{"t":"τὰ","l":"ὁ","k":"タ","p":"art","m":{"case":"主格","number":"複数","gender":"中性"},"g":"その"},{"t":"σκεύη","l":"σκεῦος","k":"スケウエー","p":"noun","m":{"case":"主格","number":"複数","gender":"中性"}},{"t":"αὐτοῦ","l":"αὐτός","k":"アウトウ","p":"pers","m":{"case":"属格","number":"単数","gender":"男性"},"g":"彼"},{"t":"ἐν","l":"ἐν","k":"エン","p":"prep","g":"〜の中に"},{"t":"τῇ","l":"ὁ","k":"テー","p":"art","m":{"case":"与格","number":"単数","gender":"女性"},"g":"その"},{"t":"οἰκίᾳ","l":"οἰκία","k":"オイキア","p":"noun","m":{"case":"与格","number":"単数","gender":"女性"},"g":"家"},{"t":"μὴ","l":"μή","k":"メー","p":"adv","g":"〜ない"},{"t":"καταβάτω","l":"καταβαίνω","k":"カタバトー","p":"verb","m":{"person":"3人称","tense":"アオリスト","voice":"能動態"},"g":"下る"},{"t":"ἆραι","l":"αἴρω","k":"アライ","p":"verb","m":{"tense":"アオリスト","voice":"能動態","mood":"不定詞"},"g":"取り上げる"},{"t":"αὐτά","l":"αὐτός","k":"アウタ","p":"pers","m":{"case":"対格","number":"複数","gender":"中性"},"g":"彼"},{"t":"καὶ","l":"καί","k":"カイ","p":"conj","g":"そして"},{"t":"ὁ","l":"ὁ","k":"ホ","p":"art","m":{"case":"主格","number":"単数","gender":"男性"},"g":"その"},{"t":"⸀ἐν","l":"ἐν","k":"エン","p":"prep","g":"〜の中に"},{"t":"ἀγρῷ","l":"ἀγρός","k":"アグロー","p":"noun","m":{"case":"与格","number":"単数","gender":"男性"},"g":"畑"},{"t":"ὁμοίως","l":"ὁμοίως","k":"ホモイオース","p":"adv"},{"t":"μὴ","l":"μή","k":"メー","p":"adv","g":"〜ない"},{"t":"ἐπιστρεψάτω","l":"ἐπιστρέφω","k":"エピストレプサトー","p":"verb","m":{"person":"3人称","tense":"アオリスト","voice":"能動態"}},{"t":"εἰς","l":"εἰς","k":"エイス","p":"prep","g":"〜の中へ"},{"t":"τὰ","l":"ὁ","k":"タ","p":"art","m":{"case":"対格","number":"複数","gender":"中性"},"g":"その"},{"t":"ὀπίσω","l":"ὀπίσω","k":"オピソー","p":"adv","g":"〜の後ろに"}]},{"verse":32,"words":[{"t":"μνημονεύετε","l":"μνημονεύω","k":"ムネーモネウエテ","p":"verb","m":{"person":"2人称","tense":"現在","voice":"能動態"}},{"t":"τῆς","l":"ὁ","k":"テース","p":"art","m":{"case":"属格","number":"単数","gender":"女性"},"g":"その"},{"t":"γυναικὸς","l":"γυνή","k":"ギュナイコス","p":"noun","m":{"case":"属格","number":"単数","gender":"女性"},"g":"女"},{"t":"Λώτ","l":"Λώτ","k":"ロート","p":"noun","m":{"case":"属格","number":"単数","gender":"男性"}}]},{"verse":33,"words":[{"t":"ὃς","l":"ὅς","k":"ホス","p":"rel","m":{"case":"主格","number":"単数","gender":"男性"},"g":"〜ところの"},{"t":"ἐὰν","l":"ἐάν","k":"エアン","p":"part","g":"もし〜なら"},{"t":"ζητήσῃ","l":"ζητέω","k":"ゼーテーセー","p":"verb","m":{"person":"3人称","tense":"アオリスト","voice":"能動態","mood":"接続法"},"g":"求める"},{"t":"τὴν","l":"ὁ","k":"テーン","p":"art","m":{"case":"対格","number":"単数","gender":"女性"},"g":"その"},{"t":"ψυχὴν","l":"ψυχή","k":"プシュケーン","p":"noun","m":{"case":"対格","number":"単数","gender":"女性"},"g":"魂"},{"t":"αὐτοῦ","l":"αὐτός","k":"アウトウ","p":"pers","m":{"case":"属格","number":"単数","gender":"男性"},"g":"彼"},{"t":"⸀περιποιήσασθαι","l":"περιποιέομαι","k":"ペリポイエーサスサイ","p":"verb","m":{"tense":"アオリスト","voice":"中動態","mood":"不定詞"}},{"t":"ἀπολέσει","l":"ἀπόλλυμι","k":"アポレセイ","p":"verb","m":{"person":"3人称","tense":"未来","voice":"能動態","mood":"直説法"},"g":"滅ぼす"},{"t":"αὐτήν","l":"αὐτός","k":"アウテーン","p":"pers","m":{"case":"対格","number":"単数","gender":"女性"},"g":"彼"},{"t":"⸂ὃς","l":"ὅς","k":"ホス","p":"rel","m":{"case":"主格","number":"単数","gender":"男性"},"g":"〜ところの"},{"t":"δ’","l":"δέ","k":"デ","p":"conj","g":"しかし"},{"t":"ἂν⸃","l":"ἄν","k":"アン","p":"part"},{"t":"⸀ἀπολέσῃ","l":"ἀπόλλυμι","k":"アポレセー","p":"verb","m":{"person":"3人称","tense":"アオリスト","voice":"能動態","mood":"接続法"},"g":"滅ぼす"},{"t":"ζῳογονήσει","l":"ζῳογονέω","k":"ゾーオゴネーセイ","p":"verb","m":{"person":"3人称","tense":"未来","voice":"能動態","mood":"直説法"}},{"t":"αὐτήν","l":"αὐτός","k":"アウテーン","p":"pers","m":{"case":"対格","number":"単数","gender":"女性"},"g":"彼"}]},{"verse":34,"words":[{"t":"λέγω","l":"λέγω","k":"レゴー","p":"verb","m":{"person":"1人称","tense":"現在","voice":"能動態","mood":"直説法"},"g":"言う"},{"t":"ὑμῖν","l":"σύ","k":"フミン","p":"pers","m":{"case":"与格","number":"複数"},"g":"あなた"},{"t":"ταύτῃ","l":"οὗτος","k":"タウテー","p":"dem","m":{"case":"与格","number":"単数","gender":"女性"},"g":"この"},{"t":"τῇ","l":"ὁ","k":"テー","p":"art","m":{"case":"与格","number":"単数","gender":"女性"},"g":"その"},{"t":"νυκτὶ","l":"νύξ","k":"ニュクティ","p":"noun","m":{"case":"与格","number":"単数","gender":"女性"},"g":"夜"},{"t":"ἔσονται","l":"εἰμί","k":"エソンタイ","p":"verb","m":{"person":"3人称","tense":"未来","voice":"中動態","mood":"直説法"},"g":"〜である"},{"t":"δύο","l":"δύο","k":"デュオ","p":"adj","m":{"case":"主格","number":"複数","gender":"男性"},"g":"二"},{"t":"ἐπὶ","l":"ἐπί","k":"エピ","p":"prep","g":"〜の上に"},{"t":"κλίνης","l":"κλίνη","k":"クリネース","p":"noun","m":{"case":"属格","number":"単数","gender":"女性"}},{"t":"μιᾶς","l":"εἷς","k":"ミアス","p":"adj","m":{"case":"属格","number":"単数","gender":"女性"},"g":"一つ"},{"t":"⸀ὁ","l":"ὁ","k":"ホ","p":"art","m":{"case":"主格","number":"単数","gender":"男性"},"g":"その"},{"t":"εἷς","l":"εἷς","k":"エイス","p":"adj","m":{"case":"主格","number":"単数","gender":"男性"},"g":"一つ"},{"t":"παραλημφθήσεται","l":"παραλαμβάνω","k":"パラレームフセーセタイ","p":"verb","m":{"person":"3人称","tense":"未来","voice":"受動態","mood":"直説法"},"g":"受け取る"},{"t":"καὶ","l":"καί","k":"カイ","p":"conj","g":"そして"},{"t":"ὁ","l":"ὁ","k":"ホ","p":"art","m":{"case":"主格","number":"単数","gender":"男性"},"g":"その"},{"t":"ἕτερος","l":"ἕτερος","k":"ヘテロス","p":"adj","m":{"case":"主格","number":"単数","gender":"男性"},"g":"他の"},{"t":"ἀφεθήσεται","l":"ἀφίημι","k":"アフェセーセタイ","p":"verb","m":{"person":"3人称","tense":"未来","voice":"受動態","mood":"直説法"},"g":"赦す"}]},{"verse":35,"words":[{"t":"⸂ἔσονται","l":"εἰμί","k":"エソンタイ","p":"verb","m":{"person":"3人称","tense":"未来","voice":"中動態","mood":"直説法"},"g":"〜である"},{"t":"δύο⸃","l":"δύο","k":"デュオ","p":"adj","m":{"case":"主格","number":"複数","gender":"女性"},"g":"二"},{"t":"ἀλήθουσαι","l":"ἀλήθω","k":"アレーソウサイ","p":"verb","m":{"tense":"現在","voice":"能動態","mood":"分詞","case":"主格","number":"複数","gender":"女性"}},{"t":"ἐπὶ","l":"ἐπί","k":"エピ","p":"prep","g":"〜の上に"},{"t":"τὸ","l":"ὁ","k":"ト","p":"art","m":{"case":"対格","number":"単数","gender":"中性"},"g":"その"},{"t":"αὐτό","l":"αὐτός","k":"アウト","p":"adj","m":{"case":"対格","number":"単数","gender":"中性"},"g":"彼"},{"t":"⸀ἡ","l":"ὁ","k":"ヘー","p":"art","m":{"case":"主格","number":"単数","gender":"女性"},"g":"その"},{"t":"μία","l":"εἷς","k":"ミア","p":"adj","m":{"case":"主格","number":"単数","gender":"女性"},"g":"一つ"},{"t":"παραλημφθήσεται","l":"παραλαμβάνω","k":"パラレームフセーセタイ","p":"verb","m":{"person":"3人称","tense":"未来","voice":"受動態","mood":"直説法"},"g":"受け取る"},{"t":"⸂ἡ","l":"ὁ","k":"ヘー","p":"art","m":{"case":"主格","number":"単数","gender":"女性"},"g":"その"},{"t":"δὲ⸃","l":"δέ","k":"デ","p":"conj","g":"しかし"},{"t":"ἑτέρα","l":"ἕτερος","k":"ヘテラ","p":"adj","m":{"case":"主格","number":"単数","gender":"女性"},"g":"他の"},{"t":"⸀ἀφεθήσεται","l":"ἀφίημι","k":"アフェセーセタイ","p":"verb","m":{"person":"3人称","tense":"未来","voice":"受動態","mood":"直説法"},"g":"赦す"}]},{"verse":37,"words":[{"t":"καὶ","l":"καί","k":"カイ","p":"conj","g":"そして"},{"t":"ἀποκριθέντες","l":"ἀποκρίνομαι","k":"アポクリセンテス","p":"verb","m":{"tense":"アオリスト","voice":"受動態","mood":"分詞","case":"主格","number":"複数","gender":"男性"},"g":"答える"},{"t":"λέγουσιν","l":"λέγω","k":"レゴウシン","p":"verb","m":{"person":"3人称","tense":"現在","voice":"能動態","mood":"直説法"},"g":"言う"},{"t":"αὐτῷ","l":"αὐτός","k":"アウトー","p":"pers","m":{"case":"与格","number":"単数","gender":"男性"},"g":"彼"},{"t":"Ποῦ","l":"ποῦ","k":"ポウ","p":"adv","g":"どこに"},{"t":"κύριε","l":"κύριος","k":"キュリエ","p":"noun","m":{"case":"呼格","number":"単数","gender":"男性"},"g":"主人"},{"t":"ὁ","l":"ὁ","k":"ホ","p":"art","m":{"case":"主格","number":"単数","gender":"男性"},"g":"その"},{"t":"δὲ","l":"δέ","k":"デ","p":"conj","g":"しかし"},{"t":"εἶπεν","l":"λέγω","k":"エイペン","p":"verb","m":{"person":"3人称","tense":"アオリスト","voice":"能動態","mood":"直説法"},"g":"言う"},{"t":"αὐτοῖς","l":"αὐτός","k":"アウトイス","p":"pers","m":{"case":"与格","number":"複数","gender":"男性"},"g":"彼"},{"t":"Ὅπου","l":"ὅπου","k":"ホポウ","p":"conj","g":"〜する所"},{"t":"τὸ","l":"ὁ","k":"ト","p":"art","m":{"case":"主格","number":"単数","gender":"中性"},"g":"その"},{"t":"σῶμα","l":"σῶμα","k":"ソーマ","p":"noun","m":{"case":"主格","number":"単数","gender":"中性"},"g":"体"},{"t":"ἐκεῖ","l":"ἐκεῖ","k":"エケイ","p":"adv","g":"そこに"},{"t":"⸂καὶ","l":"καί","k":"カイ","p":"adv","g":"そして"},{"t":"οἱ","l":"ὁ","k":"オイ","p":"art","m":{"case":"主格","number":"複数","gender":"男性"},"g":"その"},{"t":"ἀετοὶ","l":"ἀετός","k":"アエトイ","p":"noun","m":{"case":"主格","number":"複数","gender":"男性"}},{"t":"ἐπισυναχθήσονται⸃","l":"ἐπισυνάγω","k":"エピシュナクセーソンタイ","p":"verb","m":{"person":"3人称","tense":"未来","voice":"受動態","mood":"直説法"}}]}]