[{"verse":1,"words":[{"t":"Καὶ","l":"καί","k":"カイ","p":"conj","g":"そして"},{"t":"ἐγένετο","l":"γίνομαι","k":"エゲネト","p":"verb","m":{"person":"3人称","tense":"アオリスト","voice":"中動態","mood":"直説法"},"g":"〜になる"},{"t":"ἐν","l":"ἐν","k":"エン","p":"prep","g":"〜の中に"},{"t":"μιᾷ","l":"εἷς","k":"ミア","p":"adj","m":{"case":"与格","number":"単数","gender":"女性"},"g":"一つ"},{"t":"τῶν","l":"ὁ","k":"トーン","p":"art","m":{"case":"属格","number":"複数","gender":"女性"},"g":"その"},{"t":"⸀ἡμερῶν","l":"ἡμέρα","k":"ヘーメローン","p":"noun","m":{"case":"属格","number":"複数","gender":"女性"},"g":"日"},{"t":"διδάσκοντος","l":"διδάσκω","k":"ディダスコントス","p":"verb","m":{"tense":"現在","voice":"能動態","mood":"分詞","case":"属格","number":"単数","gender":"男性"},"g":"教える"},{"t":"αὐτοῦ","l":"αὐτός","k":"アウトウ","p":"pers","m":{"case":"属格","number":"単数","gender":"男性"},"g":"彼"},{"t":"τὸν","l":"ὁ","k":"トン","p":"art","m":{"case":"対格","number":"単数","gender":"男性"},"g":"その"},{"t":"λαὸν","l":"λαός","k":"ラオン","p":"noun","m":{"case":"対格","number":"単数","gender":"男性"},"g":"民"},{"t":"ἐν","l":"ἐν","k":"エン","p":"prep","g":"〜の中に"},{"t":"τῷ","l":"ὁ","k":"トー","p":"art","m":{"case":"与格","number":"単数","gender":"中性"},"g":"その"},{"t":"ἱερῷ","l":"ἱερός","k":"ヒエロー","p":"adj","m":{"case":"与格","number":"単数","gender":"中性"},"g":"聖なる"},{"t":"καὶ","l":"καί","k":"カイ","p":"conj","g":"そして"},{"t":"εὐαγγελιζομένου","l":"εὐαγγελίζω","k":"エウアンゲリゾメノウ","p":"verb","m":{"tense":"現在","voice":"中動態","mood":"分詞","case":"属格","number":"単数","gender":"男性"},"g":"福音を伝える"},{"t":"ἐπέστησαν","l":"ἐφίστημι","k":"エペステーサン","p":"verb","m":{"person":"3人称","tense":"アオリスト","voice":"能動態","mood":"直説法"},"g":"近づく"},{"t":"οἱ","l":"ὁ","k":"オイ","p":"art","m":{"case":"主格","number":"複数","gender":"男性"},"g":"その"},{"t":"⸀ἀρχιερεῖς","l":"ἀρχιερεύς","k":"アルキエレイス","p":"noun","m":{"case":"主格","number":"複数","gender":"男性"},"g":"大祭司"},{"t":"καὶ","l":"καί","k":"カイ","p":"conj","g":"そして"},{"t":"οἱ","l":"ὁ","k":"オイ","p":"art","m":{"case":"主格","number":"複数","gender":"男性"},"g":"その"},{"t":"γραμματεῖς","l":"γραμματεύς","k":"グラムマテイス","p":"noun","m":{"case":"主格","number":"複数","gender":"男性"},"g":"律法学者"},{"t":"σὺν","l":"σύν","k":"シュン","p":"prep","g":"〜と共に"},{"t":"τοῖς","l":"ὁ","k":"トイス","p":"art","m":{"case":"与格","number":"複数","gender":"男性"},"g":"その"},{"t":"πρεσβυτέροις","l":"πρεσβύτερος","k":"プレスビュテロイス","p":"adj","m":{"case":"与格","number":"複数","gender":"男性"},"g":"長老"}]},{"verse":2,"words":[{"t":"καὶ","l":"καί","k":"カイ","p":"conj","g":"そして"},{"t":"εἶπαν","l":"λέγω","k":"エイパン","p":"verb","m":{"person":"3人称","tense":"アオリスト","voice":"能動態","mood":"直説法"},"g":"言う"},{"t":"⸂λέγοντες","l":"λέγω","k":"レゴンテス","p":"verb","m":{"tense":"現在","voice":"能動態","mood":"分詞","case":"主格","number":"複数","gender":"男性"},"g":"言う"},{"t":"πρὸς","l":"πρός","k":"プロス","p":"prep","g":"〜に向かって"},{"t":"αὐτόν⸃","l":"αὐτός","k":"アウトン","p":"pers","m":{"case":"対格","number":"単数","gender":"男性"},"g":"彼"},{"t":"Εἰπὸν","l":"λέγω","k":"エイポン","p":"verb","m":{"person":"2人称","tense":"アオリスト","voice":"能動態"},"g":"言う"},{"t":"ἡμῖν","l":"ἐγώ","k":"ヘーミン","p":"pers","m":{"case":"与格","number":"複数"},"g":"私"},{"t":"ἐν","l":"ἐν","k":"エン","p":"prep","g":"〜の中に"},{"t":"ποίᾳ","l":"ποῖος","k":"ポイア","p":"inter","m":{"case":"与格","number":"単数","gender":"女性"},"g":"どのような"},{"t":"ἐξουσίᾳ","l":"ἐξουσία","k":"エクソウシア","p":"noun","m":{"case":"与格","number":"単数","gender":"女性"},"g":"権威"},{"t":"ταῦτα","l":"οὗτος","k":"タウタ","p":"dem","m":{"case":"対格","number":"複数","gender":"中性"},"g":"この"},{"t":"ποιεῖς","l":"ποιέω","k":"ポイエイス","p":"verb","m":{"person":"2人称","tense":"現在","voice":"能動態","mood":"直説法"},"g":"する"},{"t":"ἢ","l":"ἤ","k":"エー","p":"conj","g":"または"},{"t":"τίς","l":"τίς","k":"ティス","p":"inter","m":{"case":"主格","number":"単数","gender":"男性"},"g":"誰"},{"t":"ἐστιν","l":"εἰμί","k":"エスティン","p":"verb","m":{"person":"3人称","tense":"現在","voice":"能動態","mood":"直説法"},"g":"〜である"},{"t":"ὁ","l":"ὁ","k":"ホ","p":"art","m":{"case":"主格","number":"単数","gender":"男性"},"g":"その"},{"t":"δούς","l":"δίδωμι","k":"ドウス","p":"verb","m":{"tense":"アオリスト","voice":"能動態","mood":"分詞","case":"主格","number":"単数","gender":"男性"},"g":"与える"},{"t":"σοι","l":"σύ","k":"ソイ","p":"pers","m":{"case":"与格","number":"単数"},"g":"あなた"},{"t":"τὴν","l":"ὁ","k":"テーン","p":"art","m":{"case":"対格","number":"単数","gender":"女性"},"g":"その"},{"t":"ἐξουσίαν","l":"ἐξουσία","k":"エクソウシアン","p":"noun","m":{"case":"対格","number":"単数","gender":"女性"},"g":"権威"},{"t":"ταύτην","l":"οὗτος","k":"タウテーン","p":"dem","m":{"case":"対格","number":"単数","gender":"女性"},"g":"この"}]},{"verse":3,"words":[{"t":"ἀποκριθεὶς","l":"ἀποκρίνομαι","k":"アポクリセイス","p":"verb","m":{"tense":"アオリスト","voice":"受動態","mood":"分詞","case":"主格","number":"単数","gender":"男性"},"g":"答える"},{"t":"δὲ","l":"δέ","k":"デ","p":"conj","g":"しかし"},{"t":"εἶπεν","l":"λέγω","k":"エイペン","p":"verb","m":{"person":"3人称","tense":"アオリスト","voice":"能動態","mood":"直説法"},"g":"言う"},{"t":"πρὸς","l":"πρός","k":"プロス","p":"prep","g":"〜に向かって"},{"t":"αὐτούς","l":"αὐτός","k":"アウトウス","p":"pers","m":{"case":"対格","number":"複数","gender":"男性"},"g":"彼"},{"t":"Ἐρωτήσω","l":"ἐρωτάω","k":"エローテーソー","p":"verb","m":{"person":"1人称","tense":"未来","voice":"能動態","mood":"直説法"},"g":"尋ねる"},{"t":"ὑμᾶς","l":"σύ","k":"フマス","p":"pers","m":{"case":"対格","number":"複数"},"g":"あなた"},{"t":"⸀κἀγὼ","l":"κἀγώ","k":"カゴー","p":"pers","m":{"case":"主格","number":"単数"},"g":"私も"},{"t":"λόγον","l":"λόγος","k":"ロゴン","p":"noun","m":{"case":"対格","number":"単数","gender":"男性"},"g":"ことば"},{"t":"καὶ","l":"καί","k":"カイ","p":"conj","g":"そして"},{"t":"εἴπατέ","l":"λέγω","k":"エイパテ","p":"verb","m":{"person":"2人称","tense":"アオリスト","voice":"能動態"},"g":"言う"},{"t":"μοι","l":"ἐγώ","k":"モイ","p":"pers","m":{"case":"与格","number":"単数"},"g":"私"}]},{"verse":4,"words":[{"t":"Τὸ","l":"ὁ","k":"ト","p":"art","m":{"case":"主格","number":"単数","gender":"中性"},"g":"その"},{"t":"βάπτισμα","l":"βάπτισμα","k":"バプティスマ","p":"noun","m":{"case":"主格","number":"単数","gender":"中性"},"g":"バプテスマ"},{"t":"Ἰωάννου","l":"Ἰωάννης","k":"イオーアンノウ","p":"noun","m":{"case":"属格","number":"単数","gender":"男性"},"g":"ヨハネ"},{"t":"ἐξ","l":"ἐκ","k":"エク","p":"prep","g":"〜から"},{"t":"οὐρανοῦ","l":"οὐρανός","k":"ウーラノウ","p":"noun","m":{"case":"属格","number":"単数","gender":"男性"},"g":"天"},{"t":"ἦν","l":"εἰμί","k":"エーン","p":"verb","m":{"person":"3人称","tense":"未完了","voice":"能動態","mood":"直説法"},"g":"〜である"},{"t":"ἢ","l":"ἤ","k":"エー","p":"conj","g":"または"},{"t":"ἐξ","l":"ἐκ","k":"エク","p":"prep","g":"〜から"},{"t":"ἀνθρώπων","l":"ἄνθρωπος","k":"アンスローポーン","p":"noun","m":{"case":"属格","number":"複数","gender":"男性"},"g":"人"}]},{"verse":5,"words":[{"t":"οἱ","l":"ὁ","k":"オイ","p":"art","m":{"case":"主格","number":"複数","gender":"男性"},"g":"その"},{"t":"δὲ","l":"δέ","k":"デ","p":"conj","g":"しかし"},{"t":"συνελογίσαντο","l":"συλλογίζομαι","k":"シュネロギサント","p":"verb","m":{"person":"3人称","tense":"アオリスト","voice":"中動態","mood":"直説法"}},{"t":"πρὸς","l":"πρός","k":"プロス","p":"prep","g":"〜に向かって"},{"t":"ἑαυτοὺς","l":"ἑαυτοῦ","k":"ヘアウトウス","p":"pers","m":{"case":"対格","number":"複数","gender":"男性"},"g":"自分自身"},{"t":"λέγοντες","l":"λέγω","k":"レゴンテス","p":"verb","m":{"tense":"現在","voice":"能動態","mood":"分詞","case":"主格","number":"複数","gender":"男性"},"g":"言う"},{"t":"ὅτι","l":"ὅτι","k":"ホティ","p":"conj","g":"〜ということ"},{"t":"Ἐὰν","l":"ἐάν","k":"エアン","p":"conj","g":"もし〜なら"},{"t":"εἴπωμεν","l":"λέγω","k":"エイポーメン","p":"verb","m":{"person":"1人称","tense":"アオリスト","voice":"能動態","mood":"接続法"},"g":"言う"},{"t":"Ἐξ","l":"ἐκ","k":"エク","p":"prep","g":"〜から"},{"t":"οὐρανοῦ","l":"οὐρανός","k":"ウーラノウ","p":"noun","m":{"case":"属格","number":"単数","gender":"男性"},"g":"天"},{"t":"ἐρεῖ","l":"λέγω","k":"エレイ","p":"verb","m":{"person":"3人称","tense":"未来","voice":"能動態","mood":"直説法"},"g":"言う"},{"t":"Διὰ","l":"διά","k":"ディア","p":"prep","g":"〜を通して"},{"t":"τί","l":"τίς","k":"ティ","p":"inter","m":{"case":"対格","number":"単数","gender":"中性"},"g":"誰"},{"t":"οὐκ","l":"οὐ","k":"ウー","p":"adv","g":"〜ない"},{"t":"ἐπιστεύσατε","l":"πιστεύω","k":"エピステウサテ","p":"verb","m":{"person":"2人称","tense":"アオリスト","voice":"能動態","mood":"直説法"},"g":"信じる"},{"t":"αὐτῷ","l":"αὐτός","k":"アウトー","p":"pers","m":{"case":"与格","number":"単数","gender":"男性"},"g":"彼"}]},{"verse":6,"words":[{"t":"ἐὰν","l":"ἐάν","k":"エアン","p":"conj","g":"もし〜なら"},{"t":"δὲ","l":"δέ","k":"デ","p":"conj","g":"しかし"},{"t":"εἴπωμεν","l":"λέγω","k":"エイポーメン","p":"verb","m":{"person":"1人称","tense":"アオリスト","voice":"能動態","mood":"接続法"},"g":"言う"},{"t":"Ἐξ","l":"ἐκ","k":"エク","p":"prep","g":"〜から"},{"t":"ἀνθρώπων","l":"ἄνθρωπος","k":"アンスローポーン","p":"noun","m":{"case":"属格","number":"複数","gender":"男性"},"g":"人"},{"t":"⸂ὁ","l":"ὁ","k":"ホ","p":"art","m":{"case":"主格","number":"単数","gender":"男性"},"g":"その"},{"t":"λαὸς","l":"λαός","k":"ラオス","p":"noun","m":{"case":"主格","number":"単数","gender":"男性"},"g":"民"},{"t":"ἅπας⸃","l":"ἅπας","k":"ハパス","p":"adj","m":{"case":"主格","number":"単数","gender":"男性"},"g":"すべての"},{"t":"καταλιθάσει","l":"καταλιθάζω","k":"カタリサセイ","p":"verb","m":{"person":"3人称","tense":"未来","voice":"能動態","mood":"直説法"}},{"t":"ἡμᾶς","l":"ἐγώ","k":"ヘーマス","p":"pers","m":{"case":"対格","number":"複数"},"g":"私"},{"t":"πεπεισμένος","l":"πείθω","k":"ペペイスメノス","p":"verb","m":{"voice":"受動態","mood":"分詞","case":"主格","number":"単数","gender":"男性"},"g":"説得する"},{"t":"γάρ","l":"γάρ","k":"ガル","p":"conj","g":"なぜなら"},{"t":"ἐστιν","l":"εἰμί","k":"エスティン","p":"verb","m":{"person":"3人称","tense":"現在","voice":"能動態","mood":"直説法"},"g":"〜である"},{"t":"Ἰωάννην","l":"Ἰωάννης","k":"イオーアンネーン","p":"noun","m":{"case":"対格","number":"単数","gender":"男性"},"g":"ヨハネ"},{"t":"προφήτην","l":"προφήτης","k":"プロフェーテーン","p":"noun","m":{"case":"対格","number":"単数","gender":"男性"},"g":"預言者"},{"t":"εἶναι","l":"εἰμί","k":"エイナイ","p":"verb","m":{"tense":"現在","voice":"能動態","mood":"不定詞"},"g":"〜である"}]},{"verse":7,"words":[{"t":"καὶ","l":"καί","k":"カイ","p":"conj","g":"そして"},{"t":"ἀπεκρίθησαν","l":"ἀποκρίνομαι","k":"アペクリセーサン","p":"verb","m":{"person":"3人称","tense":"アオリスト","voice":"受動態","mood":"直説法"},"g":"答える"},{"t":"μὴ","l":"μή","k":"メー","p":"adv","g":"〜ない"},{"t":"εἰδέναι","l":"οἶδα","k":"エイデナイ","p":"verb","m":{"voice":"能動態","mood":"不定詞"},"g":"知る"},{"t":"πόθεν","l":"πόθεν","k":"ポセン","p":"adv","g":"どこから"}]},{"verse":8,"words":[{"t":"καὶ","l":"καί","k":"カイ","p":"conj","g":"そして"},{"t":"ὁ","l":"ὁ","k":"ホ","p":"art","m":{"case":"主格","number":"単数","gender":"男性"},"g":"その"},{"t":"Ἰησοῦς","l":"Ἰησοῦς","k":"イエーソウス","p":"noun","m":{"case":"主格","number":"単数","gender":"男性"},"g":"イエス"},{"t":"εἶπεν","l":"λέγω","k":"エイペン","p":"verb","m":{"person":"3人称","tense":"アオリスト","voice":"能動態","mood":"直説法"},"g":"言う"},{"t":"αὐτοῖς","l":"αὐτός","k":"アウトイス","p":"pers","m":{"case":"与格","number":"複数","gender":"男性"},"g":"彼"},{"t":"Οὐδὲ","l":"οὐδέ","k":"ウーデ","p":"adv","g":"〜もない"},{"t":"ἐγὼ","l":"ἐγώ","k":"エゴー","p":"pers","m":{"case":"主格","number":"単数"},"g":"私"},{"t":"λέγω","l":"λέγω","k":"レゴー","p":"verb","m":{"person":"1人称","tense":"現在","voice":"能動態","mood":"直説法"},"g":"言う"},{"t":"ὑμῖν","l":"σύ","k":"フミン","p":"pers","m":{"case":"与格","number":"複数"},"g":"あなた"},{"t":"ἐν","l":"ἐν","k":"エン","p":"prep","g":"〜の中に"},{"t":"ποίᾳ","l":"ποῖος","k":"ポイア","p":"inter","m":{"case":"与格","number":"単数","gender":"女性"},"g":"どのような"},{"t":"ἐξουσίᾳ","l":"ἐξουσία","k":"エクソウシア","p":"noun","m":{"case":"与格","number":"単数","gender":"女性"},"g":"権威"},{"t":"ταῦτα","l":"οὗτος","k":"タウタ","p":"dem","m":{"case":"対格","number":"複数","gender":"中性"},"g":"この"},{"t":"ποιῶ","l":"ποιέω","k":"ポイオー","p":"verb","m":{"person":"1人称","tense":"現在","voice":"能動態","mood":"直説法"},"g":"する"}]},{"verse":9,"words":[{"t":"Ἤρξατο","l":"ἄρχω","k":"エールクサト","p":"verb","m":{"person":"3人称","tense":"アオリスト","voice":"中動態","mood":"直説法"},"g":"始める"},{"t":"δὲ","l":"δέ","k":"デ","p":"conj","g":"しかし"},{"t":"πρὸς","l":"πρός","k":"プロス","p":"prep","g":"〜に向かって"},{"t":"τὸν","l":"ὁ","k":"トン","p":"art","m":{"case":"対格","number":"単数","gender":"男性"},"g":"その"},{"t":"λαὸν","l":"λαός","k":"ラオン","p":"noun","m":{"case":"対格","number":"単数","gender":"男性"},"g":"民"},{"t":"λέγειν","l":"λέγω","k":"レゲイン","p":"verb","m":{"tense":"現在","voice":"能動態","mood":"不定詞"},"g":"言う"},{"t":"τὴν","l":"ὁ","k":"テーン","p":"art","m":{"case":"対格","number":"単数","gender":"女性"},"g":"その"},{"t":"παραβολὴν","l":"παραβολή","k":"パラボレーン","p":"noun","m":{"case":"対格","number":"単数","gender":"女性"},"g":"たとえ"},{"t":"ταύτην","l":"οὗτος","k":"タウテーン","p":"dem","m":{"case":"対格","number":"単数","gender":"女性"},"g":"この"},{"t":"⸀Ἄνθρωπος","l":"ἄνθρωπος","k":"アンスローポス","p":"noun","m":{"case":"主格","number":"単数","gender":"男性"},"g":"人"},{"t":"ἐφύτευσεν","l":"φυτεύω","k":"エフュテウセン","p":"verb","m":{"person":"3人称","tense":"アオリスト","voice":"能動態","mood":"直説法"}},{"t":"ἀμπελῶνα","l":"ἀμπελών","k":"アムペローナ","p":"noun","m":{"case":"対格","number":"単数","gender":"男性"},"g":"ぶどう園"},{"t":"καὶ","l":"καί","k":"カイ","p":"conj","g":"そして"},{"t":"ἐξέδετο","l":"ἐκδίδωμι","k":"エクセデト","p":"verb","m":{"person":"3人称","tense":"アオリスト","voice":"中動態","mood":"直説法"}},{"t":"αὐτὸν","l":"αὐτός","k":"アウトン","p":"pers","m":{"case":"対格","number":"単数","gender":"男性"},"g":"彼"},{"t":"γεωργοῖς","l":"γεωργός","k":"ゲオールゴイス","p":"noun","m":{"case":"与格","number":"複数","gender":"男性"},"g":"農夫"},{"t":"καὶ","l":"καί","k":"カイ","p":"conj","g":"そして"},{"t":"ἀπεδήμησεν","l":"ἀποδημέω","k":"アペデーメーセン","p":"verb","m":{"person":"3人称","tense":"アオリスト","voice":"能動態","mood":"直説法"}},{"t":"χρόνους","l":"χρόνος","k":"クロノウス","p":"noun","m":{"case":"対格","number":"複数","gender":"男性"},"g":"時間"},{"t":"ἱκανούς","l":"ἱκανός","k":"ヒカノウス","p":"adj","m":{"case":"対格","number":"複数","gender":"男性"},"g":"十分な"}]},{"verse":10,"words":[{"t":"⸀καὶ","l":"καί","k":"カイ","p":"conj","g":"そして"},{"t":"καιρῷ","l":"καιρός","k":"カイロー","p":"noun","m":{"case":"与格","number":"単数","gender":"男性"},"g":"時"},{"t":"ἀπέστειλεν","l":"ἀποστέλλω","k":"アペステイレン","p":"verb","m":{"person":"3人称","tense":"アオリスト","voice":"能動態","mood":"直説法"},"g":"遣わす"},{"t":"πρὸς","l":"πρός","k":"プロス","p":"prep","g":"〜に向かって"},{"t":"τοὺς","l":"ὁ","k":"トウス","p":"art","m":{"case":"対格","number":"複数","gender":"男性"},"g":"その"},{"t":"γεωργοὺς","l":"γεωργός","k":"ゲオールゴウス","p":"noun","m":{"case":"対格","number":"複数","gender":"男性"},"g":"農夫"},{"t":"δοῦλον","l":"δοῦλος","k":"ドウロン","p":"noun","m":{"case":"対格","number":"単数","gender":"男性"},"g":"奴隷"},{"t":"ἵνα","l":"ἵνα","k":"ヒナ","p":"conj","g":"〜するために"},{"t":"ἀπὸ","l":"ἀπό","k":"アポ","p":"prep","g":"〜から"},{"t":"τοῦ","l":"ὁ","k":"トウ","p":"art","m":{"case":"属格","number":"単数","gender":"男性"},"g":"その"},{"t":"καρποῦ","l":"καρπός","k":"カルポウ","p":"noun","m":{"case":"属格","number":"単数","gender":"男性"},"g":"実"},{"t":"τοῦ","l":"ὁ","k":"トウ","p":"art","m":{"case":"属格","number":"単数","gender":"男性"},"g":"その"},{"t":"ἀμπελῶνος","l":"ἀμπελών","k":"アムペローノス","p":"noun","m":{"case":"属格","number":"単数","gender":"男性"},"g":"ぶどう園"},{"t":"⸀δώσουσιν","l":"δίδωμι","k":"ドーソウシン","p":"verb","m":{"person":"3人称","tense":"未来","voice":"能動態","mood":"直説法"},"g":"与える"},{"t":"αὐτῷ","l":"αὐτός","k":"アウトー","p":"pers","m":{"case":"与格","number":"単数","gender":"男性"},"g":"彼"},{"t":"οἱ","l":"ὁ","k":"オイ","p":"art","m":{"case":"主格","number":"複数","gender":"男性"},"g":"その"},{"t":"δὲ","l":"δέ","k":"デ","p":"conj","g":"しかし"},{"t":"γεωργοὶ","l":"γεωργός","k":"ゲオールゴイ","p":"noun","m":{"case":"主格","number":"複数","gender":"男性"},"g":"農夫"},{"t":"⸂ἐξαπέστειλαν","l":"ἐξαποστέλλω","k":"エクサペステイラン","p":"verb","m":{"person":"3人称","tense":"アオリスト","voice":"能動態","mood":"直説法"},"g":"送り出す"},{"t":"αὐτὸν","l":"αὐτός","k":"アウトン","p":"pers","m":{"case":"対格","number":"単数","gender":"男性"},"g":"彼"},{"t":"δείραντες⸃","l":"δέρω","k":"デイランテス","p":"verb","m":{"tense":"アオリスト","voice":"能動態","mood":"分詞","case":"主格","number":"複数","gender":"男性"},"g":"打つ"},{"t":"κενόν","l":"κενός","k":"ケノン","p":"adj","m":{"case":"対格","number":"単数","gender":"男性"},"g":"空の"}]},{"verse":11,"words":[{"t":"καὶ","l":"καί","k":"カイ","p":"conj","g":"そして"},{"t":"προσέθετο","l":"προστίθημι","k":"プロセセト","p":"verb","m":{"person":"3人称","tense":"アオリスト","voice":"中動態","mood":"直説法"},"g":"加える"},{"t":"⸂ἕτερον","l":"ἕτερος","k":"ヘテロン","p":"adj","m":{"case":"対格","number":"単数","gender":"男性"},"g":"他の"},{"t":"πέμψαι⸃","l":"πέμπω","k":"ペムプサイ","p":"verb","m":{"tense":"アオリスト","voice":"能動態","mood":"不定詞"},"g":"送る"},{"t":"δοῦλον","l":"δοῦλος","k":"ドウロン","p":"noun","m":{"case":"対格","number":"単数","gender":"男性"},"g":"奴隷"},{"t":"οἱ","l":"ὁ","k":"オイ","p":"art","m":{"case":"主格","number":"複数","gender":"男性"},"g":"その"},{"t":"δὲ","l":"δέ","k":"デ","p":"conj","g":"しかし"},{"t":"κἀκεῖνον","l":"κἀκεῖνος","k":"カケイノン","p":"dem","m":{"case":"対格","number":"単数","gender":"男性"},"g":"あの人も"},{"t":"δείραντες","l":"δέρω","k":"デイランテス","p":"verb","m":{"tense":"アオリスト","voice":"能動態","mood":"分詞","case":"主格","number":"複数","gender":"男性"},"g":"打つ"},{"t":"καὶ","l":"καί","k":"カイ","p":"conj","g":"そして"},{"t":"ἀτιμάσαντες","l":"ἀτιμάζω","k":"アティマサンテス","p":"verb","m":{"tense":"アオリスト","voice":"能動態","mood":"分詞","case":"主格","number":"複数","gender":"男性"}},{"t":"ἐξαπέστειλαν","l":"ἐξαποστέλλω","k":"エクサペステイラン","p":"verb","m":{"person":"3人称","tense":"アオリスト","voice":"能動態","mood":"直説法"},"g":"送り出す"},{"t":"κενόν","l":"κενός","k":"ケノン","p":"adj","m":{"case":"対格","number":"単数","gender":"男性"},"g":"空の"}]},{"verse":12,"words":[{"t":"καὶ","l":"καί","k":"カイ","p":"conj","g":"そして"},{"t":"προσέθετο","l":"προστίθημι","k":"プロセセト","p":"verb","m":{"person":"3人称","tense":"アオリスト","voice":"中動態","mood":"直説法"},"g":"加える"},{"t":"⸂τρίτον","l":"τρίτον","k":"トリトン","p":"adv"},{"t":"πέμψαι⸃","l":"πέμπω","k":"ペムプサイ","p":"verb","m":{"tense":"アオリスト","voice":"能動態","mood":"不定詞"},"g":"送る"},{"t":"οἱ","l":"ὁ","k":"オイ","p":"art","m":{"case":"主格","number":"複数","gender":"男性"},"g":"その"},{"t":"δὲ","l":"δέ","k":"デ","p":"conj","g":"しかし"},{"t":"καὶ","l":"καί","k":"カイ","p":"adv","g":"そして"},{"t":"τοῦτον","l":"οὗτος","k":"トウトン","p":"dem","m":{"case":"対格","number":"単数","gender":"男性"},"g":"この"},{"t":"τραυματίσαντες","l":"τραυματίζω","k":"トラウマティサンテス","p":"verb","m":{"tense":"アオリスト","voice":"能動態","mood":"分詞","case":"主格","number":"複数","gender":"男性"}},{"t":"ἐξέβαλον","l":"ἐκβάλλω","k":"エクセバロン","p":"verb","m":{"person":"3人称","tense":"アオリスト","voice":"能動態","mood":"直説法"},"g":"追い出す"}]},{"verse":13,"words":[{"t":"εἶπεν","l":"λέγω","k":"エイペン","p":"verb","m":{"person":"3人称","tense":"アオリスト","voice":"能動態","mood":"直説法"},"g":"言う"},{"t":"δὲ","l":"δέ","k":"デ","p":"conj","g":"しかし"},{"t":"ὁ","l":"ὁ","k":"ホ","p":"art","m":{"case":"主格","number":"単数","gender":"男性"},"g":"その"},{"t":"κύριος","l":"κύριος","k":"キュリオス","p":"noun","m":{"case":"主格","number":"単数","gender":"男性"},"g":"主人"},{"t":"τοῦ","l":"ὁ","k":"トウ","p":"art","m":{"case":"属格","number":"単数","gender":"男性"},"g":"その"},{"t":"ἀμπελῶνος","l":"ἀμπελών","k":"アムペローノス","p":"noun","m":{"case":"属格","number":"単数","gender":"男性"},"g":"ぶどう園"},{"t":"Τί","l":"τίς","k":"ティ","p":"inter","m":{"case":"対格","number":"単数","gender":"中性"},"g":"誰"},{"t":"ποιήσω","l":"ποιέω","k":"ポイエーソー","p":"verb","m":{"person":"1人称","tense":"アオリスト","voice":"能動態","mood":"接続法"},"g":"する"},{"t":"πέμψω","l":"πέμπω","k":"ペムプソー","p":"verb","m":{"person":"1人称","tense":"未来","voice":"能動態","mood":"直説法"},"g":"送る"},{"t":"τὸν","l":"ὁ","k":"トン","p":"art","m":{"case":"対格","number":"単数","gender":"男性"},"g":"その"},{"t":"υἱόν","l":"υἱός","k":"ウイオン","p":"noun","m":{"case":"対格","number":"単数","gender":"男性"},"g":"息子"},{"t":"μου","l":"ἐγώ","k":"モウ","p":"pers","m":{"case":"属格","number":"単数"},"g":"私"},{"t":"τὸν","l":"ὁ","k":"トン","p":"art","m":{"case":"対格","number":"単数","gender":"男性"},"g":"その"},{"t":"ἀγαπητόν","l":"ἀγαπητός","k":"アガペートン","p":"adj","m":{"case":"対格","number":"単数","gender":"男性"},"g":"愛する"},{"t":"ἴσως","l":"ἴσως","k":"イソース","p":"adv"},{"t":"⸀τοῦτον","l":"οὗτος","k":"トウトン","p":"dem","m":{"case":"対格","number":"単数","gender":"男性"},"g":"この"},{"t":"ἐντραπήσονται","l":"ἐντρέπω","k":"エントラペーソンタイ","p":"verb","m":{"person":"3人称","tense":"未来","voice":"受動態","mood":"直説法"}}]},{"verse":14,"words":[{"t":"ἰδόντες","l":"ὁράω","k":"イドンテス","p":"verb","m":{"tense":"アオリスト","voice":"能動態","mood":"分詞","case":"主格","number":"複数","gender":"男性"},"g":"見る"},{"t":"δὲ","l":"δέ","k":"デ","p":"conj","g":"しかし"},{"t":"αὐτὸν","l":"αὐτός","k":"アウトン","p":"pers","m":{"case":"対格","number":"単数","gender":"男性"},"g":"彼"},{"t":"οἱ","l":"ὁ","k":"オイ","p":"art","m":{"case":"主格","number":"複数","gender":"男性"},"g":"その"},{"t":"γεωργοὶ","l":"γεωργός","k":"ゲオールゴイ","p":"noun","m":{"case":"主格","number":"複数","gender":"男性"},"g":"農夫"},{"t":"διελογίζοντο","l":"διαλογίζομαι","k":"ディエロギゾント","p":"verb","m":{"person":"3人称","tense":"未完了","voice":"中動態","mood":"直説法"},"g":"考える"},{"t":"πρὸς","l":"πρός","k":"プロス","p":"prep","g":"〜に向かって"},{"t":"⸀ἀλλήλους","l":"ἀλλήλων","k":"アルレーロウス","p":"pers","m":{"case":"対格","number":"複数","gender":"男性"},"g":"互いに"},{"t":"λέγοντες","l":"λέγω","k":"レゴンテス","p":"verb","m":{"tense":"現在","voice":"能動態","mood":"分詞","case":"主格","number":"複数","gender":"男性"},"g":"言う"},{"t":"Οὗτός","l":"οὗτος","k":"ウートス","p":"dem","m":{"case":"主格","number":"単数","gender":"男性"},"g":"この"},{"t":"ἐστιν","l":"εἰμί","k":"エスティン","p":"verb","m":{"person":"3人称","tense":"現在","voice":"能動態","mood":"直説法"},"g":"〜である"},{"t":"ὁ","l":"ὁ","k":"ホ","p":"art","m":{"case":"主格","number":"単数","gender":"男性"},"g":"その"},{"t":"κληρονόμος","l":"κληρονόμος","k":"クレーロノモス","p":"noun","m":{"case":"主格","number":"単数","gender":"男性"},"g":"相続人"},{"t":"⸀ἀποκτείνωμεν","l":"ἀποκτείνω","k":"アポクテイノーメン","p":"verb","m":{"person":"1人称","tense":"アオリスト","voice":"能動態","mood":"接続法"},"g":"殺す"},{"t":"αὐτόν","l":"αὐτός","k":"アウトン","p":"pers","m":{"case":"対格","number":"単数","gender":"男性"},"g":"彼"},{"t":"ἵνα","l":"ἵνα","k":"ヒナ","p":"conj","g":"〜するために"},{"t":"ἡμῶν","l":"ἐγώ","k":"ヘーモーン","p":"pers","m":{"case":"属格","number":"複数"},"g":"私"},{"t":"γένηται","l":"γίνομαι","k":"ゲネータイ","p":"verb","m":{"person":"3人称","tense":"アオリスト","voice":"中動態","mood":"接続法"},"g":"〜になる"},{"t":"ἡ","l":"ὁ","k":"ヘー","p":"art","m":{"case":"主格","number":"単数","gender":"女性"},"g":"その"},{"t":"κληρονομία","l":"κληρονομία","k":"クレーロノミア","p":"noun","m":{"case":"主格","number":"単数","gender":"女性"},"g":"相続"}]},{"verse":15,"words":[{"t":"καὶ","l":"καί","k":"カイ","p":"conj","g":"そして"},{"t":"ἐκβαλόντες","l":"ἐκβάλλω","k":"エクバロンテス","p":"verb","m":{"tense":"アオリスト","voice":"能動態","mood":"分詞","case":"主格","number":"複数","gender":"男性"},"g":"追い出す"},{"t":"αὐτὸν","l":"αὐτός","k":"アウトン","p":"pers","m":{"case":"対格","number":"単数","gender":"男性"},"g":"彼"},{"t":"ἔξω","l":"ἔξω","k":"エクソー","p":"prep","g":"〜の外に"},{"t":"τοῦ","l":"ὁ","k":"トウ","p":"art","m":{"case":"属格","number":"単数","gender":"男性"},"g":"その"},{"t":"ἀμπελῶνος","l":"ἀμπελών","k":"アムペローノス","p":"noun","m":{"case":"属格","number":"単数","gender":"男性"},"g":"ぶどう園"},{"t":"ἀπέκτειναν","l":"ἀποκτείνω","k":"アペクテイナン","p":"verb","m":{"person":"3人称","tense":"アオリスト","voice":"能動態","mood":"直説法"},"g":"殺す"},{"t":"τί","l":"τίς","k":"ティ","p":"inter","m":{"case":"対格","number":"単数","gender":"中性"},"g":"誰"},{"t":"οὖν","l":"οὖν","k":"ウーン","p":"conj","g":"それゆえ"},{"t":"ποιήσει","l":"ποιέω","k":"ポイエーセイ","p":"verb","m":{"person":"3人称","tense":"未来","voice":"能動態","mood":"直説法"},"g":"する"},{"t":"αὐτοῖς","l":"αὐτός","k":"アウトイス","p":"pers","m":{"case":"与格","number":"複数","gender":"男性"},"g":"彼"},{"t":"ὁ","l":"ὁ","k":"ホ","p":"art","m":{"case":"主格","number":"単数","gender":"男性"},"g":"その"},{"t":"κύριος","l":"κύριος","k":"キュリオス","p":"noun","m":{"case":"主格","number":"単数","gender":"男性"},"g":"主人"},{"t":"τοῦ","l":"ὁ","k":"トウ","p":"art","m":{"case":"属格","number":"単数","gender":"男性"},"g":"その"},{"t":"ἀμπελῶνος","l":"ἀμπελών","k":"アムペローノス","p":"noun","m":{"case":"属格","number":"単数","gender":"男性"},"g":"ぶどう園"}]},{"verse":16,"words":[{"t":"ἐλεύσεται","l":"ἔρχομαι","k":"エレウセタイ","p":"verb","m":{"person":"3人称","tense":"未来","voice":"中動態","mood":"直説法"},"g":"来る"},{"t":"καὶ","l":"καί","k":"カイ","p":"conj","g":"そして"},{"t":"ἀπολέσει","l":"ἀπόλλυμι","k":"アポレセイ","p":"verb","m":{"person":"3人称","tense":"未来","voice":"能動態","mood":"直説法"},"g":"滅ぼす"},{"t":"τοὺς","l":"ὁ","k":"トウス","p":"art","m":{"case":"対格","number":"複数","gender":"男性"},"g":"その"},{"t":"γεωργοὺς","l":"γεωργός","k":"ゲオールゴウス","p":"noun","m":{"case":"対格","number":"複数","gender":"男性"},"g":"農夫"},{"t":"τούτους","l":"οὗτος","k":"トウトウス","p":"dem","m":{"case":"対格","number":"複数","gender":"男性"},"g":"この"},{"t":"καὶ","l":"καί","k":"カイ","p":"conj","g":"そして"},{"t":"δώσει","l":"δίδωμι","k":"ドーセイ","p":"verb","m":{"person":"3人称","tense":"未来","voice":"能動態","mood":"直説法"},"g":"与える"},{"t":"τὸν","l":"ὁ","k":"トン","p":"art","m":{"case":"対格","number":"単数","gender":"男性"},"g":"その"},{"t":"ἀμπελῶνα","l":"ἀμπελών","k":"アムペローナ","p":"noun","m":{"case":"対格","number":"単数","gender":"男性"},"g":"ぶどう園"},{"t":"ἄλλοις","l":"ἄλλος","k":"アルロイス","p":"adj","m":{"case":"与格","number":"複数","gender":"男性"},"g":"他の"},{"t":"ἀκούσαντες","l":"ἀκούω","k":"アコウサンテス","p":"verb","m":{"tense":"アオリスト","voice":"能動態","mood":"分詞","case":"主格","number":"複数","gender":"男性"},"g":"聞く"},{"t":"δὲ","l":"δέ","k":"デ","p":"conj","g":"しかし"},{"t":"εἶπαν","l":"λέγω","k":"エイパン","p":"verb","m":{"person":"3人称","tense":"アオリスト","voice":"能動態","mood":"直説法"},"g":"言う"},{"t":"Μὴ","l":"μή","k":"メー","p":"adv","g":"〜ない"},{"t":"γένοιτο","l":"γίνομαι","k":"ゲノイト","p":"verb","m":{"person":"3人称","tense":"アオリスト","voice":"中動態","mood":"希求法"},"g":"〜になる"}]},{"verse":17,"words":[{"t":"ὁ","l":"ὁ","k":"ホ","p":"art","m":{"case":"主格","number":"単数","gender":"男性"},"g":"その"},{"t":"δὲ","l":"δέ","k":"デ","p":"conj","g":"しかし"},{"t":"ἐμβλέψας","l":"ἐμβλέπω","k":"エムブレプサス","p":"verb","m":{"tense":"アオリスト","voice":"能動態","mood":"分詞","case":"主格","number":"単数","gender":"男性"}},{"t":"αὐτοῖς","l":"αὐτός","k":"アウトイス","p":"pers","m":{"case":"与格","number":"複数","gender":"男性"},"g":"彼"},{"t":"εἶπεν","l":"λέγω","k":"エイペン","p":"verb","m":{"person":"3人称","tense":"アオリスト","voice":"能動態","mood":"直説法"},"g":"言う"},{"t":"Τί","l":"τίς","k":"ティ","p":"inter","m":{"case":"主格","number":"単数","gender":"中性"},"g":"誰"},{"t":"οὖν","l":"οὖν","k":"ウーン","p":"conj","g":"それゆえ"},{"t":"ἐστιν","l":"εἰμί","k":"エスティン","p":"verb","m":{"person":"3人称","tense":"現在","voice":"能動態","mood":"直説法"},"g":"〜である"},{"t":"τὸ","l":"ὁ","k":"ト","p":"art","m":{"case":"主格","number":"単数","gender":"中性"},"g":"その"},{"t":"γεγραμμένον","l":"γράφω","k":"ゲグラムメノン","p":"verb","m":{"voice":"受動態","mood":"分詞","case":"主格","number":"単数","gender":"中性"},"g":"書く"},{"t":"τοῦτο","l":"οὗτος","k":"トウト","p":"dem","m":{"case":"主格","number":"単数","gender":"中性"},"g":"この"},{"t":"Λίθον","l":"λίθος","k":"リソン","p":"noun","m":{"case":"対格","number":"単数","gender":"男性"},"g":"石"},{"t":"ὃν","l":"ὅς","k":"ホン","p":"rel","m":{"case":"対格","number":"単数","gender":"男性"},"g":"〜ところの"},{"t":"ἀπεδοκίμασαν","l":"ἀποδοκιμάζω","k":"アペドキマサン","p":"verb","m":{"person":"3人称","tense":"アオリスト","voice":"能動態","mood":"直説法"}},{"t":"οἱ","l":"ὁ","k":"オイ","p":"art","m":{"case":"主格","number":"複数","gender":"男性"},"g":"その"},{"t":"οἰκοδομοῦντες","l":"οἰκοδομέω","k":"オイコドモウンテス","p":"verb","m":{"tense":"現在","voice":"能動態","mood":"分詞","case":"主格","number":"複数","gender":"男性"},"g":"建てる"},{"t":"οὗτος","l":"οὗτος","k":"ウートス","p":"dem","m":{"case":"主格","number":"単数","gender":"男性"},"g":"この"},{"t":"ἐγενήθη","l":"γίνομαι","k":"エゲネーセー","p":"verb","m":{"person":"3人称","tense":"アオリスト","voice":"受動態","mood":"直説法"},"g":"〜になる"},{"t":"εἰς","l":"εἰς","k":"エイス","p":"prep","g":"〜の中へ"},{"t":"κεφαλὴν","l":"κεφαλή","k":"ケファレーン","p":"noun","m":{"case":"対格","number":"単数","gender":"女性"},"g":"頭"},{"t":"γωνίας","l":"γωνία","k":"ゴーニアス","p":"noun","m":{"case":"属格","number":"単数","gender":"女性"}}]},{"verse":18,"words":[{"t":"πᾶς","l":"πᾶς","k":"パス","p":"adj","m":{"case":"主格","number":"単数","gender":"男性"},"g":"すべての"},{"t":"ὁ","l":"ὁ","k":"ホ","p":"art","m":{"case":"主格","number":"単数","gender":"男性"},"g":"その"},{"t":"πεσὼν","l":"πίπτω","k":"ペソーン","p":"verb","m":{"tense":"アオリスト","voice":"能動態","mood":"分詞","case":"主格","number":"単数","gender":"男性"},"g":"落ちる"},{"t":"ἐπ’","l":"ἐπί","k":"エピ","p":"prep","g":"〜の上に"},{"t":"ἐκεῖνον","l":"ἐκεῖνος","k":"エケイノン","p":"dem","m":{"case":"対格","number":"単数","gender":"男性"},"g":"あの"},{"t":"τὸν","l":"ὁ","k":"トン","p":"art","m":{"case":"対格","number":"単数","gender":"男性"},"g":"その"},{"t":"λίθον","l":"λίθος","k":"リソン","p":"noun","m":{"case":"対格","number":"単数","gender":"男性"},"g":"石"},{"t":"συνθλασθήσεται","l":"συνθλάομαι","k":"シュンスラスセーセタイ","p":"verb","m":{"person":"3人称","tense":"未来","voice":"受動態","mood":"直説法"}},{"t":"ἐφ’","l":"ἐπί","k":"エピ","p":"prep","g":"〜の上に"},{"t":"ὃν","l":"ὅς","k":"ホン","p":"rel","m":{"case":"対格","number":"単数","gender":"男性"},"g":"〜ところの"},{"t":"δ’","l":"δέ","k":"デ","p":"conj","g":"しかし"},{"t":"ἂν","l":"ἄν","k":"アン","p":"part","g":"〜かもしれない"},{"t":"πέσῃ","l":"πίπτω","k":"ペセー","p":"verb","m":{"person":"3人称","tense":"アオリスト","voice":"能動態","mood":"接続法"},"g":"落ちる"},{"t":"λικμήσει","l":"λικμάω","k":"リクメーセイ","p":"verb","m":{"person":"3人称","tense":"未来","voice":"能動態","mood":"直説法"}},{"t":"αὐτόν","l":"αὐτός","k":"アウトン","p":"pers","m":{"case":"対格","number":"単数","gender":"男性"},"g":"彼"}]},{"verse":19,"words":[{"t":"καὶ","l":"καί","k":"カイ","p":"conj","g":"そして"},{"t":"ἐζήτησαν","l":"ζητέω","k":"エゼーテーサン","p":"verb","m":{"person":"3人称","tense":"アオリスト","voice":"能動態","mood":"直説法"},"g":"求める"},{"t":"οἱ","l":"ὁ","k":"オイ","p":"art","m":{"case":"主格","number":"複数","gender":"男性"},"g":"その"},{"t":"⸂γραμματεῖς","l":"γραμματεύς","k":"グラムマテイス","p":"noun","m":{"case":"主格","number":"複数","gender":"男性"},"g":"律法学者"},{"t":"καὶ","l":"καί","k":"カイ","p":"conj","g":"そして"},{"t":"οἱ","l":"ὁ","k":"オイ","p":"art","m":{"case":"主格","number":"複数","gender":"男性"},"g":"その"},{"t":"ἀρχιερεῖς⸃","l":"ἀρχιερεύς","k":"アルキエレイス","p":"noun","m":{"case":"主格","number":"複数","gender":"男性"},"g":"大祭司"},{"t":"ἐπιβαλεῖν","l":"ἐπιβάλλω","k":"エピバレイン","p":"verb","m":{"tense":"アオリスト","voice":"能動態","mood":"不定詞"},"g":"手を置く"},{"t":"ἐπ’","l":"ἐπί","k":"エピ","p":"prep","g":"〜の上に"},{"t":"αὐτὸν","l":"αὐτός","k":"アウトン","p":"pers","m":{"case":"対格","number":"単数","gender":"男性"},"g":"彼"},{"t":"τὰς","l":"ὁ","k":"タス","p":"art","m":{"case":"対格","number":"複数","gender":"女性"},"g":"その"},{"t":"χεῖρας","l":"χείρ","k":"ケイラス","p":"noun","m":{"case":"対格","number":"複数","gender":"女性"},"g":"手"},{"t":"ἐν","l":"ἐν","k":"エン","p":"prep","g":"〜の中に"},{"t":"αὐτῇ","l":"αὐτός","k":"アウテー","p":"pers","m":{"case":"与格","number":"単数","gender":"女性"},"g":"彼"},{"t":"τῇ","l":"ὁ","k":"テー","p":"art","m":{"case":"与格","number":"単数","gender":"女性"},"g":"その"},{"t":"ὥρᾳ","l":"ὥρα","k":"ホーラ","p":"noun","m":{"case":"与格","number":"単数","gender":"女性"},"g":"時"},{"t":"καὶ","l":"καί","k":"カイ","p":"conj","g":"そして"},{"t":"ἐφοβήθησαν","l":"φοβέομαι","k":"エフォベーセーサン","p":"verb","m":{"person":"3人称","tense":"アオリスト","voice":"受動態","mood":"直説法"},"g":"恐れる"},{"t":"⸂τὸν","l":"ὁ","k":"トン","p":"art","m":{"case":"対格","number":"単数","gender":"男性"},"g":"その"},{"t":"λαόν⸃","l":"λαός","k":"ラオン","p":"noun","m":{"case":"対格","number":"単数","gender":"男性"},"g":"民"},{"t":"ἔγνωσαν","l":"γινώσκω","k":"エグノーサン","p":"verb","m":{"person":"3人称","tense":"アオリスト","voice":"能動態","mood":"直説法"},"g":"知る"},{"t":"γὰρ","l":"γάρ","k":"ガル","p":"conj","g":"なぜなら"},{"t":"ὅτι","l":"ὅτι","k":"ホティ","p":"conj","g":"〜ということ"},{"t":"πρὸς","l":"πρός","k":"プロス","p":"prep","g":"〜に向かって"},{"t":"αὐτοὺς","l":"αὐτός","k":"アウトウス","p":"pers","m":{"case":"対格","number":"複数","gender":"男性"},"g":"彼"},{"t":"⸂εἶπεν","l":"λέγω","k":"エイペン","p":"verb","m":{"person":"3人称","tense":"アオリスト","voice":"能動態","mood":"直説法"},"g":"言う"},{"t":"τὴν","l":"ὁ","k":"テーン","p":"art","m":{"case":"対格","number":"単数","gender":"女性"},"g":"その"},{"t":"παραβολὴν","l":"παραβολή","k":"パラボレーン","p":"noun","m":{"case":"対格","number":"単数","gender":"女性"},"g":"たとえ"},{"t":"ταύτην⸃","l":"οὗτος","k":"タウテーン","p":"dem","m":{"case":"対格","number":"単数","gender":"女性"},"g":"この"}]},{"verse":20,"words":[{"t":"Καὶ","l":"καί","k":"カイ","p":"conj","g":"そして"},{"t":"παρατηρήσαντες","l":"παρατηρέω","k":"パラテーレーサンテス","p":"verb","m":{"tense":"アオリスト","voice":"能動態","mood":"分詞","case":"主格","number":"複数","gender":"男性"}},{"t":"ἀπέστειλαν","l":"ἀποστέλλω","k":"アペステイラン","p":"verb","m":{"person":"3人称","tense":"アオリスト","voice":"能動態","mood":"直説法"},"g":"遣わす"},{"t":"ἐγκαθέτους","l":"ἐγκάθετος","k":"エンカセトウス","p":"adj","m":{"case":"対格","number":"複数","gender":"男性"}},{"t":"ὑποκρινομένους","l":"ὑποκρίνομαι","k":"フポクリノメノウス","p":"verb","m":{"tense":"現在","voice":"中動態","mood":"分詞","case":"対格","number":"複数","gender":"男性"}},{"t":"ἑαυτοὺς","l":"ἑαυτοῦ","k":"ヘアウトウス","p":"pers","m":{"case":"対格","number":"複数","gender":"男性"},"g":"自分自身"},{"t":"δικαίους","l":"δίκαιος","k":"ディカイウース","p":"adj","m":{"case":"対格","number":"複数","gender":"男性"},"g":"正しい"},{"t":"εἶναι","l":"εἰμί","k":"エイナイ","p":"verb","m":{"tense":"現在","voice":"能動態","mood":"不定詞"},"g":"〜である"},{"t":"ἵνα","l":"ἵνα","k":"ヒナ","p":"conj","g":"〜するために"},{"t":"ἐπιλάβωνται","l":"ἐπιλαμβάνομαι","k":"エピラボーンタイ","p":"verb","m":{"person":"3人称","tense":"アオリスト","voice":"中動態","mood":"接続法"},"g":"つかむ"},{"t":"αὐτοῦ","l":"αὐτός","k":"アウトウ","p":"pers","m":{"case":"属格","number":"単数","gender":"男性"},"g":"彼"},{"t":"λόγου","l":"λόγος","k":"ロゴウ","p":"noun","m":{"case":"属格","number":"単数","gender":"男性"},"g":"ことば"},{"t":"⸀ὥστε","l":"ὥστε","k":"ホーステ","p":"conj","g":"その結果"},{"t":"παραδοῦναι","l":"παραδίδωμι","k":"パラドウナイ","p":"verb","m":{"tense":"アオリスト","voice":"能動態","mood":"不定詞"},"g":"引き渡す"},{"t":"αὐτὸν","l":"αὐτός","k":"アウトン","p":"pers","m":{"case":"対格","number":"単数","gender":"男性"},"g":"彼"},{"t":"τῇ","l":"ὁ","k":"テー","p":"art","m":{"case":"与格","number":"単数","gender":"女性"},"g":"その"},{"t":"ἀρχῇ","l":"ἀρχή","k":"アルケー","p":"noun","m":{"case":"与格","number":"単数","gender":"女性"},"g":"初め/支配"},{"t":"καὶ","l":"καί","k":"カイ","p":"conj","g":"そして"},{"t":"τῇ","l":"ὁ","k":"テー","p":"art","m":{"case":"与格","number":"単数","gender":"女性"},"g":"その"},{"t":"ἐξουσίᾳ","l":"ἐξουσία","k":"エクソウシア","p":"noun","m":{"case":"与格","number":"単数","gender":"女性"},"g":"権威"},{"t":"τοῦ","l":"ὁ","k":"トウ","p":"art","m":{"case":"属格","number":"単数","gender":"男性"},"g":"その"},{"t":"ἡγεμόνος","l":"ἡγεμών","k":"ヘーゲモノス","p":"noun","m":{"case":"属格","number":"単数","gender":"男性"},"g":"総督"}]},{"verse":21,"words":[{"t":"καὶ","l":"καί","k":"カイ","p":"conj","g":"そして"},{"t":"ἐπηρώτησαν","l":"ἐπερωτάω","k":"エペーローテーサン","p":"verb","m":{"person":"3人称","tense":"アオリスト","voice":"能動態","mood":"直説法"},"g":"質問する"},{"t":"αὐτὸν","l":"αὐτός","k":"アウトン","p":"pers","m":{"case":"対格","number":"単数","gender":"男性"},"g":"彼"},{"t":"λέγοντες","l":"λέγω","k":"レゴンテス","p":"verb","m":{"tense":"現在","voice":"能動態","mood":"分詞","case":"主格","number":"複数","gender":"男性"},"g":"言う"},{"t":"Διδάσκαλε","l":"διδάσκαλος","k":"ディダスカレ","p":"noun","m":{"case":"呼格","number":"単数","gender":"男性"},"g":"教師"},{"t":"οἴδαμεν","l":"οἶδα","k":"オイダメン","p":"verb","m":{"person":"1人称","voice":"能動態","mood":"直説法"},"g":"知る"},{"t":"ὅτι","l":"ὅτι","k":"ホティ","p":"conj","g":"〜ということ"},{"t":"ὀρθῶς","l":"ὀρθῶς","k":"オルソース","p":"adv"},{"t":"λέγεις","l":"λέγω","k":"レゲイス","p":"verb","m":{"person":"2人称","tense":"現在","voice":"能動態","mood":"直説法"},"g":"言う"},{"t":"καὶ","l":"καί","k":"カイ","p":"conj","g":"そして"},{"t":"διδάσκεις","l":"διδάσκω","k":"ディダスケイス","p":"verb","m":{"person":"2人称","tense":"現在","voice":"能動態","mood":"直説法"},"g":"教える"},{"t":"καὶ","l":"καί","k":"カイ","p":"conj","g":"そして"},{"t":"οὐ","l":"οὐ","k":"ウー","p":"adv","g":"〜ない"},{"t":"λαμβάνεις","l":"λαμβάνω","k":"ラムバネイス","p":"verb","m":{"person":"2人称","tense":"現在","voice":"能動態","mood":"直説法"},"g":"受ける"},{"t":"πρόσωπον","l":"πρόσωπον","k":"プロソーポン","p":"noun","m":{"case":"対格","number":"単数","gender":"中性"},"g":"顔"},{"t":"ἀλλ’","l":"ἀλλά","k":"アルラ","p":"conj","g":"しかし"},{"t":"ἐπ’","l":"ἐπί","k":"エピ","p":"prep","g":"〜の上に"},{"t":"ἀληθείας","l":"ἀλήθεια","k":"アレーセイアス","p":"noun","m":{"case":"属格","number":"単数","gender":"女性"},"g":"真理"},{"t":"τὴν","l":"ὁ","k":"テーン","p":"art","m":{"case":"対格","number":"単数","gender":"女性"},"g":"その"},{"t":"ὁδὸν","l":"ὁδός","k":"ホドン","p":"noun","m":{"case":"対格","number":"単数","gender":"女性"},"g":"道"},{"t":"τοῦ","l":"ὁ","k":"トウ","p":"art","m":{"case":"属格","number":"単数","gender":"男性"},"g":"その"},{"t":"θεοῦ","l":"θεός","k":"セウー","p":"noun","m":{"case":"属格","number":"単数","gender":"男性"},"g":"神"},{"t":"διδάσκεις","l":"διδάσκω","k":"ディダスケイス","p":"verb","m":{"person":"2人称","tense":"現在","voice":"能動態","mood":"直説法"},"g":"教える"}]},{"verse":22,"words":[{"t":"ἔξεστιν","l":"ἔξεστι(ν)","k":"エクセスティン","p":"verb","m":{"person":"3人称","tense":"現在","voice":"能動態","mood":"直説法"},"g":"許されている"},{"t":"⸀ἡμᾶς","l":"ἐγώ","k":"ヘーマス","p":"pers","m":{"case":"対格","number":"複数"},"g":"私"},{"t":"Καίσαρι","l":"Καῖσαρ","k":"カイサリ","p":"noun","m":{"case":"与格","number":"単数","gender":"男性"},"g":"カエサル"},{"t":"φόρον","l":"φόρος","k":"フォロン","p":"noun","m":{"case":"対格","number":"単数","gender":"男性"}},{"t":"δοῦναι","l":"δίδωμι","k":"ドウナイ","p":"verb","m":{"tense":"アオリスト","voice":"能動態","mood":"不定詞"},"g":"与える"},{"t":"ἢ","l":"ἤ","k":"エー","p":"conj","g":"または"},{"t":"οὔ","l":"οὔ","k":"ウー","p":"adv","g":"いいえ"}]},{"verse":23,"words":[{"t":"κατανοήσας","l":"κατανοέω","k":"カタノエーサス","p":"verb","m":{"tense":"アオリスト","voice":"能動態","mood":"分詞","case":"主格","number":"単数","gender":"男性"},"g":"注意深く見る"},{"t":"δὲ","l":"δέ","k":"デ","p":"conj","g":"しかし"},{"t":"αὐτῶν","l":"αὐτός","k":"アウトーン","p":"pers","m":{"case":"属格","number":"複数","gender":"男性"},"g":"彼"},{"t":"τὴν","l":"ὁ","k":"テーン","p":"art","m":{"case":"対格","number":"単数","gender":"女性"},"g":"その"},{"t":"πανουργίαν","l":"πανουργία","k":"パノウルギアン","p":"noun","m":{"case":"対格","number":"単数","gender":"女性"}},{"t":"εἶπεν","l":"λέγω","k":"エイペン","p":"verb","m":{"person":"3人称","tense":"アオリスト","voice":"能動態","mood":"直説法"},"g":"言う"},{"t":"πρὸς","l":"πρός","k":"プロス","p":"prep","g":"〜に向かって"},{"t":"⸀αὐτούς","l":"αὐτός","k":"アウトウス","p":"pers","m":{"case":"対格","number":"複数","gender":"男性"},"g":"彼"}]},{"verse":24,"words":[{"t":"⸀Δείξατέ","l":"δείκνυμι","k":"デイクサテ","p":"verb","m":{"person":"2人称","tense":"アオリスト","voice":"能動態"},"g":"示す"},{"t":"μοι","l":"ἐγώ","k":"モイ","p":"pers","m":{"case":"与格","number":"単数"},"g":"私"},{"t":"δηνάριον","l":"δηνάριον","k":"デーナリオン","p":"noun","m":{"case":"対格","number":"単数","gender":"中性"},"g":"デナリ"},{"t":"τίνος","l":"τίς","k":"ティノス","p":"inter","m":{"case":"属格","number":"単数","gender":"男性"},"g":"誰"},{"t":"ἔχει","l":"ἔχω","k":"エケイ","p":"verb","m":{"person":"3人称","tense":"現在","voice":"能動態","mood":"直説法"},"g":"持つ"},{"t":"εἰκόνα","l":"εἰκών","k":"エイコナ","p":"noun","m":{"case":"対格","number":"単数","gender":"女性"},"g":"像"},{"t":"καὶ","l":"καί","k":"カイ","p":"conj","g":"そして"},{"t":"ἐπιγραφήν","l":"ἐπιγραφή","k":"エピグラフェーン","p":"noun","m":{"case":"対格","number":"単数","gender":"女性"}},{"t":"⸀ἀποκριθέντες","l":"ἀποκρίνομαι","k":"アポクリセンテス","p":"verb","m":{"tense":"アオリスト","voice":"受動態","mood":"分詞","case":"主格","number":"複数","gender":"男性"},"g":"答える"},{"t":"δὲ","l":"δέ","k":"デ","p":"conj","g":"しかし"},{"t":"εἶπαν","l":"λέγω","k":"エイパン","p":"verb","m":{"person":"3人称","tense":"アオリスト","voice":"能動態","mood":"直説法"},"g":"言う"},{"t":"Καίσαρος","l":"Καῖσαρ","k":"カイサロス","p":"noun","m":{"case":"属格","number":"単数","gender":"男性"},"g":"カエサル"}]},{"verse":25,"words":[{"t":"ὁ","l":"ὁ","k":"ホ","p":"art","m":{"case":"主格","number":"単数","gender":"男性"},"g":"その"},{"t":"δὲ","l":"δέ","k":"デ","p":"conj","g":"しかし"},{"t":"εἶπεν","l":"λέγω","k":"エイペン","p":"verb","m":{"person":"3人称","tense":"アオリスト","voice":"能動態","mood":"直説法"},"g":"言う"},{"t":"⸂πρὸς","l":"πρός","k":"プロス","p":"prep","g":"〜に向かって"},{"t":"αὐτούς","l":"αὐτός","k":"アウトウス","p":"pers","m":{"case":"対格","number":"複数","gender":"男性"},"g":"彼"},{"t":"Τοίνυν","l":"τοίνυν","k":"トイニュン","p":"conj"},{"t":"ἀπόδοτε⸃","l":"ἀποδίδωμι","k":"アポドテ","p":"verb","m":{"person":"2人称","tense":"アオリスト","voice":"能動態"},"g":"返す/報いる"},{"t":"τὰ","l":"ὁ","k":"タ","p":"art","m":{"case":"対格","number":"複数","gender":"中性"},"g":"その"},{"t":"Καίσαρος","l":"Καῖσαρ","k":"カイサロス","p":"noun","m":{"case":"属格","number":"単数","gender":"男性"},"g":"カエサル"},{"t":"Καίσαρι","l":"Καῖσαρ","k":"カイサリ","p":"noun","m":{"case":"与格","number":"単数","gender":"男性"},"g":"カエサル"},{"t":"καὶ","l":"καί","k":"カイ","p":"conj","g":"そして"},{"t":"τὰ","l":"ὁ","k":"タ","p":"art","m":{"case":"対格","number":"複数","gender":"中性"},"g":"その"},{"t":"τοῦ","l":"ὁ","k":"トウ","p":"art","m":{"case":"属格","number":"単数","gender":"男性"},"g":"その"},{"t":"θεοῦ","l":"θεός","k":"セウー","p":"noun","m":{"case":"属格","number":"単数","gender":"男性"},"g":"神"},{"t":"τῷ","l":"ὁ","k":"トー","p":"art","m":{"case":"与格","number":"単数","gender":"男性"},"g":"その"},{"t":"θεῷ","l":"θεός","k":"セオー","p":"noun","m":{"case":"与格","number":"単数","gender":"男性"},"g":"神"}]},{"verse":26,"words":[{"t":"καὶ","l":"καί","k":"カイ","p":"conj","g":"そして"},{"t":"οὐκ","l":"οὐ","k":"ウー","p":"adv","g":"〜ない"},{"t":"ἴσχυσαν","l":"ἰσχύω","k":"イスキュサン","p":"verb","m":{"person":"3人称","tense":"アオリスト","voice":"能動態","mood":"直説法"},"g":"力がある"},{"t":"ἐπιλαβέσθαι","l":"ἐπιλαμβάνομαι","k":"エピラベスサイ","p":"verb","m":{"tense":"アオリスト","voice":"中動態","mood":"不定詞"},"g":"つかむ"},{"t":"⸀τοῦ","l":"ὁ","k":"トウ","p":"art","m":{"case":"属格","number":"単数","gender":"男性"},"g":"その"},{"t":"ῥήματος","l":"ῥῆμα","k":"レーマトス","p":"noun","m":{"case":"属格","number":"単数","gender":"中性"},"g":"言葉"},{"t":"ἐναντίον","l":"ἐναντίον","k":"エナンティオン","p":"prep"},{"t":"τοῦ","l":"ὁ","k":"トウ","p":"art","m":{"case":"属格","number":"単数","gender":"男性"},"g":"その"},{"t":"λαοῦ","l":"λαός","k":"ラウー","p":"noun","m":{"case":"属格","number":"単数","gender":"男性"},"g":"民"},{"t":"καὶ","l":"καί","k":"カイ","p":"conj","g":"そして"},{"t":"θαυμάσαντες","l":"θαυμάζω","k":"サウマサンテス","p":"verb","m":{"tense":"アオリスト","voice":"能動態","mood":"分詞","case":"主格","number":"複数","gender":"男性"},"g":"驚く"},{"t":"ἐπὶ","l":"ἐπί","k":"エピ","p":"prep","g":"〜の上に"},{"t":"τῇ","l":"ὁ","k":"テー","p":"art","m":{"case":"与格","number":"単数","gender":"女性"},"g":"その"},{"t":"ἀποκρίσει","l":"ἀπόκρισις","k":"アポクリセイ","p":"noun","m":{"case":"与格","number":"単数","gender":"女性"}},{"t":"αὐτοῦ","l":"αὐτός","k":"アウトウ","p":"pers","m":{"case":"属格","number":"単数","gender":"男性"},"g":"彼"},{"t":"ἐσίγησαν","l":"σιγάω","k":"エシゲーサン","p":"verb","m":{"person":"3人称","tense":"アオリスト","voice":"能動態","mood":"直説法"}}]},{"verse":27,"words":[{"t":"Προσελθόντες","l":"προσέρχομαι","k":"プロセルソンテス","p":"verb","m":{"tense":"アオリスト","voice":"能動態","mood":"分詞","case":"主格","number":"複数","gender":"男性"},"g":"近づく"},{"t":"δέ","l":"δέ","k":"デ","p":"conj","g":"しかし"},{"t":"τινες","l":"τις","k":"ティネス","p":"inter","m":{"case":"主格","number":"複数","gender":"男性"},"g":"ある人/何か"},{"t":"τῶν","l":"ὁ","k":"トーン","p":"art","m":{"case":"属格","number":"複数","gender":"男性"},"g":"その"},{"t":"Σαδδουκαίων","l":"Σαδδουκαῖος","k":"サドドウカイオーン","p":"noun","m":{"case":"属格","number":"複数","gender":"男性"},"g":"サドカイ人"},{"t":"οἱ","l":"ὁ","k":"オイ","p":"art","m":{"case":"主格","number":"複数","gender":"男性"},"g":"その"},{"t":"⸀ἀντιλέγοντες","l":"ἀντιλέγω","k":"アンティレゴンテス","p":"verb","m":{"tense":"現在","voice":"能動態","mood":"分詞","case":"主格","number":"複数","gender":"男性"}},{"t":"ἀνάστασιν","l":"ἀνάστασις","k":"アナスタシン","p":"noun","m":{"case":"対格","number":"単数","gender":"女性"},"g":"復活"},{"t":"μὴ","l":"μή","k":"メー","p":"adv","g":"〜ない"},{"t":"εἶναι","l":"εἰμί","k":"エイナイ","p":"verb","m":{"tense":"現在","voice":"能動態","mood":"不定詞"},"g":"〜である"},{"t":"ἐπηρώτησαν","l":"ἐπερωτάω","k":"エペーローテーサン","p":"verb","m":{"person":"3人称","tense":"アオリスト","voice":"能動態","mood":"直説法"},"g":"質問する"},{"t":"αὐτὸν","l":"αὐτός","k":"アウトン","p":"pers","m":{"case":"対格","number":"単数","gender":"男性"},"g":"彼"}]},{"verse":28,"words":[{"t":"λέγοντες","l":"λέγω","k":"レゴンテス","p":"verb","m":{"tense":"現在","voice":"能動態","mood":"分詞","case":"主格","number":"複数","gender":"男性"},"g":"言う"},{"t":"Διδάσκαλε","l":"διδάσκαλος","k":"ディダスカレ","p":"noun","m":{"case":"呼格","number":"単数","gender":"男性"},"g":"教師"},{"t":"Μωϋσῆς","l":"Μωϋσῆς","k":"モーウセース","p":"noun","m":{"case":"主格","number":"単数","gender":"男性"},"g":"モーセ"},{"t":"ἔγραψεν","l":"γράφω","k":"エグラプセン","p":"verb","m":{"person":"3人称","tense":"アオリスト","voice":"能動態","mood":"直説法"},"g":"書く"},{"t":"ἡμῖν","l":"ἐγώ","k":"ヘーミン","p":"pers","m":{"case":"与格","number":"複数"},"g":"私"},{"t":"ἐάν","l":"ἐάν","k":"エアン","p":"conj","g":"もし〜なら"},{"t":"τινος","l":"τις","k":"ティノス","p":"inter","m":{"case":"属格","number":"単数","gender":"男性"},"g":"ある人/何か"},{"t":"ἀδελφὸς","l":"ἀδελφός","k":"アデルフォス","p":"noun","m":{"case":"主格","number":"単数","gender":"男性"},"g":"兄弟"},{"t":"ἀποθάνῃ","l":"ἀποθνῄσκω","k":"アポサネー","p":"verb","m":{"person":"3人称","tense":"アオリスト","voice":"能動態","mood":"接続法"},"g":"死ぬ"},{"t":"ἔχων","l":"ἔχω","k":"エコーン","p":"verb","m":{"tense":"現在","voice":"能動態","mood":"分詞","case":"主格","number":"単数","gender":"男性"},"g":"持つ"},{"t":"γυναῖκα","l":"γυνή","k":"ギュナイカ","p":"noun","m":{"case":"対格","number":"単数","gender":"女性"},"g":"女"},{"t":"καὶ","l":"καί","k":"カイ","p":"conj","g":"そして"},{"t":"οὗτος","l":"οὗτος","k":"ウートス","p":"dem","m":{"case":"主格","number":"単数","gender":"男性"},"g":"この"},{"t":"ἄτεκνος","l":"ἄτεκνος","k":"アテクノス","p":"adj","m":{"case":"主格","number":"単数","gender":"男性"}},{"t":"⸀ᾖ","l":"εἰμί","k":"エー","p":"verb","m":{"person":"3人称","tense":"現在","voice":"能動態","mood":"接続法"},"g":"〜である"},{"t":"ἵνα","l":"ἵνα","k":"ヒナ","p":"conj","g":"〜するために"},{"t":"λάβῃ","l":"λαμβάνω","k":"ラベー","p":"verb","m":{"person":"3人称","tense":"アオリスト","voice":"能動態","mood":"接続法"},"g":"受ける"},{"t":"ὁ","l":"ὁ","k":"ホ","p":"art","m":{"case":"主格","number":"単数","gender":"男性"},"g":"その"},{"t":"ἀδελφὸς","l":"ἀδελφός","k":"アデルフォス","p":"noun","m":{"case":"主格","number":"単数","gender":"男性"},"g":"兄弟"},{"t":"αὐτοῦ","l":"αὐτός","k":"アウトウ","p":"pers","m":{"case":"属格","number":"単数","gender":"男性"},"g":"彼"},{"t":"τὴν","l":"ὁ","k":"テーン","p":"art","m":{"case":"対格","number":"単数","gender":"女性"},"g":"その"},{"t":"γυναῖκα","l":"γυνή","k":"ギュナイカ","p":"noun","m":{"case":"対格","number":"単数","gender":"女性"},"g":"女"},{"t":"καὶ","l":"καί","k":"カイ","p":"conj","g":"そして"},{"t":"ἐξαναστήσῃ","l":"ἐξανίστημι","k":"エクサナステーセー","p":"verb","m":{"person":"3人称","tense":"アオリスト","voice":"能動態","mood":"接続法"}},{"t":"σπέρμα","l":"σπέρμα","k":"スペルマ","p":"noun","m":{"case":"対格","number":"単数","gender":"中性"},"g":"種/子孫"},{"t":"τῷ","l":"ὁ","k":"トー","p":"art","m":{"case":"与格","number":"単数","gender":"男性"},"g":"その"},{"t":"ἀδελφῷ","l":"ἀδελφός","k":"アデルフォー","p":"noun","m":{"case":"与格","number":"単数","gender":"男性"},"g":"兄弟"},{"t":"αὐτοῦ","l":"αὐτός","k":"アウトウ","p":"pers","m":{"case":"属格","number":"単数","gender":"男性"},"g":"彼"}]},{"verse":29,"words":[{"t":"ἑπτὰ","l":"ἑπτά","k":"ヘプタ","p":"adj","m":{"case":"主格","number":"複数","gender":"男性"},"g":"七"},{"t":"οὖν","l":"οὖν","k":"ウーン","p":"conj","g":"それゆえ"},{"t":"ἀδελφοὶ","l":"ἀδελφός","k":"アデルフォイ","p":"noun","m":{"case":"主格","number":"複数","gender":"男性"},"g":"兄弟"},{"t":"ἦσαν","l":"εἰμί","k":"エーサン","p":"verb","m":{"person":"3人称","tense":"未完了","voice":"能動態","mood":"直説法"},"g":"〜である"},{"t":"καὶ","l":"καί","k":"カイ","p":"conj","g":"そして"},{"t":"ὁ","l":"ὁ","k":"ホ","p":"art","m":{"case":"主格","number":"単数","gender":"男性"},"g":"その"},{"t":"πρῶτος","l":"πρῶτος","k":"プロートス","p":"adj","m":{"case":"主格","number":"単数","gender":"男性"},"g":"第一の"},{"t":"λαβὼν","l":"λαμβάνω","k":"ラボーン","p":"verb","m":{"tense":"アオリスト","voice":"能動態","mood":"分詞","case":"主格","number":"単数","gender":"男性"},"g":"受ける"},{"t":"γυναῖκα","l":"γυνή","k":"ギュナイカ","p":"noun","m":{"case":"対格","number":"単数","gender":"女性"},"g":"女"},{"t":"ἀπέθανεν","l":"ἀποθνῄσκω","k":"アペサネン","p":"verb","m":{"person":"3人称","tense":"アオリスト","voice":"能動態","mood":"直説法"},"g":"死ぬ"},{"t":"ἄτεκνος","l":"ἄτεκνος","k":"アテクノス","p":"adj","m":{"case":"主格","number":"単数","gender":"男性"}}]},{"verse":30,"words":[{"t":"καὶ","l":"καί","k":"カイ","p":"conj","g":"そして"},{"t":"⸂ὁ","l":"ὁ","k":"ホ","p":"art","m":{"case":"主格","number":"単数","gender":"男性"},"g":"その"},{"t":"δεύτερος⸃","l":"δεύτερος","k":"デウテロス","p":"adj","m":{"case":"主格","number":"単数","gender":"男性"},"g":"第二の"}]},{"verse":31,"words":[{"t":"καὶ","l":"καί","k":"カイ","p":"conj","g":"そして"},{"t":"ὁ","l":"ὁ","k":"ホ","p":"art","m":{"case":"主格","number":"単数","gender":"男性"},"g":"その"},{"t":"τρίτος","l":"τρίτος","k":"トリトス","p":"adj","m":{"case":"主格","number":"単数","gender":"男性"},"g":"第三の"},{"t":"ἔλαβεν","l":"λαμβάνω","k":"エラベン","p":"verb","m":{"person":"3人称","tense":"アオリスト","voice":"能動態","mood":"直説法"},"g":"受ける"},{"t":"⸀αὐτήν","l":"αὐτός","k":"アウテーン","p":"pers","m":{"case":"対格","number":"単数","gender":"女性"},"g":"彼"},{"t":"ὡσαύτως","l":"ὡσαύτως","k":"ホーサウトース","p":"adv","g":"同様に"},{"t":"δὲ","l":"δέ","k":"デ","p":"conj","g":"しかし"},{"t":"καὶ","l":"καί","k":"カイ","p":"adv","g":"そして"},{"t":"οἱ","l":"ὁ","k":"オイ","p":"art","m":{"case":"主格","number":"複数","gender":"男性"},"g":"その"},{"t":"ἑπτὰ","l":"ἑπτά","k":"ヘプタ","p":"adj","m":{"case":"主格","number":"複数","gender":"男性"},"g":"七"},{"t":"οὐ","l":"οὐ","k":"ウー","p":"adv","g":"〜ない"},{"t":"κατέλιπον","l":"καταλείπω","k":"カテリポン","p":"verb","m":{"person":"3人称","tense":"アオリスト","voice":"能動態","mood":"直説法"},"g":"残す"},{"t":"τέκνα","l":"τέκνον","k":"テクナ","p":"noun","m":{"case":"対格","number":"複数","gender":"中性"},"g":"子供"},{"t":"καὶ","l":"καί","k":"カイ","p":"conj","g":"そして"},{"t":"ἀπέθανον","l":"ἀποθνῄσκω","k":"アペサノン","p":"verb","m":{"person":"3人称","tense":"アオリスト","voice":"能動態","mood":"直説法"},"g":"死ぬ"}]},{"verse":32,"words":[{"t":"ὕστερον","l":"ὕστερος","k":"フステロン","p":"adj","m":{"case":"対格","number":"単数","gender":"中性","degree":"比較級"}},{"t":"⸂καὶ","l":"καί","k":"カイ","p":"adv","g":"そして"},{"t":"ἡ","l":"ὁ","k":"ヘー","p":"art","m":{"case":"主格","number":"単数","gender":"女性"},"g":"その"},{"t":"γυνὴ","l":"γυνή","k":"ギュネー","p":"noun","m":{"case":"主格","number":"単数","gender":"女性"},"g":"女"},{"t":"ἀπέθανεν⸃","l":"ἀποθνῄσκω","k":"アペサネン","p":"verb","m":{"person":"3人称","tense":"アオリスト","voice":"能動態","mood":"直説法"},"g":"死ぬ"}]},{"verse":33,"words":[{"t":"⸂ἡ","l":"ὁ","k":"ヘー","p":"art","m":{"case":"主格","number":"単数","gender":"女性"},"g":"その"},{"t":"γυνὴ","l":"γυνή","k":"ギュネー","p":"noun","m":{"case":"主格","number":"単数","gender":"女性"},"g":"女"},{"t":"οὖν","l":"οὖν","k":"ウーン","p":"conj","g":"それゆえ"},{"t":"ἐν","l":"ἐν","k":"エン","p":"prep","g":"〜の中に"},{"t":"τῇ⸃","l":"ὁ","k":"テー","p":"art","m":{"case":"与格","number":"単数","gender":"女性"},"g":"その"},{"t":"ἀναστάσει","l":"ἀνάστασις","k":"アナスタセイ","p":"noun","m":{"case":"与格","number":"単数","gender":"女性"},"g":"復活"},{"t":"τίνος","l":"τίς","k":"ティノス","p":"inter","m":{"case":"属格","number":"単数","gender":"男性"},"g":"誰"},{"t":"αὐτῶν","l":"αὐτός","k":"アウトーン","p":"pers","m":{"case":"属格","number":"複数","gender":"男性"},"g":"彼"},{"t":"γίνεται","l":"γίνομαι","k":"ギネタイ","p":"verb","m":{"person":"3人称","tense":"現在","voice":"中動態","mood":"直説法"},"g":"〜になる"},{"t":"γυνή","l":"γυνή","k":"ギュネー","p":"noun","m":{"case":"主格","number":"単数","gender":"女性"},"g":"女"},{"t":"οἱ","l":"ὁ","k":"オイ","p":"art","m":{"case":"主格","number":"複数","gender":"男性"},"g":"その"},{"t":"γὰρ","l":"γάρ","k":"ガル","p":"conj","g":"なぜなら"},{"t":"ἑπτὰ","l":"ἑπτά","k":"ヘプタ","p":"adj","m":{"case":"主格","number":"複数","gender":"男性"},"g":"七"},{"t":"ἔσχον","l":"ἔχω","k":"エスコン","p":"verb","m":{"person":"3人称","tense":"アオリスト","voice":"能動態","mood":"直説法"},"g":"持つ"},{"t":"αὐτὴν","l":"αὐτός","k":"アウテーン","p":"pers","m":{"case":"対格","number":"単数","gender":"女性"},"g":"彼"},{"t":"γυναῖκα","l":"γυνή","k":"ギュナイカ","p":"noun","m":{"case":"対格","number":"単数","gender":"女性"},"g":"女"}]},{"verse":34,"words":[{"t":"⸀Καὶ","l":"καί","k":"カイ","p":"conj","g":"そして"},{"t":"εἶπεν","l":"λέγω","k":"エイペン","p":"verb","m":{"person":"3人称","tense":"アオリスト","voice":"能動態","mood":"直説法"},"g":"言う"},{"t":"αὐτοῖς","l":"αὐτός","k":"アウトイス","p":"pers","m":{"case":"与格","number":"複数","gender":"男性"},"g":"彼"},{"t":"ὁ","l":"ὁ","k":"ホ","p":"art","m":{"case":"主格","number":"単数","gender":"男性"},"g":"その"},{"t":"Ἰησοῦς","l":"Ἰησοῦς","k":"イエーソウス","p":"noun","m":{"case":"主格","number":"単数","gender":"男性"},"g":"イエス"},{"t":"Οἱ","l":"ὁ","k":"オイ","p":"art","m":{"case":"主格","number":"複数","gender":"男性"},"g":"その"},{"t":"υἱοὶ","l":"υἱός","k":"ウイオイ","p":"noun","m":{"case":"主格","number":"複数","gender":"男性"},"g":"息子"},{"t":"τοῦ","l":"ὁ","k":"トウ","p":"art","m":{"case":"属格","number":"単数","gender":"男性"},"g":"その"},{"t":"αἰῶνος","l":"αἰών","k":"アイオーノス","p":"noun","m":{"case":"属格","number":"単数","gender":"男性"},"g":"時代"},{"t":"τούτου","l":"οὗτος","k":"トウトウ","p":"dem","m":{"case":"属格","number":"単数","gender":"男性"},"g":"この"},{"t":"γαμοῦσιν","l":"γαμέω","k":"ガモウシン","p":"verb","m":{"person":"3人称","tense":"現在","voice":"能動態","mood":"直説法"},"g":"結婚する"},{"t":"καὶ","l":"καί","k":"カイ","p":"conj","g":"そして"},{"t":"⸀γαμίσκονται","l":"γαμίσκω","k":"ガミスコンタイ","p":"verb","m":{"person":"3人称","tense":"現在","voice":"受動態","mood":"直説法"}}]},{"verse":35,"words":[{"t":"οἱ","l":"ὁ","k":"オイ","p":"art","m":{"case":"主格","number":"複数","gender":"男性"},"g":"その"},{"t":"δὲ","l":"δέ","k":"デ","p":"conj","g":"しかし"},{"t":"καταξιωθέντες","l":"καταξιόω","k":"カタクシオーセンテス","p":"verb","m":{"tense":"アオリスト","voice":"受動態","mood":"分詞","case":"主格","number":"複数","gender":"男性"}},{"t":"τοῦ","l":"ὁ","k":"トウ","p":"art","m":{"case":"属格","number":"単数","gender":"男性"},"g":"その"},{"t":"αἰῶνος","l":"αἰών","k":"アイオーノス","p":"noun","m":{"case":"属格","number":"単数","gender":"男性"},"g":"時代"},{"t":"ἐκείνου","l":"ἐκεῖνος","k":"エケイノウ","p":"dem","m":{"case":"属格","number":"単数","gender":"男性"},"g":"あの"},{"t":"τυχεῖν","l":"τυγχάνω","k":"テュケイン","p":"verb","m":{"tense":"アオリスト","voice":"能動態","mood":"不定詞"}},{"t":"καὶ","l":"καί","k":"カイ","p":"conj","g":"そして"},{"t":"τῆς","l":"ὁ","k":"テース","p":"art","m":{"case":"属格","number":"単数","gender":"女性"},"g":"その"},{"t":"ἀναστάσεως","l":"ἀνάστασις","k":"アナスタセオース","p":"noun","m":{"case":"属格","number":"単数","gender":"女性"},"g":"復活"},{"t":"τῆς","l":"ὁ","k":"テース","p":"art","m":{"case":"属格","number":"単数","gender":"女性"},"g":"その"},{"t":"ἐκ","l":"ἐκ","k":"エク","p":"prep","g":"〜から"},{"t":"νεκρῶν","l":"νεκρός","k":"ネクローン","p":"adj","m":{"case":"属格","number":"複数","gender":"男性"},"g":"死んだ"},{"t":"οὔτε","l":"οὔτε","k":"ウーテ","p":"conj","g":"〜もない"},{"t":"γαμοῦσιν","l":"γαμέω","k":"ガモウシン","p":"verb","m":{"person":"3人称","tense":"現在","voice":"能動態","mood":"直説法"},"g":"結婚する"},{"t":"οὔτε","l":"οὔτε","k":"ウーテ","p":"conj","g":"〜もない"},{"t":"⸀γαμίζονται","l":"γαμίζω","k":"ガミゾンタイ","p":"verb","m":{"person":"3人称","tense":"現在","voice":"受動態","mood":"直説法"}}]},{"verse":36,"words":[{"t":"⸀οὐδὲ","l":"οὐδέ","k":"ウーデ","p":"adv","g":"〜もない"},{"t":"γὰρ","l":"γάρ","k":"ガル","p":"conj","g":"なぜなら"},{"t":"ἀποθανεῖν","l":"ἀποθνῄσκω","k":"アポサネイン","p":"verb","m":{"tense":"アオリスト","voice":"能動態","mood":"不定詞"},"g":"死ぬ"},{"t":"ἔτι","l":"ἔτι","k":"エティ","p":"adv","g":"なお"},{"t":"δύνανται","l":"δύναμαι","k":"デュナンタイ","p":"verb","m":{"person":"3人称","tense":"現在","voice":"中動態","mood":"直説法"},"g":"〜できる"},{"t":"ἰσάγγελοι","l":"ἰσάγγελος","k":"イサンゲロイ","p":"adj","m":{"case":"主格","number":"複数","gender":"男性"}},{"t":"γάρ","l":"γάρ","k":"ガル","p":"conj","g":"なぜなら"},{"t":"εἰσιν","l":"εἰμί","k":"エイシン","p":"verb","m":{"person":"3人称","tense":"現在","voice":"能動態","mood":"直説法"},"g":"〜である"},{"t":"καὶ","l":"καί","k":"カイ","p":"conj","g":"そして"},{"t":"υἱοί","l":"υἱός","k":"ウイオイ","p":"noun","m":{"case":"主格","number":"複数","gender":"男性"},"g":"息子"},{"t":"⸀εἰσιν","l":"εἰμί","k":"エイシン","p":"verb","m":{"person":"3人称","tense":"現在","voice":"能動態","mood":"直説法"},"g":"〜である"},{"t":"θεοῦ","l":"θεός","k":"セウー","p":"noun","m":{"case":"属格","number":"単数","gender":"男性"},"g":"神"},{"t":"τῆς","l":"ὁ","k":"テース","p":"art","m":{"case":"属格","number":"単数","gender":"女性"},"g":"その"},{"t":"ἀναστάσεως","l":"ἀνάστασις","k":"アナスタセオース","p":"noun","m":{"case":"属格","number":"単数","gender":"女性"},"g":"復活"},{"t":"υἱοὶ","l":"υἱός","k":"ウイオイ","p":"noun","m":{"case":"主格","number":"複数","gender":"男性"},"g":"息子"},{"t":"ὄντες","l":"εἰμί","k":"オンテス","p":"verb","m":{"tense":"現在","voice":"能動態","mood":"分詞","case":"主格","number":"複数","gender":"男性"},"g":"〜である"}]},{"verse":37,"words":[{"t":"ὅτι","l":"ὅτι","k":"ホティ","p":"conj","g":"〜ということ"},{"t":"δὲ","l":"δέ","k":"デ","p":"conj","g":"しかし"},{"t":"ἐγείρονται","l":"ἐγείρω","k":"エゲイロンタイ","p":"verb","m":{"person":"3人称","tense":"現在","voice":"受動態","mood":"直説法"},"g":"起こす"},{"t":"οἱ","l":"ὁ","k":"オイ","p":"art","m":{"case":"主格","number":"複数","gender":"男性"},"g":"その"},{"t":"νεκροὶ","l":"νεκρός","k":"ネクロイ","p":"adj","m":{"case":"主格","number":"複数","gender":"男性"},"g":"死んだ"},{"t":"καὶ","l":"καί","k":"カイ","p":"adv","g":"そして"},{"t":"Μωϋσῆς","l":"Μωϋσῆς","k":"モーウセース","p":"noun","m":{"case":"主格","number":"単数","gender":"男性"},"g":"モーセ"},{"t":"ἐμήνυσεν","l":"μηνύω","k":"エメーニュセン","p":"verb","m":{"person":"3人称","tense":"アオリスト","voice":"能動態","mood":"直説法"}},{"t":"ἐπὶ","l":"ἐπί","k":"エピ","p":"prep","g":"〜の上に"},{"t":"τῆς","l":"ὁ","k":"テース","p":"art","m":{"case":"属格","number":"単数","gender":"女性"},"g":"その"},{"t":"βάτου","l":"βάτος","k":"バトウ","p":"noun","m":{"case":"属格","number":"単数","gender":"女性"}},{"t":"ὡς","l":"ὡς","k":"ホース","p":"conj","g":"〜のように"},{"t":"λέγει","l":"λέγω","k":"レゲイ","p":"verb","m":{"person":"3人称","tense":"現在","voice":"能動態","mood":"直説法"},"g":"言う"},{"t":"κύριον","l":"κύριος","k":"キュリオン","p":"noun","m":{"case":"対格","number":"単数","gender":"男性"},"g":"主人"},{"t":"τὸν","l":"ὁ","k":"トン","p":"art","m":{"case":"対格","number":"単数","gender":"男性"},"g":"その"},{"t":"θεὸν","l":"θεός","k":"セオン","p":"noun","m":{"case":"対格","number":"単数","gender":"男性"},"g":"神"},{"t":"Ἀβραὰμ","l":"Ἀβραάμ","k":"アブラアム","p":"noun","m":{"case":"属格","number":"単数","gender":"男性"},"g":"アブラハム"},{"t":"⸀καὶ","l":"καί","k":"カイ","p":"conj","g":"そして"},{"t":"θεὸν","l":"θεός","k":"セオン","p":"noun","m":{"case":"対格","number":"単数","gender":"男性"},"g":"神"},{"t":"Ἰσαὰκ","l":"Ἰσαάκ","k":"イサアク","p":"noun","m":{"case":"属格","number":"単数","gender":"男性"},"g":"イサク"},{"t":"⸁καὶ","l":"καί","k":"カイ","p":"conj","g":"そして"},{"t":"θεὸν","l":"θεός","k":"セオン","p":"noun","m":{"case":"対格","number":"単数","gender":"男性"},"g":"神"},{"t":"Ἰακώβ","l":"Ἰακώβ","k":"イアコーブ","p":"noun","m":{"case":"属格","number":"単数","gender":"男性"},"g":"ヤコブ"}]},{"verse":38,"words":[{"t":"θεὸς","l":"θεός","k":"セオス","p":"noun","m":{"case":"主格","number":"単数","gender":"男性"},"g":"神"},{"t":"δὲ","l":"δέ","k":"デ","p":"conj","g":"しかし"},{"t":"οὐκ","l":"οὐ","k":"ウー","p":"adv","g":"〜ない"},{"t":"ἔστιν","l":"εἰμί","k":"エスティン","p":"verb","m":{"person":"3人称","tense":"現在","voice":"能動態","mood":"直説法"},"g":"〜である"},{"t":"νεκρῶν","l":"νεκρός","k":"ネクローン","p":"adj","m":{"case":"属格","number":"複数","gender":"男性"},"g":"死んだ"},{"t":"ἀλλὰ","l":"ἀλλά","k":"アルラ","p":"conj","g":"しかし"},{"t":"ζώντων","l":"ζάω","k":"ゾーントーン","p":"verb","m":{"tense":"現在","voice":"能動態","mood":"分詞","case":"属格","number":"複数","gender":"男性"},"g":"生きる"},{"t":"πάντες","l":"πᾶς","k":"パンテス","p":"adj","m":{"case":"主格","number":"複数","gender":"男性"},"g":"すべての"},{"t":"γὰρ","l":"γάρ","k":"ガル","p":"conj","g":"なぜなら"},{"t":"αὐτῷ","l":"αὐτός","k":"アウトー","p":"pers","m":{"case":"与格","number":"単数","gender":"男性"},"g":"彼"},{"t":"ζῶσιν","l":"ζάω","k":"ゾーシン","p":"verb","m":{"person":"3人称","tense":"現在","voice":"能動態","mood":"直説法"},"g":"生きる"}]},{"verse":39,"words":[{"t":"ἀποκριθέντες","l":"ἀποκρίνομαι","k":"アポクリセンテス","p":"verb","m":{"tense":"アオリスト","voice":"受動態","mood":"分詞","case":"主格","number":"複数","gender":"男性"},"g":"答える"},{"t":"δέ","l":"δέ","k":"デ","p":"conj","g":"しかし"},{"t":"τινες","l":"τις","k":"ティネス","p":"inter","m":{"case":"主格","number":"複数","gender":"男性"},"g":"ある人/何か"},{"t":"τῶν","l":"ὁ","k":"トーン","p":"art","m":{"case":"属格","number":"複数","gender":"男性"},"g":"その"},{"t":"γραμματέων","l":"γραμματεύς","k":"グラムマテオーン","p":"noun","m":{"case":"属格","number":"複数","gender":"男性"},"g":"律法学者"},{"t":"εἶπαν","l":"λέγω","k":"エイパン","p":"verb","m":{"person":"3人称","tense":"アオリスト","voice":"能動態","mood":"直説法"},"g":"言う"},{"t":"Διδάσκαλε","l":"διδάσκαλος","k":"ディダスカレ","p":"noun","m":{"case":"呼格","number":"単数","gender":"男性"},"g":"教師"},{"t":"καλῶς","l":"καλῶς","k":"カロース","p":"adv","g":"よく"},{"t":"εἶπας","l":"λέγω","k":"エイパス","p":"verb","m":{"person":"2人称","tense":"アオリスト","voice":"能動態","mood":"直説法"},"g":"言う"}]},{"verse":40,"words":[{"t":"οὐκέτι","l":"οὐκέτι","k":"ウーケティ","p":"adv","g":"もはや〜ない"},{"t":"⸀γὰρ","l":"γάρ","k":"ガル","p":"conj","g":"なぜなら"},{"t":"ἐτόλμων","l":"τολμάω","k":"エトルモーン","p":"verb","m":{"person":"3人称","tense":"未完了","voice":"能動態","mood":"直説法"},"g":"思い切る"},{"t":"ἐπερωτᾶν","l":"ἐπερωτάω","k":"エペロータン","p":"verb","m":{"tense":"現在","voice":"能動態","mood":"不定詞"},"g":"質問する"},{"t":"αὐτὸν","l":"αὐτός","k":"アウトン","p":"pers","m":{"case":"対格","number":"単数","gender":"男性"},"g":"彼"},{"t":"οὐδέν","l":"οὐδείς","k":"ウーデン","p":"adj","m":{"case":"対格","number":"単数","gender":"中性"},"g":"誰も〜ない"}]},{"verse":41,"words":[{"t":"Εἶπεν","l":"λέγω","k":"エイペン","p":"verb","m":{"person":"3人称","tense":"アオリスト","voice":"能動態","mood":"直説法"},"g":"言う"},{"t":"δὲ","l":"δέ","k":"デ","p":"conj","g":"しかし"},{"t":"πρὸς","l":"πρός","k":"プロス","p":"prep","g":"〜に向かって"},{"t":"αὐτούς","l":"αὐτός","k":"アウトウス","p":"pers","m":{"case":"対格","number":"複数","gender":"男性"},"g":"彼"},{"t":"Πῶς","l":"πῶς","k":"ポース","p":"adv","g":"どのように"},{"t":"λέγουσιν","l":"λέγω","k":"レゴウシン","p":"verb","m":{"person":"3人称","tense":"現在","voice":"能動態","mood":"直説法"},"g":"言う"},{"t":"τὸν","l":"ὁ","k":"トン","p":"art","m":{"case":"対格","number":"単数","gender":"男性"},"g":"その"},{"t":"χριστὸν","l":"Χριστός","k":"クリストン","p":"noun","m":{"case":"対格","number":"単数","gender":"男性"},"g":"キリスト"},{"t":"⸂εἶναι","l":"εἰμί","k":"エイナイ","p":"verb","m":{"tense":"現在","voice":"能動態","mood":"不定詞"},"g":"〜である"},{"t":"Δαυὶδ","l":"Δαυίδ","k":"ダウイド","p":"noun","m":{"case":"属格","number":"単数","gender":"男性"},"g":"ダビデ"},{"t":"υἱόν⸃","l":"υἱός","k":"ウイオン","p":"noun","m":{"case":"対格","number":"単数","gender":"男性"},"g":"息子"}]},{"verse":42,"words":[{"t":"⸂αὐτὸς","l":"αὐτός","k":"アウトス","p":"pers","m":{"case":"主格","number":"単数","gender":"男性"},"g":"彼"},{"t":"γὰρ⸃","l":"γάρ","k":"ガル","p":"conj","g":"なぜなら"},{"t":"Δαυὶδ","l":"Δαυίδ","k":"ダウイド","p":"noun","m":{"case":"主格","number":"単数","gender":"男性"},"g":"ダビデ"},{"t":"λέγει","l":"λέγω","k":"レゲイ","p":"verb","m":{"person":"3人称","tense":"現在","voice":"能動態","mood":"直説法"},"g":"言う"},{"t":"ἐν","l":"ἐν","k":"エン","p":"prep","g":"〜の中に"},{"t":"βίβλῳ","l":"βίβλος","k":"ビブロー","p":"noun","m":{"case":"与格","number":"単数","gender":"女性"}},{"t":"ψαλμῶν","l":"ψαλμός","k":"プサルモーン","p":"noun","m":{"case":"属格","number":"複数","gender":"男性"}},{"t":"⸀Εἶπεν","l":"λέγω","k":"エイペン","p":"verb","m":{"person":"3人称","tense":"アオリスト","voice":"能動態","mood":"直説法"},"g":"言う"},{"t":"κύριος","l":"κύριος","k":"キュリオス","p":"noun","m":{"case":"主格","number":"単数","gender":"男性"},"g":"主人"},{"t":"τῷ","l":"ὁ","k":"トー","p":"art","m":{"case":"与格","number":"単数","gender":"男性"},"g":"その"},{"t":"κυρίῳ","l":"κύριος","k":"キュリオー","p":"noun","m":{"case":"与格","number":"単数","gender":"男性"},"g":"主人"},{"t":"μου","l":"ἐγώ","k":"モウ","p":"pers","m":{"case":"属格","number":"単数"},"g":"私"},{"t":"Κάθου","l":"κάθημαι","k":"カソウ","p":"verb","m":{"person":"2人称","tense":"現在","voice":"中動態"},"g":"座る"},{"t":"ἐκ","l":"ἐκ","k":"エク","p":"prep","g":"〜から"},{"t":"δεξιῶν","l":"δεξιός","k":"デクシオーン","p":"adj","m":{"case":"属格","number":"複数","gender":"中性"},"g":"右の"},{"t":"μου","l":"ἐγώ","k":"モウ","p":"pers","m":{"case":"属格","number":"単数"},"g":"私"}]},{"verse":43,"words":[{"t":"ἕως","l":"ἕως","k":"ヘオース","p":"conj","g":"〜まで"},{"t":"ἂν","l":"ἄν","k":"アン","p":"part","g":"〜かもしれない"},{"t":"θῶ","l":"τίθημι","k":"ソー","p":"verb","m":{"person":"1人称","tense":"アオリスト","voice":"能動態","mood":"接続法"},"g":"置く"},{"t":"τοὺς","l":"ὁ","k":"トウス","p":"art","m":{"case":"対格","number":"複数","gender":"男性"},"g":"その"},{"t":"ἐχθρούς","l":"ἐχθρός","k":"エクスロウス","p":"adj","m":{"case":"対格","number":"複数","gender":"男性"},"g":"敵"},{"t":"σου","l":"σύ","k":"ソウ","p":"pers","m":{"case":"属格","number":"単数"},"g":"あなた"},{"t":"ὑποπόδιον","l":"ὑποπόδιον","k":"フポポディオン","p":"noun","m":{"case":"対格","number":"単数","gender":"中性"}},{"t":"τῶν","l":"ὁ","k":"トーン","p":"art","m":{"case":"属格","number":"複数","gender":"男性"},"g":"その"},{"t":"ποδῶν","l":"πούς","k":"ポドーン","p":"noun","m":{"case":"属格","number":"複数","gender":"男性"},"g":"足"},{"t":"σου","l":"σύ","k":"ソウ","p":"pers","m":{"case":"属格","number":"単数"},"g":"あなた"}]},{"verse":44,"words":[{"t":"Δαυὶδ","l":"Δαυίδ","k":"ダウイド","p":"noun","m":{"case":"主格","number":"単数","gender":"男性"},"g":"ダビデ"},{"t":"οὖν","l":"οὖν","k":"ウーン","p":"conj","g":"それゆえ"},{"t":"⸂αὐτὸν","l":"αὐτός","k":"アウトン","p":"pers","m":{"case":"対格","number":"単数","gender":"男性"},"g":"彼"},{"t":"κύριον⸃","l":"κύριος","k":"キュリオン","p":"noun","m":{"case":"対格","number":"単数","gender":"男性"},"g":"主人"},{"t":"καλεῖ","l":"καλέω","k":"カレイ","p":"verb","m":{"person":"3人称","tense":"現在","voice":"能動態","mood":"直説法"},"g":"呼ぶ"},{"t":"καὶ","l":"καί","k":"カイ","p":"conj","g":"そして"},{"t":"πῶς","l":"πῶς","k":"ポース","p":"adv","g":"どのように"},{"t":"⸂αὐτοῦ","l":"αὐτός","k":"アウトウ","p":"pers","m":{"case":"属格","number":"単数","gender":"男性"},"g":"彼"},{"t":"υἱός⸃","l":"υἱός","k":"ウイオス","p":"noun","m":{"case":"主格","number":"単数","gender":"男性"},"g":"息子"},{"t":"ἐστιν","l":"εἰμί","k":"エスティン","p":"verb","m":{"person":"3人称","tense":"現在","voice":"能動態","mood":"直説法"},"g":"〜である"}]},{"verse":45,"words":[{"t":"Ἀκούοντος","l":"ἀκούω","k":"アコウオントス","p":"verb","m":{"tense":"現在","voice":"能動態","mood":"分詞","case":"属格","number":"単数","gender":"男性"},"g":"聞く"},{"t":"δὲ","l":"δέ","k":"デ","p":"conj","g":"しかし"},{"t":"παντὸς","l":"πᾶς","k":"パントス","p":"adj","m":{"case":"属格","number":"単数","gender":"男性"},"g":"すべての"},{"t":"τοῦ","l":"ὁ","k":"トウ","p":"art","m":{"case":"属格","number":"単数","gender":"男性"},"g":"その"},{"t":"λαοῦ","l":"λαός","k":"ラウー","p":"noun","m":{"case":"属格","number":"単数","gender":"男性"},"g":"民"},{"t":"εἶπεν","l":"λέγω","k":"エイペン","p":"verb","m":{"person":"3人称","tense":"アオリスト","voice":"能動態","mood":"直説法"},"g":"言う"},{"t":"τοῖς","l":"ὁ","k":"トイス","p":"art","m":{"case":"与格","number":"複数","gender":"男性"},"g":"その"},{"t":"⸀μαθηταῖς","l":"μαθητής","k":"マセータイス","p":"noun","m":{"case":"与格","number":"複数","gender":"男性"},"g":"弟子"}]},{"verse":46,"words":[{"t":"Προσέχετε","l":"προσέχω","k":"プロセケテ","p":"verb","m":{"person":"2人称","tense":"現在","voice":"能動態"},"g":"注意する"},{"t":"ἀπὸ","l":"ἀπό","k":"アポ","p":"prep","g":"〜から"},{"t":"τῶν","l":"ὁ","k":"トーン","p":"art","m":{"case":"属格","number":"複数","gender":"男性"},"g":"その"},{"t":"γραμματέων","l":"γραμματεύς","k":"グラムマテオーン","p":"noun","m":{"case":"属格","number":"複数","gender":"男性"},"g":"律法学者"},{"t":"τῶν","l":"ὁ","k":"トーン","p":"art","m":{"case":"属格","number":"複数","gender":"男性"},"g":"その"},{"t":"θελόντων","l":"θέλω","k":"セロントーン","p":"verb","m":{"tense":"現在","voice":"能動態","mood":"分詞","case":"属格","number":"複数","gender":"男性"},"g":"欲する"},{"t":"περιπατεῖν","l":"περιπατέω","k":"ペリパテイン","p":"verb","m":{"tense":"現在","voice":"能動態","mood":"不定詞"},"g":"歩く"},{"t":"ἐν","l":"ἐν","k":"エン","p":"prep","g":"〜の中に"},{"t":"στολαῖς","l":"στολή","k":"ストライス","p":"noun","m":{"case":"与格","number":"複数","gender":"女性"}},{"t":"καὶ","l":"καί","k":"カイ","p":"conj","g":"そして"},{"t":"φιλούντων","l":"φιλέω","k":"フィロウントーン","p":"verb","m":{"tense":"現在","voice":"能動態","mood":"分詞","case":"属格","number":"複数","gender":"男性"},"g":"愛する"},{"t":"ἀσπασμοὺς","l":"ἀσπασμός","k":"アスパスモウス","p":"noun","m":{"case":"対格","number":"複数","gender":"男性"}},{"t":"ἐν","l":"ἐν","k":"エン","p":"prep","g":"〜の中に"},{"t":"ταῖς","l":"ὁ","k":"タイス","p":"art","m":{"case":"与格","number":"複数","gender":"女性"},"g":"その"},{"t":"ἀγοραῖς","l":"ἀγορά","k":"アゴライス","p":"noun","m":{"case":"与格","number":"複数","gender":"女性"}},{"t":"καὶ","l":"καί","k":"カイ","p":"conj","g":"そして"},{"t":"πρωτοκαθεδρίας","l":"πρωτοκαθεδρία","k":"プロートカセドリアス","p":"noun","m":{"case":"対格","number":"複数","gender":"女性"}},{"t":"ἐν","l":"ἐν","k":"エン","p":"prep","g":"〜の中に"},{"t":"ταῖς","l":"ὁ","k":"タイス","p":"art","m":{"case":"与格","number":"複数","gender":"女性"},"g":"その"},{"t":"συναγωγαῖς","l":"συναγωγή","k":"シュナゴーガイス","p":"noun","m":{"case":"与格","number":"複数","gender":"女性"},"g":"会堂"},{"t":"καὶ","l":"καί","k":"カイ","p":"conj","g":"そして"},{"t":"πρωτοκλισίας","l":"πρωτοκλισία","k":"プロートクリシアス","p":"noun","m":{"case":"対格","number":"複数","gender":"女性"}},{"t":"ἐν","l":"ἐν","k":"エン","p":"prep","g":"〜の中に"},{"t":"τοῖς","l":"ὁ","k":"トイス","p":"art","m":{"case":"与格","number":"複数","gender":"中性"},"g":"その"},{"t":"δείπνοις","l":"δεῖπνον","k":"デイプノイス","p":"noun","m":{"case":"与格","number":"複数","gender":"中性"},"g":"食事"}]},{"verse":47,"words":[{"t":"οἳ","l":"ὅς","k":"オイ","p":"rel","m":{"case":"主格","number":"複数","gender":"男性"},"g":"〜ところの"},{"t":"κατεσθίουσιν","l":"κατεσθίω","k":"カテスシウーシン","p":"verb","m":{"person":"3人称","tense":"現在","voice":"能動態","mood":"直説法"},"g":"食い尽くす"},{"t":"τὰς","l":"ὁ","k":"タス","p":"art","m":{"case":"対格","number":"複数","gender":"女性"},"g":"その"},{"t":"οἰκίας","l":"οἰκία","k":"オイキアス","p":"noun","m":{"case":"対格","number":"複数","gender":"女性"},"g":"家"},{"t":"τῶν","l":"ὁ","k":"トーン","p":"art","m":{"case":"属格","number":"複数","gender":"女性"},"g":"その"},{"t":"χηρῶν","l":"χήρα","k":"ケーローン","p":"adj","m":{"case":"属格","number":"複数","gender":"女性"},"g":"やもめ"},{"t":"καὶ","l":"καί","k":"カイ","p":"conj","g":"そして"},{"t":"προφάσει","l":"πρόφασις","k":"プロファセイ","p":"noun","m":{"case":"与格","number":"単数","gender":"女性"}},{"t":"μακρὰ","l":"μακρός","k":"マクラ","p":"adj","m":{"case":"対格","number":"複数","gender":"中性"}},{"t":"προσεύχονται","l":"προσεύχομαι","k":"プロセウコンタイ","p":"verb","m":{"person":"3人称","tense":"現在","voice":"中動態","mood":"直説法"},"g":"祈る"},{"t":"οὗτοι","l":"οὗτος","k":"ウートイ","p":"dem","m":{"case":"主格","number":"複数","gender":"男性"},"g":"この"},{"t":"λήμψονται","l":"λαμβάνω","k":"レームプソンタイ","p":"verb","m":{"person":"3人称","tense":"未来","voice":"中動態","mood":"直説法"},"g":"受ける"},{"t":"περισσότερον","l":"περισσότερος","k":"ペリスソテロン","p":"adj","m":{"case":"対格","number":"単数","gender":"中性","degree":"比較級"},"g":"より多くの"},{"t":"κρίμα","l":"κρίμα","k":"クリマ","p":"noun","m":{"case":"対格","number":"単数","gender":"中性"},"g":"裁き"}]}]