[{"verse":1,"words":[{"t":"Παῦλος","l":"Παῦλος","k":"パウロス","p":"noun","m":{"case":"主格","number":"単数","gender":"男性"},"g":"パウロ"},{"t":"ἀπόστολος","l":"ἀπόστολος","k":"アポストロス","p":"noun","m":{"case":"主格","number":"単数","gender":"男性"},"g":"使徒"},{"t":"⸂Χριστοῦ","l":"Χριστός","k":"クリストウ","p":"noun","m":{"case":"属格","number":"単数","gender":"男性"},"g":"キリスト"},{"t":"Ἰησοῦ⸃","l":"Ἰησοῦς","k":"イエーソウ","p":"noun","m":{"case":"属格","number":"単数","gender":"男性"},"g":"イエス"},{"t":"κατ’","l":"κατά","k":"カタ","p":"prep","g":"〜に従って"},{"t":"ἐπιταγὴν","l":"ἐπιταγή","k":"エピタゲーン","p":"noun","m":{"case":"対格","number":"単数","gender":"女性"}},{"t":"θεοῦ","l":"θεός","k":"セウー","p":"noun","m":{"case":"属格","number":"単数","gender":"男性"},"g":"神"},{"t":"σωτῆρος","l":"σωτήρ","k":"ソーテーロス","p":"noun","m":{"case":"属格","number":"単数","gender":"男性"}},{"t":"ἡμῶν","l":"ἐγώ","k":"ヘーモーン","p":"pers","m":{"case":"属格","number":"複数"},"g":"私"},{"t":"καὶ","l":"καί","k":"カイ","p":"conj","g":"そして"},{"t":"⸂Χριστοῦ","l":"Χριστός","k":"クリストウ","p":"noun","m":{"case":"属格","number":"単数","gender":"男性"},"g":"キリスト"},{"t":"Ἰησοῦ⸃","l":"Ἰησοῦς","k":"イエーソウ","p":"noun","m":{"case":"属格","number":"単数","gender":"男性"},"g":"イエス"},{"t":"τῆς","l":"ὁ","k":"テース","p":"art","m":{"case":"属格","number":"単数","gender":"女性"},"g":"その"},{"t":"ἐλπίδος","l":"ἐλπίς","k":"エルピドス","p":"noun","m":{"case":"属格","number":"単数","gender":"女性"},"g":"希望"},{"t":"ἡμῶν","l":"ἐγώ","k":"ヘーモーン","p":"pers","m":{"case":"属格","number":"複数"},"g":"私"}]},{"verse":2,"words":[{"t":"Τιμοθέῳ","l":"Τιμόθεος","k":"ティモセオー","p":"noun","m":{"case":"与格","number":"単数","gender":"男性"}},{"t":"γνησίῳ","l":"γνήσιος","k":"グネーシオー","p":"adj","m":{"case":"与格","number":"単数","gender":"中性"}},{"t":"τέκνῳ","l":"τέκνον","k":"テクノー","p":"noun","m":{"case":"与格","number":"単数","gender":"中性"},"g":"子供"},{"t":"ἐν","l":"ἐν","k":"エン","p":"prep","g":"〜の中に"},{"t":"πίστει","l":"πίστις","k":"ピステイ","p":"noun","m":{"case":"与格","number":"単数","gender":"女性"},"g":"信仰"},{"t":"χάρις","l":"χάρις","k":"カリス","p":"noun","m":{"case":"主格","number":"単数","gender":"女性"},"g":"恵み"},{"t":"ἔλεος","l":"ἔλεος","k":"エレオス","p":"noun","m":{"case":"主格","number":"単数","gender":"中性"}},{"t":"εἰρήνη","l":"εἰρήνη","k":"エイレーネー","p":"noun","m":{"case":"主格","number":"単数","gender":"女性"},"g":"平和"},{"t":"ἀπὸ","l":"ἀπό","k":"アポ","p":"prep","g":"〜から"},{"t":"θεοῦ","l":"θεός","k":"セウー","p":"noun","m":{"case":"属格","number":"単数","gender":"男性"},"g":"神"},{"t":"⸀πατρὸς","l":"πατήρ","k":"パトロス","p":"noun","m":{"case":"属格","number":"単数","gender":"男性"},"g":"父"},{"t":"καὶ","l":"καί","k":"カイ","p":"conj","g":"そして"},{"t":"Χριστοῦ","l":"Χριστός","k":"クリストウ","p":"noun","m":{"case":"属格","number":"単数","gender":"男性"},"g":"キリスト"},{"t":"Ἰησοῦ","l":"Ἰησοῦς","k":"イエーソウ","p":"noun","m":{"case":"属格","number":"単数","gender":"男性"},"g":"イエス"},{"t":"τοῦ","l":"ὁ","k":"トウ","p":"art","m":{"case":"属格","number":"単数","gender":"男性"},"g":"その"},{"t":"κυρίου","l":"κύριος","k":"キュリウー","p":"noun","m":{"case":"属格","number":"単数","gender":"男性"},"g":"主人"},{"t":"ἡμῶν","l":"ἐγώ","k":"ヘーモーン","p":"pers","m":{"case":"属格","number":"複数"},"g":"私"}]},{"verse":3,"words":[{"t":"Καθὼς","l":"καθώς","k":"カソース","p":"conj","g":"〜のように"},{"t":"παρεκάλεσά","l":"παρακαλέω","k":"パレカレサ","p":"verb","m":{"person":"1人称","tense":"アオリスト","voice":"能動態","mood":"直説法"},"g":"励ます"},{"t":"σε","l":"σύ","k":"セ","p":"pers","m":{"case":"対格","number":"単数"},"g":"あなた"},{"t":"προσμεῖναι","l":"προσμένω","k":"プロスメイナイ","p":"verb","m":{"tense":"アオリスト","voice":"能動態","mood":"不定詞"}},{"t":"ἐν","l":"ἐν","k":"エン","p":"prep","g":"〜の中に"},{"t":"Ἐφέσῳ","l":"Ἔφεσος","k":"エフェソー","p":"noun","m":{"case":"与格","number":"単数","gender":"女性"}},{"t":"πορευόμενος","l":"πορεύομαι","k":"ポレウオメノス","p":"verb","m":{"tense":"現在","voice":"中動態","mood":"分詞","case":"主格","number":"単数","gender":"男性"},"g":"行く"},{"t":"εἰς","l":"εἰς","k":"エイス","p":"prep","g":"〜の中へ"},{"t":"Μακεδονίαν","l":"Μακεδονία","k":"マケドニアン","p":"noun","m":{"case":"対格","number":"単数","gender":"女性"}},{"t":"ἵνα","l":"ἵνα","k":"ヒナ","p":"conj","g":"〜するために"},{"t":"παραγγείλῃς","l":"παραγγέλλω","k":"パランゲイレース","p":"verb","m":{"person":"2人称","tense":"アオリスト","voice":"能動態","mood":"接続法"}},{"t":"τισὶν","l":"τις","k":"ティシン","p":"inter","m":{"case":"与格","number":"複数","gender":"男性"}},{"t":"μὴ","l":"μή","k":"メー","p":"adv","g":"〜ない"},{"t":"ἑτεροδιδασκαλεῖν","l":"ἑτεροδιδασκαλέω","k":"ヘテロディダスカレイン","p":"verb","m":{"tense":"現在","voice":"能動態","mood":"不定詞"}}]},{"verse":4,"words":[{"t":"μηδὲ","l":"μηδέ","k":"メーデ","p":"conj","g":"〜もない"},{"t":"προσέχειν","l":"προσέχω","k":"プロセケイン","p":"verb","m":{"tense":"現在","voice":"能動態","mood":"不定詞"}},{"t":"μύθοις","l":"μῦθος","k":"ミュソイス","p":"noun","m":{"case":"与格","number":"複数","gender":"男性"}},{"t":"καὶ","l":"καί","k":"カイ","p":"conj","g":"そして"},{"t":"γενεαλογίαις","l":"γενεαλογία","k":"ゲネアロギアイス","p":"noun","m":{"case":"与格","number":"複数","gender":"女性"}},{"t":"ἀπεράντοις","l":"ἀπέραντος","k":"アペラントイス","p":"adj","m":{"case":"与格","number":"複数","gender":"女性"}},{"t":"αἵτινες","l":"ὅστις","k":"アイティネス","p":"rel","m":{"case":"主格","number":"複数","gender":"女性"},"g":"〜ところの者"},{"t":"⸀ἐκζητήσεις","l":"ἐκζήτησις","k":"エクゼーテーセイス","p":"noun","m":{"case":"対格","number":"複数","gender":"女性"}},{"t":"παρέχουσι","l":"παρέχω","k":"パレコウシン","p":"verb","m":{"person":"3人称","tense":"現在","voice":"能動態","mood":"直説法"}},{"t":"μᾶλλον","l":"μᾶλλον","k":"マルロン","p":"adv","g":"むしろ"},{"t":"ἢ","l":"ἤ","k":"エー","p":"conj","g":"または"},{"t":"οἰκονομίαν","l":"οἰκονομία","k":"オイコノミアン","p":"noun","m":{"case":"対格","number":"単数","gender":"女性"}},{"t":"θεοῦ","l":"θεός","k":"セウー","p":"noun","m":{"case":"属格","number":"単数","gender":"男性"},"g":"神"},{"t":"τὴν","l":"ὁ","k":"テーン","p":"art","m":{"case":"対格","number":"単数","gender":"女性"},"g":"その"},{"t":"ἐν","l":"ἐν","k":"エン","p":"prep","g":"〜の中に"},{"t":"πίστει—","l":"πίστις","k":"ピステイ","p":"noun","m":{"case":"与格","number":"単数","gender":"女性"},"g":"信仰"}]},{"verse":5,"words":[{"t":"τὸ","l":"ὁ","k":"ト","p":"art","m":{"case":"主格","number":"単数","gender":"中性"},"g":"その"},{"t":"δὲ","l":"δέ","k":"デ","p":"conj","g":"しかし"},{"t":"τέλος","l":"τέλος","k":"テロス","p":"noun","m":{"case":"主格","number":"単数","gender":"中性"}},{"t":"τῆς","l":"ὁ","k":"テース","p":"art","m":{"case":"属格","number":"単数","gender":"女性"},"g":"その"},{"t":"παραγγελίας","l":"παραγγελία","k":"パランゲリアス","p":"noun","m":{"case":"属格","number":"単数","gender":"女性"}},{"t":"ἐστὶν","l":"εἰμί","k":"エスティン","p":"verb","m":{"person":"3人称","tense":"現在","voice":"能動態","mood":"直説法"},"g":"〜である"},{"t":"ἀγάπη","l":"ἀγάπη","k":"アガペー","p":"noun","m":{"case":"主格","number":"単数","gender":"女性"},"g":"愛"},{"t":"ἐκ","l":"ἐκ","k":"エク","p":"prep","g":"〜から"},{"t":"καθαρᾶς","l":"καθαρός","k":"カサラス","p":"adj","m":{"case":"属格","number":"単数","gender":"女性"}},{"t":"καρδίας","l":"καρδία","k":"カルディアス","p":"noun","m":{"case":"属格","number":"単数","gender":"女性"},"g":"心"},{"t":"καὶ","l":"καί","k":"カイ","p":"conj","g":"そして"},{"t":"συνειδήσεως","l":"συνείδησις","k":"シュネイデーセオース","p":"noun","m":{"case":"属格","number":"単数","gender":"女性"}},{"t":"ἀγαθῆς","l":"ἀγαθός","k":"アガセース","p":"adj","m":{"case":"属格","number":"単数","gender":"女性"},"g":"善い"},{"t":"καὶ","l":"καί","k":"カイ","p":"conj","g":"そして"},{"t":"πίστεως","l":"πίστις","k":"ピステオース","p":"noun","m":{"case":"属格","number":"単数","gender":"女性"},"g":"信仰"},{"t":"ἀνυποκρίτου","l":"ἀνυπόκριτος","k":"アニュポクリトウ","p":"adj","m":{"case":"属格","number":"単数","gender":"女性"}}]},{"verse":6,"words":[{"t":"ὧν","l":"ὅς","k":"オーン","p":"rel","m":{"case":"属格","number":"複数","gender":"女性"},"g":"〜ところの"},{"t":"τινες","l":"τις","k":"ティネス","p":"inter","m":{"case":"主格","number":"複数","gender":"男性"}},{"t":"ἀστοχήσαντες","l":"ἀστοχέω","k":"アストケーサンテス","p":"verb","m":{"tense":"アオリスト","voice":"能動態","mood":"分詞","case":"主格","number":"複数","gender":"男性"}},{"t":"ἐξετράπησαν","l":"ἐκτρέπομαι","k":"エクセトラペーサン","p":"verb","m":{"person":"3人称","tense":"アオリスト","voice":"受動態","mood":"直説法"}},{"t":"εἰς","l":"εἰς","k":"エイス","p":"prep","g":"〜の中へ"},{"t":"ματαιολογίαν","l":"ματαιολογία","k":"マタイオロギアン","p":"noun","m":{"case":"対格","number":"単数","gender":"女性"}}]},{"verse":7,"words":[{"t":"θέλοντες","l":"θέλω","k":"セロンテス","p":"verb","m":{"tense":"現在","voice":"能動態","mood":"分詞","case":"主格","number":"複数","gender":"男性"},"g":"欲する"},{"t":"εἶναι","l":"εἰμί","k":"エイナイ","p":"verb","m":{"tense":"現在","voice":"能動態","mood":"不定詞"},"g":"〜である"},{"t":"νομοδιδάσκαλοι","l":"νομοδιδάσκαλος","k":"ノモディダスカロイ","p":"noun","m":{"case":"主格","number":"複数","gender":"男性"}},{"t":"μὴ","l":"μή","k":"メー","p":"adv","g":"〜ない"},{"t":"νοοῦντες","l":"νοέω","k":"ノウーンテス","p":"verb","m":{"tense":"現在","voice":"能動態","mood":"分詞","case":"主格","number":"複数","gender":"男性"}},{"t":"μήτε","l":"μήτε","k":"メーテ","p":"conj","g":"〜もない"},{"t":"ἃ","l":"ὅς","k":"ハ","p":"rel","m":{"case":"対格","number":"複数","gender":"中性"},"g":"〜ところの"},{"t":"λέγουσιν","l":"λέγω","k":"レゴウシン","p":"verb","m":{"person":"3人称","tense":"現在","voice":"能動態","mood":"直説法"},"g":"言う"},{"t":"μήτε","l":"μήτε","k":"メーテ","p":"conj","g":"〜もない"},{"t":"περὶ","l":"περί","k":"ペリ","p":"prep","g":"〜について"},{"t":"τίνων","l":"τίς","k":"ティノーン","p":"inter","m":{"case":"属格","number":"複数","gender":"中性"},"g":"誰"},{"t":"διαβεβαιοῦνται","l":"διαβεβαιόομαι","k":"ディアベバイウーンタイ","p":"verb","m":{"person":"3人称","tense":"現在","voice":"中動態","mood":"直説法"}}]},{"verse":8,"words":[{"t":"Οἴδαμεν","l":"οἶδα","k":"オイダメン","p":"verb","m":{"person":"1人称","voice":"能動態","mood":"直説法"},"g":"知る"},{"t":"δὲ","l":"δέ","k":"デ","p":"conj","g":"しかし"},{"t":"ὅτι","l":"ὅτι","k":"ホティ","p":"conj","g":"〜ということ"},{"t":"καλὸς","l":"καλός","k":"カロス","p":"adj","m":{"case":"主格","number":"単数","gender":"男性"},"g":"良い"},{"t":"ὁ","l":"ὁ","k":"ホ","p":"art","m":{"case":"主格","number":"単数","gender":"男性"},"g":"その"},{"t":"νόμος","l":"νόμος","k":"ノモス","p":"noun","m":{"case":"主格","number":"単数","gender":"男性"},"g":"律法"},{"t":"ἐάν","l":"ἐάν","k":"エアン","p":"conj","g":"もし〜なら"},{"t":"τις","l":"τις","k":"ティス","p":"inter","m":{"case":"主格","number":"単数","gender":"男性"}},{"t":"αὐτῷ","l":"αὐτός","k":"アウトー","p":"pers","m":{"case":"与格","number":"単数","gender":"男性"},"g":"彼"},{"t":"νομίμως","l":"νομίμως","k":"ノミモース","p":"adv"},{"t":"χρῆται","l":"χράομαι","k":"クレータイ","p":"verb","m":{"person":"3人称","tense":"現在","voice":"中動態","mood":"接続法"}}]},{"verse":9,"words":[{"t":"εἰδὼς","l":"ὁράω","k":"エイドース","p":"verb","m":{"voice":"能動態","mood":"分詞","case":"主格","number":"単数","gender":"男性"},"g":"見る"},{"t":"τοῦτο","l":"οὗτος","k":"トウト","p":"dem","m":{"case":"対格","number":"単数","gender":"中性"},"g":"この"},{"t":"ὅτι","l":"ὅτι","k":"ホティ","p":"adv","g":"〜ということ"},{"t":"δικαίῳ","l":"δίκαιος","k":"ディカイオー","p":"adj","m":{"case":"与格","number":"単数","gender":"男性"},"g":"正しい"},{"t":"νόμος","l":"νόμος","k":"ノモス","p":"noun","m":{"case":"主格","number":"単数","gender":"男性"},"g":"律法"},{"t":"οὐ","l":"οὐ","k":"ウー","p":"adv","g":"〜ない"},{"t":"κεῖται","l":"κεῖμαι","k":"ケイタイ","p":"verb","m":{"person":"3人称","tense":"現在","voice":"中動態","mood":"直説法"}},{"t":"ἀνόμοις","l":"ἄνομος","k":"アノモイス","p":"adj","m":{"case":"与格","number":"複数","gender":"男性"}},{"t":"δὲ","l":"δέ","k":"デ","p":"conj","g":"しかし"},{"t":"καὶ","l":"καί","k":"カイ","p":"conj","g":"そして"},{"t":"ἀνυποτάκτοις","l":"ἀνυπότακτος","k":"アニュポタクトイス","p":"adj","m":{"case":"与格","number":"複数","gender":"男性"}},{"t":"ἀσεβέσι","l":"ἀσεβής","k":"アセベシン","p":"adj","m":{"case":"与格","number":"複数","gender":"男性"}},{"t":"καὶ","l":"καί","k":"カイ","p":"conj","g":"そして"},{"t":"ἁμαρτωλοῖς","l":"ἁμαρτωλός","k":"ハマルトーロイス","p":"adj","m":{"case":"与格","number":"複数","gender":"男性"}},{"t":"ἀνοσίοις","l":"ἀνόσιος","k":"アノシオイス","p":"adj","m":{"case":"与格","number":"複数","gender":"男性"}},{"t":"καὶ","l":"καί","k":"カイ","p":"conj","g":"そして"},{"t":"βεβήλοις","l":"βέβηλος","k":"ベベーロイス","p":"adj","m":{"case":"与格","number":"複数","gender":"男性"}},{"t":"πατρολῴαις","l":"πατρολῴας","k":"パトロローアイス","p":"noun","m":{"case":"与格","number":"複数","gender":"男性"}},{"t":"καὶ","l":"καί","k":"カイ","p":"conj","g":"そして"},{"t":"μητρολῴαις","l":"μητρολῴας","k":"メートロローアイス","p":"noun","m":{"case":"与格","number":"複数","gender":"男性"}},{"t":"ἀνδροφόνοις","l":"ἀνδροφόνος","k":"アンドロフォノイス","p":"noun","m":{"case":"与格","number":"複数","gender":"男性"}}]},{"verse":10,"words":[{"t":"πόρνοις","l":"πόρνος","k":"ポルノイス","p":"noun","m":{"case":"与格","number":"複数","gender":"男性"}},{"t":"ἀρσενοκοίταις","l":"ἀρσενοκοίτης","k":"アルセノコイタイス","p":"noun","m":{"case":"与格","number":"複数","gender":"男性"}},{"t":"ἀνδραποδισταῖς","l":"ἀνδραποδιστής","k":"アンドラポディスタイス","p":"noun","m":{"case":"与格","number":"複数","gender":"男性"}},{"t":"ψεύσταις","l":"ψεύστης","k":"プセウスタイス","p":"noun","m":{"case":"与格","number":"複数","gender":"男性"}},{"t":"ἐπιόρκοις","l":"ἐπίορκος","k":"エピオルコイス","p":"adj","m":{"case":"与格","number":"複数","gender":"男性"}},{"t":"καὶ","l":"καί","k":"カイ","p":"conj","g":"そして"},{"t":"εἴ","l":"εἰ","k":"エイ","p":"conj","g":"もし"},{"t":"τι","l":"τις","k":"ティ","p":"inter","m":{"case":"主格","number":"単数","gender":"中性"}},{"t":"ἕτερον","l":"ἕτερος","k":"ヘテロン","p":"adj","m":{"case":"主格","number":"単数","gender":"中性"},"g":"他の"},{"t":"τῇ","l":"ὁ","k":"テー","p":"art","m":{"case":"与格","number":"単数","gender":"女性"},"g":"その"},{"t":"ὑγιαινούσῃ","l":"ὑγιαίνω","k":"フギアイノウセー","p":"verb","m":{"tense":"現在","voice":"能動態","mood":"分詞","case":"与格","number":"単数","gender":"女性"}},{"t":"διδασκαλίᾳ","l":"διδασκαλία","k":"ディダスカリア","p":"noun","m":{"case":"与格","number":"単数","gender":"女性"}},{"t":"ἀντίκειται","l":"ἀντίκειμαι","k":"アンティケイタイ","p":"verb","m":{"person":"3人称","tense":"現在","voice":"中動態","mood":"直説法"}}]},{"verse":11,"words":[{"t":"κατὰ","l":"κατά","k":"カタ","p":"prep","g":"〜に従って"},{"t":"τὸ","l":"ὁ","k":"ト","p":"art","m":{"case":"対格","number":"単数","gender":"中性"},"g":"その"},{"t":"εὐαγγέλιον","l":"εὐαγγέλιον","k":"エウアンゲリオン","p":"noun","m":{"case":"対格","number":"単数","gender":"中性"},"g":"福音"},{"t":"τῆς","l":"ὁ","k":"テース","p":"art","m":{"case":"属格","number":"単数","gender":"女性"},"g":"その"},{"t":"δόξης","l":"δόξα","k":"ドクセース","p":"noun","m":{"case":"属格","number":"単数","gender":"女性"},"g":"栄光"},{"t":"τοῦ","l":"ὁ","k":"トウ","p":"art","m":{"case":"属格","number":"単数","gender":"男性"},"g":"その"},{"t":"μακαρίου","l":"μακάριος","k":"マカリウー","p":"adj","m":{"case":"属格","number":"単数","gender":"男性"}},{"t":"θεοῦ","l":"θεός","k":"セウー","p":"noun","m":{"case":"属格","number":"単数","gender":"男性"},"g":"神"},{"t":"ὃ","l":"ὅς","k":"ホ","p":"rel","m":{"case":"対格","number":"単数","gender":"中性"},"g":"〜ところの"},{"t":"ἐπιστεύθην","l":"πιστεύω","k":"エピステウセーン","p":"verb","m":{"person":"1人称","tense":"アオリスト","voice":"受動態","mood":"直説法"},"g":"信じる"},{"t":"ἐγώ","l":"ἐγώ","k":"エゴー","p":"pers","m":{"case":"主格","number":"単数"},"g":"私"}]},{"verse":12,"words":[{"t":"⸀Χάριν","l":"χάρις","k":"カリン","p":"noun","m":{"case":"対格","number":"単数","gender":"女性"},"g":"恵み"},{"t":"ἔχω","l":"ἔχω","k":"エコー","p":"verb","m":{"person":"1人称","tense":"現在","voice":"能動態","mood":"直説法"},"g":"持つ"},{"t":"τῷ","l":"ὁ","k":"トー","p":"art","m":{"case":"与格","number":"単数","gender":"男性"},"g":"その"},{"t":"ἐνδυναμώσαντί","l":"ἐνδυναμόω","k":"エンデュナモーサンティ","p":"verb","m":{"tense":"アオリスト","voice":"能動態","mood":"分詞","case":"与格","number":"単数","gender":"男性"}},{"t":"με","l":"ἐγώ","k":"メ","p":"pers","m":{"case":"対格","number":"単数"},"g":"私"},{"t":"Χριστῷ","l":"Χριστός","k":"クリストー","p":"noun","m":{"case":"与格","number":"単数","gender":"男性"},"g":"キリスト"},{"t":"Ἰησοῦ","l":"Ἰησοῦς","k":"イエーソウ","p":"noun","m":{"case":"与格","number":"単数","gender":"男性"},"g":"イエス"},{"t":"τῷ","l":"ὁ","k":"トー","p":"art","m":{"case":"与格","number":"単数","gender":"男性"},"g":"その"},{"t":"κυρίῳ","l":"κύριος","k":"キュリオー","p":"noun","m":{"case":"与格","number":"単数","gender":"男性"},"g":"主人"},{"t":"ἡμῶν","l":"ἐγώ","k":"ヘーモーン","p":"pers","m":{"case":"属格","number":"複数"},"g":"私"},{"t":"ὅτι","l":"ὅτι","k":"ホティ","p":"conj","g":"〜ということ"},{"t":"πιστόν","l":"πιστός","k":"ピストン","p":"adj","m":{"case":"対格","number":"単数","gender":"男性"},"g":"忠実な"},{"t":"με","l":"ἐγώ","k":"メ","p":"pers","m":{"case":"対格","number":"単数"},"g":"私"},{"t":"ἡγήσατο","l":"ἡγέομαι","k":"ヘーゲーサト","p":"verb","m":{"person":"3人称","tense":"アオリスト","voice":"中動態","mood":"直説法"}},{"t":"θέμενος","l":"τίθημι","k":"セメノス","p":"verb","m":{"tense":"アオリスト","voice":"中動態","mood":"分詞","case":"主格","number":"単数","gender":"男性"},"g":"置く"},{"t":"εἰς","l":"εἰς","k":"エイス","p":"prep","g":"〜の中へ"},{"t":"διακονίαν","l":"διακονία","k":"ディアコニアン","p":"noun","m":{"case":"対格","number":"単数","gender":"女性"}}]},{"verse":13,"words":[{"t":"⸀τὸ","l":"ὁ","k":"ト","p":"art","m":{"case":"対格","number":"単数","gender":"中性"},"g":"その"},{"t":"πρότερον","l":"πρότερος","k":"プロテロン","p":"adj","m":{"case":"対格","number":"単数","gender":"中性","degree":"比較級"}},{"t":"ὄντα","l":"εἰμί","k":"オンタ","p":"verb","m":{"tense":"現在","voice":"能動態","mood":"分詞","case":"対格","number":"単数","gender":"男性"},"g":"〜である"},{"t":"βλάσφημον","l":"βλάσφημος","k":"ブラスフェーモン","p":"adj","m":{"case":"対格","number":"単数","gender":"男性"}},{"t":"καὶ","l":"καί","k":"カイ","p":"conj","g":"そして"},{"t":"διώκτην","l":"διώκτης","k":"ディオークテーン","p":"noun","m":{"case":"対格","number":"単数","gender":"男性"}},{"t":"καὶ","l":"καί","k":"カイ","p":"conj","g":"そして"},{"t":"ὑβριστήν","l":"ὑβριστής","k":"フブリステーン","p":"noun","m":{"case":"対格","number":"単数","gender":"男性"}},{"t":"ἀλλὰ","l":"ἀλλά","k":"アルラ","p":"conj","g":"しかし"},{"t":"ἠλεήθην","l":"ἐλεάω","k":"エーレエーセーン","p":"verb","m":{"person":"1人称","tense":"アオリスト","voice":"受動態","mood":"直説法"}},{"t":"ὅτι","l":"ὅτι","k":"ホティ","p":"conj","g":"〜ということ"},{"t":"ἀγνοῶν","l":"ἀγνοέω","k":"アグノオーン","p":"verb","m":{"tense":"現在","voice":"能動態","mood":"分詞","case":"主格","number":"単数","gender":"男性"}},{"t":"ἐποίησα","l":"ποιέω","k":"エポイエーサ","p":"verb","m":{"person":"1人称","tense":"アオリスト","voice":"能動態","mood":"直説法"},"g":"する"},{"t":"ἐν","l":"ἐν","k":"エン","p":"prep","g":"〜の中に"},{"t":"ἀπιστίᾳ","l":"ἀπιστία","k":"アピスティア","p":"noun","m":{"case":"与格","number":"単数","gender":"女性"}}]},{"verse":14,"words":[{"t":"ὑπερεπλεόνασεν","l":"ὑπερπλεονάζω","k":"フペレプレオナセン","p":"verb","m":{"person":"3人称","tense":"アオリスト","voice":"能動態","mood":"直説法"}},{"t":"δὲ","l":"δέ","k":"デ","p":"conj","g":"しかし"},{"t":"ἡ","l":"ὁ","k":"ヘー","p":"art","m":{"case":"主格","number":"単数","gender":"女性"},"g":"その"},{"t":"χάρις","l":"χάρις","k":"カリス","p":"noun","m":{"case":"主格","number":"単数","gender":"女性"},"g":"恵み"},{"t":"τοῦ","l":"ὁ","k":"トウ","p":"art","m":{"case":"属格","number":"単数","gender":"男性"},"g":"その"},{"t":"κυρίου","l":"κύριος","k":"キュリウー","p":"noun","m":{"case":"属格","number":"単数","gender":"男性"},"g":"主人"},{"t":"ἡμῶν","l":"ἐγώ","k":"ヘーモーン","p":"pers","m":{"case":"属格","number":"複数"},"g":"私"},{"t":"μετὰ","l":"μετά","k":"メタ","p":"prep","g":"〜と共に"},{"t":"πίστεως","l":"πίστις","k":"ピステオース","p":"noun","m":{"case":"属格","number":"単数","gender":"女性"},"g":"信仰"},{"t":"καὶ","l":"καί","k":"カイ","p":"conj","g":"そして"},{"t":"ἀγάπης","l":"ἀγάπη","k":"アガペース","p":"noun","m":{"case":"属格","number":"単数","gender":"女性"},"g":"愛"},{"t":"τῆς","l":"ὁ","k":"テース","p":"art","m":{"case":"属格","number":"単数","gender":"女性"},"g":"その"},{"t":"ἐν","l":"ἐν","k":"エン","p":"prep","g":"〜の中に"},{"t":"Χριστῷ","l":"Χριστός","k":"クリストー","p":"noun","m":{"case":"与格","number":"単数","gender":"男性"},"g":"キリスト"},{"t":"Ἰησοῦ","l":"Ἰησοῦς","k":"イエーソウ","p":"noun","m":{"case":"与格","number":"単数","gender":"男性"},"g":"イエス"}]},{"verse":15,"words":[{"t":"πιστὸς","l":"πιστός","k":"ピストス","p":"adj","m":{"case":"主格","number":"単数","gender":"男性"},"g":"忠実な"},{"t":"ὁ","l":"ὁ","k":"ホ","p":"art","m":{"case":"主格","number":"単数","gender":"男性"},"g":"その"},{"t":"λόγος","l":"λόγος","k":"ロゴス","p":"noun","m":{"case":"主格","number":"単数","gender":"男性"},"g":"ことば"},{"t":"καὶ","l":"καί","k":"カイ","p":"conj","g":"そして"},{"t":"πάσης","l":"πᾶς","k":"パセース","p":"adj","m":{"case":"属格","number":"単数","gender":"女性"},"g":"すべての"},{"t":"ἀποδοχῆς","l":"ἀποδοχή","k":"アポドケース","p":"noun","m":{"case":"属格","number":"単数","gender":"女性"}},{"t":"ἄξιος","l":"ἄξιος","k":"アクシオス","p":"adj","m":{"case":"主格","number":"単数","gender":"男性"},"g":"ふさわしい"},{"t":"ὅτι","l":"ὅτι","k":"ホティ","p":"adv","g":"〜ということ"},{"t":"Χριστὸς","l":"Χριστός","k":"クリストス","p":"noun","m":{"case":"主格","number":"単数","gender":"男性"},"g":"キリスト"},{"t":"Ἰησοῦς","l":"Ἰησοῦς","k":"イエーソウス","p":"noun","m":{"case":"主格","number":"単数","gender":"男性"},"g":"イエス"},{"t":"ἦλθεν","l":"ἔρχομαι","k":"エールセン","p":"verb","m":{"person":"3人称","tense":"アオリスト","voice":"能動態","mood":"直説法"},"g":"来る"},{"t":"εἰς","l":"εἰς","k":"エイス","p":"prep","g":"〜の中へ"},{"t":"τὸν","l":"ὁ","k":"トン","p":"art","m":{"case":"対格","number":"単数","gender":"男性"},"g":"その"},{"t":"κόσμον","l":"κόσμος","k":"コスモン","p":"noun","m":{"case":"対格","number":"単数","gender":"男性"},"g":"世"},{"t":"ἁμαρτωλοὺς","l":"ἁμαρτωλός","k":"ハマルトーロウス","p":"adj","m":{"case":"対格","number":"複数","gender":"男性"}},{"t":"σῶσαι","l":"σῴζω","k":"ソーサイ","p":"verb","m":{"tense":"アオリスト","voice":"能動態","mood":"不定詞"},"g":"救う"},{"t":"ὧν","l":"ὅς","k":"オーン","p":"rel","m":{"case":"属格","number":"複数","gender":"男性"},"g":"〜ところの"},{"t":"πρῶτός","l":"πρῶτος","k":"プロートス","p":"adj","m":{"case":"主格","number":"単数","gender":"男性"},"g":"第一の"},{"t":"εἰμι","l":"εἰμί","k":"エイミ","p":"verb","m":{"person":"1人称","tense":"現在","voice":"能動態","mood":"直説法"},"g":"〜である"},{"t":"ἐγώ","l":"ἐγώ","k":"エゴー","p":"pers","m":{"case":"主格","number":"単数"},"g":"私"}]},{"verse":16,"words":[{"t":"ἀλλὰ","l":"ἀλλά","k":"アルラ","p":"conj","g":"しかし"},{"t":"διὰ","l":"διά","k":"ディア","p":"prep","g":"〜を通して"},{"t":"τοῦτο","l":"οὗτος","k":"トウト","p":"dem","m":{"case":"対格","number":"単数","gender":"中性"},"g":"この"},{"t":"ἠλεήθην","l":"ἐλεάω","k":"エーレエーセーン","p":"verb","m":{"person":"1人称","tense":"アオリスト","voice":"受動態","mood":"直説法"}},{"t":"ἵνα","l":"ἵνα","k":"ヒナ","p":"conj","g":"〜するために"},{"t":"ἐν","l":"ἐν","k":"エン","p":"prep","g":"〜の中に"},{"t":"ἐμοὶ","l":"ἐγώ","k":"エモイ","p":"pers","m":{"case":"与格","number":"単数"},"g":"私"},{"t":"πρώτῳ","l":"πρῶτος","k":"プロートー","p":"adj","m":{"case":"与格","number":"単数","gender":"男性"},"g":"第一の"},{"t":"ἐνδείξηται","l":"ἐνδείκνυμι","k":"エンデイクセータイ","p":"verb","m":{"person":"3人称","tense":"アオリスト","voice":"中動態","mood":"接続法"}},{"t":"⸂Χριστὸς","l":"Χριστός","k":"クリストス","p":"noun","m":{"case":"主格","number":"単数","gender":"男性"},"g":"キリスト"},{"t":"Ἰησοῦς⸃","l":"Ἰησοῦς","k":"イエーソウス","p":"noun","m":{"case":"主格","number":"単数","gender":"男性"},"g":"イエス"},{"t":"τὴν","l":"ὁ","k":"テーン","p":"art","m":{"case":"対格","number":"単数","gender":"女性"},"g":"その"},{"t":"⸀ἅπασαν","l":"ἅπας","k":"ハパサン","p":"adj","m":{"case":"対格","number":"単数","gender":"女性"}},{"t":"μακροθυμίαν","l":"μακροθυμία","k":"マクロシュミアン","p":"noun","m":{"case":"対格","number":"単数","gender":"女性"}},{"t":"πρὸς","l":"πρός","k":"プロス","p":"prep","g":"〜に向かって"},{"t":"ὑποτύπωσιν","l":"ὑποτύπωσις","k":"フポテュポーシン","p":"noun","m":{"case":"対格","number":"単数","gender":"女性"}},{"t":"τῶν","l":"ὁ","k":"トーン","p":"art","m":{"case":"属格","number":"複数","gender":"男性"},"g":"その"},{"t":"μελλόντων","l":"μέλλω","k":"メルロントーン","p":"verb","m":{"tense":"現在","voice":"能動態","mood":"分詞","case":"属格","number":"複数","gender":"男性"},"g":"〜しようとする"},{"t":"πιστεύειν","l":"πιστεύω","k":"ピステウエイン","p":"verb","m":{"tense":"現在","voice":"能動態","mood":"不定詞"},"g":"信じる"},{"t":"ἐπ’","l":"ἐπί","k":"エピ","p":"prep","g":"〜の上に"},{"t":"αὐτῷ","l":"αὐτός","k":"アウトー","p":"pers","m":{"case":"与格","number":"単数","gender":"男性"},"g":"彼"},{"t":"εἰς","l":"εἰς","k":"エイス","p":"prep","g":"〜の中へ"},{"t":"ζωὴν","l":"ζωή","k":"ゾーエーン","p":"noun","m":{"case":"対格","number":"単数","gender":"女性"},"g":"いのち"},{"t":"αἰώνιον","l":"αἰώνιος","k":"アイオーニオン","p":"adj","m":{"case":"対格","number":"単数","gender":"女性"},"g":"永遠の"}]},{"verse":17,"words":[{"t":"τῷ","l":"ὁ","k":"トー","p":"art","m":{"case":"与格","number":"単数","gender":"男性"},"g":"その"},{"t":"δὲ","l":"δέ","k":"デ","p":"conj","g":"しかし"},{"t":"βασιλεῖ","l":"βασιλεύς","k":"バシレイ","p":"noun","m":{"case":"与格","number":"単数","gender":"男性"},"g":"王"},{"t":"τῶν","l":"ὁ","k":"トーン","p":"art","m":{"case":"属格","number":"複数","gender":"男性"},"g":"その"},{"t":"αἰώνων","l":"αἰών","k":"アイオーノーン","p":"noun","m":{"case":"属格","number":"複数","gender":"男性"},"g":"時代"},{"t":"ἀφθάρτῳ","l":"ἄφθαρτος","k":"アフサルトー","p":"adj","m":{"case":"与格","number":"単数","gender":"男性"}},{"t":"ἀοράτῳ","l":"ἀόρατος","k":"アオラトー","p":"adj","m":{"case":"与格","number":"単数","gender":"男性"}},{"t":"⸀μόνῳ","l":"μόνος","k":"モノー","p":"adj","m":{"case":"与格","number":"単数","gender":"男性"},"g":"ただ〜だけ"},{"t":"θεῷ","l":"θεός","k":"セオー","p":"noun","m":{"case":"与格","number":"単数","gender":"男性"},"g":"神"},{"t":"τιμὴ","l":"τιμή","k":"ティメー","p":"noun","m":{"case":"主格","number":"単数","gender":"女性"}},{"t":"καὶ","l":"καί","k":"カイ","p":"conj","g":"そして"},{"t":"δόξα","l":"δόξα","k":"ドクサ","p":"noun","m":{"case":"主格","number":"単数","gender":"女性"},"g":"栄光"},{"t":"εἰς","l":"εἰς","k":"エイス","p":"prep","g":"〜の中へ"},{"t":"τοὺς","l":"ὁ","k":"トウス","p":"art","m":{"case":"対格","number":"複数","gender":"男性"},"g":"その"},{"t":"αἰῶνας","l":"αἰών","k":"アイオーナス","p":"noun","m":{"case":"対格","number":"複数","gender":"男性"},"g":"時代"},{"t":"τῶν","l":"ὁ","k":"トーン","p":"art","m":{"case":"属格","number":"複数","gender":"男性"},"g":"その"},{"t":"αἰώνων","l":"αἰών","k":"アイオーノーン","p":"noun","m":{"case":"属格","number":"複数","gender":"男性"},"g":"時代"},{"t":"ἀμήν","l":"ἀμήν","k":"アメーン","p":"part","g":"アーメン"}]},{"verse":18,"words":[{"t":"Ταύτην","l":"οὗτος","k":"タウテーン","p":"dem","m":{"case":"対格","number":"単数","gender":"女性"},"g":"この"},{"t":"τὴν","l":"ὁ","k":"テーン","p":"art","m":{"case":"対格","number":"単数","gender":"女性"},"g":"その"},{"t":"παραγγελίαν","l":"παραγγελία","k":"パランゲリアン","p":"noun","m":{"case":"対格","number":"単数","gender":"女性"}},{"t":"παρατίθεμαί","l":"παρατίθημι","k":"パラティセマイ","p":"verb","m":{"person":"1人称","tense":"現在","voice":"中動態","mood":"直説法"}},{"t":"σοι","l":"σύ","k":"ソイ","p":"pers","m":{"case":"与格","number":"単数"},"g":"あなた"},{"t":"τέκνον","l":"τέκνον","k":"テクノン","p":"noun","m":{"case":"呼格","number":"単数","gender":"中性"},"g":"子供"},{"t":"Τιμόθεε","l":"Τιμόθεος","k":"ティモセエ","p":"noun","m":{"case":"呼格","number":"単数","gender":"男性"}},{"t":"κατὰ","l":"κατά","k":"カタ","p":"prep","g":"〜に従って"},{"t":"τὰς","l":"ὁ","k":"タス","p":"art","m":{"case":"対格","number":"複数","gender":"女性"},"g":"その"},{"t":"προαγούσας","l":"προάγω","k":"プロアゴウサス","p":"verb","m":{"tense":"現在","voice":"能動態","mood":"分詞","case":"対格","number":"複数","gender":"女性"}},{"t":"ἐπὶ","l":"ἐπί","k":"エピ","p":"prep","g":"〜の上に"},{"t":"σὲ","l":"σύ","k":"セ","p":"pers","m":{"case":"対格","number":"単数"},"g":"あなた"},{"t":"προφητείας","l":"προφητεία","k":"プロフェーテイアス","p":"noun","m":{"case":"対格","number":"複数","gender":"女性"}},{"t":"ἵνα","l":"ἵνα","k":"ヒナ","p":"adv","g":"〜するために"},{"t":"⸀στρατεύῃ","l":"στρατεύομαι","k":"ストラテウエー","p":"verb","m":{"person":"2人称","tense":"現在","voice":"中動態","mood":"接続法"}},{"t":"ἐν","l":"ἐν","k":"エン","p":"prep","g":"〜の中に"},{"t":"αὐταῖς","l":"αὐτός","k":"アウタイス","p":"pers","m":{"case":"与格","number":"複数","gender":"女性"},"g":"彼"},{"t":"τὴν","l":"ὁ","k":"テーン","p":"art","m":{"case":"対格","number":"単数","gender":"女性"},"g":"その"},{"t":"καλὴν","l":"καλός","k":"カレーン","p":"adj","m":{"case":"対格","number":"単数","gender":"女性"},"g":"良い"},{"t":"στρατείαν","l":"στρατεία","k":"ストラテイアン","p":"noun","m":{"case":"対格","number":"単数","gender":"女性"}}]},{"verse":19,"words":[{"t":"ἔχων","l":"ἔχω","k":"エコーン","p":"verb","m":{"tense":"現在","voice":"能動態","mood":"分詞","case":"主格","number":"単数","gender":"男性"},"g":"持つ"},{"t":"πίστιν","l":"πίστις","k":"ピスティン","p":"noun","m":{"case":"対格","number":"単数","gender":"女性"},"g":"信仰"},{"t":"καὶ","l":"καί","k":"カイ","p":"conj","g":"そして"},{"t":"ἀγαθὴν","l":"ἀγαθός","k":"アガセーン","p":"adj","m":{"case":"対格","number":"単数","gender":"女性"},"g":"善い"},{"t":"συνείδησιν","l":"συνείδησις","k":"シュネイデーシン","p":"noun","m":{"case":"対格","number":"単数","gender":"女性"}},{"t":"ἥν","l":"ὅς","k":"ヘーン","p":"rel","m":{"case":"対格","number":"単数","gender":"女性"},"g":"〜ところの"},{"t":"τινες","l":"τις","k":"ティネス","p":"inter","m":{"case":"主格","number":"複数","gender":"男性"}},{"t":"ἀπωσάμενοι","l":"ἀπωθέομαι","k":"アポーサメノイ","p":"verb","m":{"tense":"アオリスト","voice":"中動態","mood":"分詞","case":"主格","number":"複数","gender":"男性"}},{"t":"περὶ","l":"περί","k":"ペリ","p":"prep","g":"〜について"},{"t":"τὴν","l":"ὁ","k":"テーン","p":"art","m":{"case":"対格","number":"単数","gender":"女性"},"g":"その"},{"t":"πίστιν","l":"πίστις","k":"ピスティン","p":"noun","m":{"case":"対格","number":"単数","gender":"女性"},"g":"信仰"},{"t":"ἐναυάγησαν","l":"ναυαγέω","k":"エナウアゲーサン","p":"verb","m":{"person":"3人称","tense":"アオリスト","voice":"能動態","mood":"直説法"}}]},{"verse":20,"words":[{"t":"ὧν","l":"ὅς","k":"オーン","p":"rel","m":{"case":"属格","number":"複数","gender":"男性"},"g":"〜ところの"},{"t":"ἐστιν","l":"εἰμί","k":"エスティン","p":"verb","m":{"person":"3人称","tense":"現在","voice":"能動態","mood":"直説法"},"g":"〜である"},{"t":"Ὑμέναιος","l":"Ὑμέναιος","k":"ウメナイオス","p":"noun","m":{"case":"主格","number":"単数","gender":"男性"}},{"t":"καὶ","l":"καί","k":"カイ","p":"conj","g":"そして"},{"t":"Ἀλέξανδρος","l":"Ἀλέξανδρος","k":"アレクサンドロス","p":"noun","m":{"case":"主格","number":"単数","gender":"男性"}},{"t":"οὓς","l":"ὅς","k":"ウース","p":"rel","m":{"case":"対格","number":"複数","gender":"男性"},"g":"〜ところの"},{"t":"παρέδωκα","l":"παραδίδωμι","k":"パレドーカ","p":"verb","m":{"person":"1人称","tense":"アオリスト","voice":"能動態","mood":"直説法"},"g":"引き渡す"},{"t":"τῷ","l":"ὁ","k":"トー","p":"art","m":{"case":"与格","number":"単数","gender":"男性"},"g":"その"},{"t":"Σατανᾷ","l":"Σατανᾶς","k":"サタナ","p":"noun","m":{"case":"与格","number":"単数","gender":"男性"}},{"t":"ἵνα","l":"ἵνα","k":"ヒナ","p":"conj","g":"〜するために"},{"t":"παιδευθῶσι","l":"παιδεύω","k":"パイデウソーシン","p":"verb","m":{"person":"3人称","tense":"アオリスト","voice":"受動態","mood":"接続法"}},{"t":"μὴ","l":"μή","k":"メー","p":"adv","g":"〜ない"},{"t":"βλασφημεῖν","l":"βλασφημέω","k":"ブラスフェーメイン","p":"verb","m":{"tense":"現在","voice":"能動態","mood":"不定詞"}}]}]